Workbook

Sheet Daily Transactions
A1: Date | B1: Item/Description | C1: Amount | D1: Mode | E1: Remarks/Vendors | F1: Month | G1: Paid/Unpaid | H1: Paid By | I1: Payment Date | J1: Category | K1: ID | L1: Adv Check
A2: 45679 | B2: Electricity | C2: 19470 | D2: Bank | F2: =TEXT(A2,"MM-YYYY") -> 01-2025 | G2: Paid | H2: Sameer | J2: =VLOOKUP(B2,Table3[#All],2,0) -> Fixed Maintance | K2: =TEXT(ROW(), "0000") -> 0002 | M2: Paid
A3: 45679 | B3: Sales | C3: 19422 | D3: Wallet | F3: =TEXT(A3,"MM-YYYY") -> 01-2025 | J3: =VLOOKUP(B3,Table3[#All],2,0) -> Sales | K3: =TEXT(ROW(), "0000") -> 0003 | M3: Unpaid
A4: 45679 | B4: Chicken | C4: 5627 | D4: Bank | E4: Golden | F4: =TEXT(A4,"MM-YYYY") -> 01-2025 | G4: Paid | H4: Sameer | J4: =VLOOKUP(B4,Table3[#All],2,0) -> Inventory | K4: =TEXT(ROW(), "0000") -> 0004
A5: 45679 | B5: Sales | C5: 4759 | D5: Cash | F5: =TEXT(A5,"MM-YYYY") -> 01-2025 | J5: =VLOOKUP(B5,Table3[#All],2,0) -> Sales | K5: =TEXT(ROW(), "0000") -> 0005
A6: 45679 | B6: Grocery | C6: 2801 | D6: Bank | E6: Balaji | F6: =TEXT(A6,"MM-YYYY") -> 01-2025 | G6: Paid | H6: Sameer | J6: =VLOOKUP(B6,Table3[#All],2,0) -> Inventory | K6: =TEXT(ROW(), "0000") -> 0006
A7: 45679 | B7: Sales | C7: 2183 | D7: Online Sale | F7: =TEXT(A7,"MM-YYYY") -> 01-2025 | J7: =VLOOKUP(B7,Table3[#All],2,0) -> Sales | K7: =TEXT(ROW(), "0000") -> 0007
A8: 45679 | B8: Dairy | C8: 1617 | D8: Bank | E8: Adarsh | F8: =TEXT(A8,"MM-YYYY") -> 01-2025 | G8: Paid | H8: Sameer | J8: =VLOOKUP(B8,Table3[#All],2,0) -> Inventory | K8: =TEXT(ROW(), "0000") -> 0008
A9: 45679 | B9: Sales | C9: 1314 | D9: Card | F9: =TEXT(A9,"MM-YYYY") -> 01-2025 | J9: =VLOOKUP(B9,Table3[#All],2,0) -> Sales | K9: =TEXT(ROW(), "0000") -> 0009
A10: 45679 | B10: Dairy | C10: 825 | D10: Cash | E10: Egg | F10: =TEXT(A10,"MM-YYYY") -> 01-2025 | G10: Paid | H10: Sameer | J10: =VLOOKUP(B10,Table3[#All],2,0) -> Inventory | K10: =TEXT(ROW(), "0000") -> 0010
A11: 45679 | B11: Vegetables | C11: 469 | D11: Bank | E11: Gatha | F11: =TEXT(A11,"MM-YYYY") -> 01-2025 | G11: Paid | H11: Sameer | J11: =VLOOKUP(B11,Table3[#All],2,0) -> Inventory | K11: =TEXT(ROW(), "0000") -> 0011
A12: 45679 | B12: Petrol | C12: 400 | D12: Cash | F12: =TEXT(A12,"MM-YYYY") -> 01-2025 | G12: Paid | H12: Sameer | J12: =VLOOKUP(B12,Table3[#All],2,0) -> Bike Maintance | K12: =TEXT(ROW(), "0000") -> 0012
A13: 45679 | B13: Bakery | C13: 325 | D13: Cash | F13: =TEXT(A13,"MM-YYYY") -> 01-2025 | G13: Paid | H13: Sameer | J13: =VLOOKUP(B13,Table3[#All],2,0) -> Grocery | K13: =TEXT(ROW(), "0000") -> 0013
A14: 45679 | B14: Sales | C14: 240 | D14: UPI | F14: =TEXT(A14,"MM-YYYY") -> 01-2025 | J14: =VLOOKUP(B14,Table3[#All],2,0) -> Sales | K14: =TEXT(ROW(), "0000") -> 0014
A15: 45679 | B15: Tea | C15: 129 | D15: Cash | F15: =TEXT(A15,"MM-YYYY") -> 01-2025 | G15: Paid | H15: Sameer | J15: =VLOOKUP(B15,Table3[#All],2,0) -> Staff Expenses | K15: =TEXT(ROW(), "0000") -> 0015
A16: 45679 | B16: Stationary | C16: 100 | D16: Cash | F16: =TEXT(A16,"MM-YYYY") -> 01-2025 | G16: Paid | H16: Sameer | J16: =VLOOKUP(B16,Table3[#All],2,0) -> Inventory | K16: =TEXT(ROW(), "0000") -> 0016
A17: 45679 | B17: Vegetables | C17: 90 | D17: Cash | F17: =TEXT(A17,"MM-YYYY") -> 01-2025 | G17: Paid | H17: Sameer | J17: =VLOOKUP(B17,Table3[#All],2,0) -> Inventory | K17: =TEXT(ROW(), "0000") -> 0017
A18: 45679 | B18: Electric Work | C18: 60 | D18: Cash | F18: =TEXT(A18,"MM-YYYY") -> 01-2025 | G18: Paid | H18: Sameer | J18: =VLOOKUP(B18,Table3[#All],2,0) -> Maintance | K18: =TEXT(ROW(), "0000") -> 0018
A19: 45679 | B19: Dairy | C19: 30 | D19: Cash | F19: =TEXT(A19,"MM-YYYY") -> 01-2025 | G19: Paid | H19: Sameer | J19: =VLOOKUP(B19,Table3[#All],2,0) -> Inventory | K19: =TEXT(ROW(), "0000") -> 0019
A20: 45679 | B20: Kinners | C20: 0 | D20: Cash | F20: =TEXT(A20,"MM-YYYY") -> 01-2025 | G20: Paid | H20: Sameer | J20: =VLOOKUP(B20,Table3[#All],2,0) -> Maintance | K20: =TEXT(ROW(), "0000") -> 0020
A21: 45680 | B21: Sales | C21: 10553 | D21: Wallet | F21: =TEXT(A21,"MM-YYYY") -> 01-2025 | J21: =VLOOKUP(B21,Table3[#All],2,0) -> Sales | K21: =TEXT(ROW(), "0000") -> 0021
A22: 45680 | B22: Chicken | C22: 6577 | D22: Bank | E22: Pita Bread | F22: =TEXT(A22,"MM-YYYY") -> 01-2025 | G22: Paid | H22: Sameer | J22: =VLOOKUP(B22,Table3[#All],2,0) -> Inventory | K22: =TEXT(ROW(), "0000") -> 0022
A23: 45680 | B23: Grocery | C23: 2540 | D23: Bank | F23: =TEXT(A23,"MM-YYYY") -> 01-2025 | G23: Paid | H23: Sameer | J23: =VLOOKUP(B23,Table3[#All],2,0) -> Inventory | K23: =TEXT(ROW(), "0000") -> 0023
A24: 45680 | B24: Sales | C24: 2410 | D24: Cash | F24: =TEXT(A24,"MM-YYYY") -> 01-2025 | J24: =VLOOKUP(B24,Table3[#All],2,0) -> Sales | K24: =TEXT(ROW(), "0000") -> 0024
A25: 45680 | B25: Dairy | C25: 1486 | D25: Bank | E25: Newspaper | F25: =TEXT(A16,"MM-YYYY") -> 01-2025 | G25: Paid | H25: Sameer | J25: =VLOOKUP(B25,Table3[#All],2,0) -> Inventory | K25: =TEXT(ROW(), "0000") -> 0025
A26: 45680 | B26: Mutton | C26: 1480 | D26: Cash | E26: Papaya | F26: =TEXT(A17,"MM-YYYY") -> 01-2025 | G26: Paid | H26: Sameer | J26: =VLOOKUP(B26,Table3[#All],2,0) -> Inventory | K26: =TEXT(ROW(), "0000") -> 0026
A27: 45680 | B27: Vegetables | C27: 680 | D27: Bank | F27: =TEXT(A18,"MM-YYYY") -> 01-2025 | G27: Paid | H27: Sameer | J27: =VLOOKUP(B27,Table3[#All],2,0) -> Inventory | K27: =TEXT(ROW(), "0000") -> 0027
A28: 45680 | B28: Sales | C28: 467 | D28: Online Sale | E28: Milk | F28: =TEXT(A19,"MM-YYYY") -> 01-2025 | J28: =VLOOKUP(B28,Table3[#All],2,0) -> Sales | K28: =TEXT(ROW(), "0000") -> 0028
A29: 45680 | B29: Maintenance | C29: 350 | D29: Cash | F29: =TEXT(A20,"MM-YYYY") -> 01-2025 | G29: Paid | H29: Sameer | J29: =VLOOKUP(B29,Table3[#All],2,0) -> Maintance | K29: =TEXT(ROW(), "0000") -> 0029
A30: 45680 | B30: Bakery | C30: 160 | D30: Cash | F30: =TEXT(A21,"MM-YYYY") -> 01-2025 | G30: Paid | H30: Sameer | J30: =VLOOKUP(B30,Table3[#All],2,0) -> Grocery | K30: =TEXT(ROW(), "0000") -> 0030
A31: 45680 | B31: Tea | C31: 120 | D31: Cash | E31: Golden | F31: =TEXT(A22,"MM-YYYY") -> 01-2025 | G31: Paid | H31: Sameer | J31: =VLOOKUP(B31,Table3[#All],2,0) -> Staff Expenses | K31: =TEXT(ROW(), "0000") -> 0031
A32: 45681 | B32: Sales | C32: 19947 | D32: Wallet | E32: Balaji | F32: =TEXT(A23,"MM-YYYY") -> 01-2025 | J32: =VLOOKUP(B32,Table3[#All],2,0) -> Sales | K32: =TEXT(ROW(), "0000") -> 0032
A33: 45681 | B33: Advance | C33: 10300 | D33: Bank_Cash | F33: =TEXT(A24,"MM-YYYY") -> 01-2025 | G33: Paid | H33: Sameer | J33: =VLOOKUP(B33,Table3[#All],2,0) -> Salary | K33: =TEXT(ROW(), "0000") -> 0033
A34: 45681 | B34: Chicken | C34: 4243 | D34: Bank | E34: Adarsh | F34: =TEXT(A25,"MM-YYYY") -> 01-2025 | G34: Paid | H34: Sameer | J34: =VLOOKUP(B34,Table3[#All],2,0) -> Inventory | K34: =TEXT(ROW(), "0000") -> 0034
A35: 45681 | B35: Grocery | C35: 3967 | D35: Bank | E35: A1 | F35: =TEXT(A26,"MM-YYYY") -> 01-2025 | G35: Paid | H35: Sameer | J35: =VLOOKUP(B35,Table3[#All],2,0) -> Inventory | K35: =TEXT(ROW(), "0000") -> 0035
A36: 45681 | B36: Sales | C36: 3140 | D36: Cash | F36: =TEXT(A27,"MM-YYYY") -> 01-2025 | J36: =VLOOKUP(B36,Table3[#All],2,0) -> Sales | K36: =TEXT(ROW(), "0000") -> 0036
A37: 45681 | B37: Dairy | C37: 1250 | D37: Bank | E37: Adarsh | F37: =TEXT(A37,"MM-YYYY") -> 01-2025 | G37: Paid | H37: Sameer | J37: =VLOOKUP(B37,Table3[#All],2,0) -> Inventory | K37: =TEXT(ROW(), "0000") -> 0037
A38: 45681 | B38: Sales | C38: 1038 | D38: Online Sale | F38: =TEXT(A38,"MM-YYYY") -> 01-2025 | J38: =VLOOKUP(B38,Table3[#All],2,0) -> Sales | K38: =TEXT(ROW(), "0000") -> 0038
A39: 45681 | B39: Charcoal | C39: 840 | D39: Bank | E39: Gyanshweri | F39: =TEXT(A39,"MM-YYYY") -> 01-2025 | G39: Paid | H39: Sameer | J39: =VLOOKUP(B39,Table3[#All],2,0) -> Inventory | K39: =TEXT(ROW(), "0000") -> 0039
A40: 45681 | B40: Vegetables | C40: 580 | D40: Bank | F40: =TEXT(A40,"MM-YYYY") -> 01-2025 | G40: Paid | H40: Sameer | J40: =VLOOKUP(B40,Table3[#All],2,0) -> Inventory | K40: =TEXT(ROW(), "0000") -> 0040
A41: 45681 | B41: Sales | C41: 550 | D41: UPI | F41: =TEXT(A41,"MM-YYYY") -> 01-2025 | J41: =VLOOKUP(B41,Table3[#All],2,0) -> Sales | K41: =TEXT(ROW(), "0000") -> 0041
A42: 45681 | B42: Maintenance | C42: 350 | D42: Cash | E42: Sealer machine repair | F42: =TEXT(A42,"MM-YYYY") -> 01-2025 | G42: Paid | H42: Sameer | J42: =VLOOKUP(B42,Table3[#All],2,0) -> Maintance | K42: =TEXT(ROW(), "0000") -> 0042
A43: 45681 | B43: Sales | C43: 250 | D43: Card | F43: =TEXT(A43,"MM-YYYY") -> 01-2025 | J43: =VLOOKUP(B43,Table3[#All],2,0) -> Sales | K43: =TEXT(ROW(), "0000") -> 0043
A44: 45681 | B44: Tea | C44: 100 | D44: Cash | F44: =TEXT(A44,"MM-YYYY") -> 01-2025 | G44: Paid | H44: Sameer | J44: =VLOOKUP(B44,Table3[#All],2,0) -> Staff Expenses | K44: =TEXT(ROW(), "0000") -> 0044
A45: 45681 | B45: Kinners | C45: 40 | D45: Cash | F45: =TEXT(A45,"MM-YYYY") -> 01-2025 | G45: Paid | H45: Sameer | J45: =VLOOKUP(B45,Table3[#All],2,0) -> Maintance | K45: =TEXT(ROW(), "0000") -> 0045
A46: 45682 | B46: Sales | C46: 26464 | D46: Wallet | F46: =TEXT(A46,"MM-YYYY") -> 01-2025 | J46: =VLOOKUP(B46,Table3[#All],2,0) -> Sales | K46: =TEXT(ROW(), "0000") -> 0046
A47: 45682 | B47: Gas | C47: 9100 | D47: Bank | F47: =TEXT(A47,"MM-YYYY") -> 01-2025 | G47: Paid | H47: Sameer | J47: =VLOOKUP(B47,Table3[#All],2,0) -> Fixed Maintance | K47: =TEXT(ROW(), "0000") -> 0047
A48: 45682 | B48: Sales | C48: 5660 | D48: Cash | F48: =TEXT(A48,"MM-YYYY") -> 01-2025 | J48: =VLOOKUP(B48,Table3[#All],2,0) -> Sales | K48: =TEXT(ROW(), "0000") -> 0048
A49: 45682 | B49: Sales | C49: 3477 | D49: Online Sale | F49: =TEXT(A49,"MM-YYYY") -> 01-2025 | J49: =VLOOKUP(B49,Table3[#All],2,0) -> Sales | K49: =TEXT(ROW(), "0000") -> 0049
A50: 45682 | B50: Sales | C50: 3400 | D50: UPI | F50: =TEXT(A50,"MM-YYYY") -> 01-2025 | J50: =VLOOKUP(B50,Table3[#All],2,0) -> Sales | K50: =TEXT(ROW(), "0000") -> 0050
A51: 45682 | B51: Grocery | C51: 3373 | D51: Bank | E51: Balaji | F51: =TEXT(A51,"MM-YYYY") -> 01-2025 | G51: Paid | H51: Sameer | J51: =VLOOKUP(B51,Table3[#All],2,0) -> Inventory | K51: =TEXT(ROW(), "0000") -> 0051
A52: 45682 | B52: Disposable | C52: 3095 | D52: Bank | E52: Anand | F52: =TEXT(A52,"MM-YYYY") -> 01-2025 | G52: Paid | H52: Sameer | J52: =VLOOKUP(B52,Table3[#All],2,0) -> Inventory | K52: =TEXT(ROW(), "0000") -> 0052
A53: 45682 | B53: Chicken | C53: 1928 | D53: Bank | E53: Golden | F53: =TEXT(A53,"MM-YYYY") -> 01-2025 | G53: Paid | H53: Sameer | J53: =VLOOKUP(B53,Table3[#All],2,0) -> Inventory | K53: =TEXT(ROW(), "0000") -> 0053
A54: 45682 | B54: Beverages | C54: 1764 | D54: Cash | E54: Cold Drinks | F54: =TEXT(A54,"MM-YYYY") -> 01-2025 | G54: Paid | H54: Sameer | J54: =VLOOKUP(B54,Table3[#All],2,0) -> Grocery | K54: =TEXT(ROW(), "0000") -> 0054
A55: 45682 | B55: Dairy | C55: 1296 | D55: Bank | F55: =TEXT(A55,"MM-YYYY") -> 01-2025 | G55: Paid | H55: Sameer | J55: =VLOOKUP(B55,Table3[#All],2,0) -> Inventory | K55: =TEXT(ROW(), "0000") -> 0055
A56: 45682 | B56: Beverages | C56: 1200 | D56: Cash | E56: Water Bottel | F56: =TEXT(A56,"MM-YYYY") -> 01-2025 | G56: Paid | H56: Sameer | J56: =VLOOKUP(B56,Table3[#All],2,0) -> Grocery | K56: =TEXT(ROW(), "0000") -> 0056
A57: 45682 | B57: Electric Work | C57: 635 | D57: Cash | F57: =TEXT(A57,"MM-YYYY") -> 01-2025 | G57: Paid | H57: Sameer | J57: =VLOOKUP(B57,Table3[#All],2,0) -> Maintance | K57: =TEXT(ROW(), "0000") -> 0057
A58: 45682 | B58: Vegetables | C58: 570 | D58: Bank | F58: =TEXT(A58,"MM-YYYY") -> 01-2025 | G58: Paid | H58: Sameer | J58: =VLOOKUP(B58,Table3[#All],2,0) -> Inventory | K58: =TEXT(ROW(), "0000") -> 0058
A59: 45682 | B59: Restaurant New Inventory | C59: 200 | D59: Cash | E59: Mobile Stand | F59: =TEXT(A59,"MM-YYYY") -> 01-2025 | G59: Paid | H59: Sameer | J59: =VLOOKUP(B59,Table3[#All],2,0) -> New Inventory | K59: =TEXT(ROW(), "0000") -> 0059
A60: 45682 | B60: Tea | C60: 121 | D60: Cash | F60: =TEXT(A60,"MM-YYYY") -> 01-2025 | G60: Paid | H60: Sameer | J60: =VLOOKUP(B60,Table3[#All],2,0) -> Staff Expenses | K60: =TEXT(ROW(), "0000") -> 0060
A61: 45682 | B61: Dairy | C61: 40 | D61: Cash | E61: Milk | F61: =TEXT(A61,"MM-YYYY") -> 01-2025 | G61: Paid | H61: Sameer | J61: =VLOOKUP(B61,Table3[#All],2,0) -> Inventory | K61: =TEXT(ROW(), "0000") -> 0061
A62: 45683 | B62: Sales | C62: 33268 | D62: Wallet | F62: =TEXT(A62,"MM-YYYY") -> 01-2025 | J62: =VLOOKUP(B62,Table3[#All],2,0) -> Sales | K62: =TEXT(ROW(), "0000") -> 0062
A63: 45683 | B63: Chicken | C63: 8385 | D63: Bank | F63: =TEXT(A63,"MM-YYYY") -> 01-2025 | G63: Paid | H63: Sameer | J63: =VLOOKUP(B63,Table3[#All],2,0) -> Inventory | K63: =TEXT(ROW(), "0000") -> 0063
A64: 45683 | B64: Sales | C64: 3979 | D64: Cash | F64: =TEXT(A64,"MM-YYYY") -> 01-2025 | J64: =VLOOKUP(B64,Table3[#All],2,0) -> Sales | K64: =TEXT(ROW(), "0000") -> 0064
A65: 45683 | B65: Grocery | C65: 3000 | D65: Bank | F65: =TEXT(A65,"MM-YYYY") -> 01-2025 | G65: Paid | H65: Sameer | J65: =VLOOKUP(B65,Table3[#All],2,0) -> Inventory | K65: =TEXT(ROW(), "0000") -> 0065
A66: 45683 | B66: Advance | C66: 2700 | D66: Bank_Cash | E66: Disposable payment Umesh sir | F66: =TEXT(A66,"MM-YYYY") -> 01-2025 | G66: Paid | H66: Sameer | J66: =VLOOKUP(B66,Table3[#All],2,0) -> Salary | K66: =TEXT(ROW(), "0000") -> 0066
A67: 45683 | B67: Dairy | C67: 2486 | D67: Bank | F67: =TEXT(A67,"MM-YYYY") -> 01-2025 | G67: Paid | H67: Sameer | J67: =VLOOKUP(B67,Table3[#All],2,0) -> Inventory | K67: =TEXT(ROW(), "0000") -> 0067
A68: 45683 | B68: Sales | C68: 1658 | D68: Online Sale | F68: =TEXT(A68,"MM-YYYY") -> 01-2025 | J68: =VLOOKUP(B68,Table3[#All],2,0) -> Sales | K68: =TEXT(ROW(), "0000") -> 0068
A69: 45683 | B69: Sales | C69: 1620 | D69: Card | F69: =TEXT(A69,"MM-YYYY") -> 01-2025 | J69: =VLOOKUP(B69,Table3[#All],2,0) -> Sales | K69: =TEXT(ROW(), "0000") -> 0069
A70: 45683 | B70: Dairy | C70: 1113 | D70: Cash | E70: Egg | F70: =TEXT(A70,"MM-YYYY") -> 01-2025 | G70: Paid | H70: Sameer | J70: =VLOOKUP(B70,Table3[#All],2,0) -> Inventory | K70: =TEXT(ROW(), "0000") -> 0070
A71: 45683 | B71: Sales | C71: 950 | D71: Zomato Pay | F71: =TEXT(A71,"MM-YYYY") -> 01-2025 | J71: =VLOOKUP(B71,Table3[#All],2,0) -> Sales | K71: =TEXT(ROW(), "0000") -> 0071
A72: 45683 | B72: Vegetables | C72: 655 | D72: Bank | F72: =TEXT(A72,"MM-YYYY") -> 01-2025 | G72: Paid | H72: Sameer | J72: =VLOOKUP(B72,Table3[#All],2,0) -> Inventory | K72: =TEXT(ROW(), "0000") -> 0072
A73: 45683 | B73: Bakery | C73: 485 | D73: Cash | E73: Pita Bread | F73: =TEXT(A73,"MM-YYYY") -> 01-2025 | G73: Paid | H73: Sameer | J73: =VLOOKUP(B73,Table3[#All],2,0) -> Grocery | K73: =TEXT(ROW(), "0000") -> 0073
A74: 45683 | B74: Momos | C74: 420 | D74: Cash | F74: =TEXT(A74,"MM-YYYY") -> 01-2025 | G74: Paid | H74: Sameer | J74: =VLOOKUP(B74,Table3[#All],2,0) -> Inventory | K74: =TEXT(ROW(), "0000") -> 0074
A75: 45683 | B75: Sales | C75: 320 | D75: UPI | F75: =TEXT(A75,"MM-YYYY") -> 01-2025 | J75: =VLOOKUP(B75,Table3[#All],2,0) -> Sales | K75: =TEXT(ROW(), "0000") -> 0075
A76: 45683 | B76: Electric Work | C76: 185 | D76: Cash | F76: =TEXT(A76,"MM-YYYY") -> 01-2025 | G76: Paid | H76: Sameer | J76: =VLOOKUP(B76,Table3[#All],2,0) -> Maintance | K76: =TEXT(ROW(), "0000") -> 0076
A77: 45683 | B77: Tea | C77: 96 | D77: Cash | F77: =TEXT(A77,"MM-YYYY") -> 01-2025 | G77: Paid | H77: Sameer | J77: =VLOOKUP(B77,Table3[#All],2,0) -> Staff Expenses | K77: =TEXT(ROW(), "0000") -> 0077
A78: 45683 | B78: Beverages | C78: 40 | D78: Cash | E78: Soda | F78: =TEXT(A78,"MM-YYYY") -> 01-2025 | G78: Paid | H78: Sameer | J78: =VLOOKUP(B78,Table3[#All],2,0) -> Grocery | K78: =TEXT(ROW(), "0000") -> 0078
A79: 45683 | B79: Dairy | C79: 40 | D79: Cash | E79: Milk | F79: =TEXT(A79,"MM-YYYY") -> 01-2025 | G79: Paid | H79: Sameer | J79: =VLOOKUP(B79,Table3[#All],2,0) -> Inventory | K79: =TEXT(ROW(), "0000") -> 0079
A80: 45684 | B80: Sales | C80: 15670 | D80: Wallet | F80: =TEXT(A80,"MM-YYYY") -> 01-2025 | J80: =VLOOKUP(B80,Table3[#All],2,0) -> Sales | K80: =TEXT(ROW(), "0000") -> 0080
A81: 45684 | B81: Chicken | C81: 3997 | D81: Bank | F81: =TEXT(A81,"MM-YYYY") -> 01-2025 | G81: Paid | H81: Sameer | J81: =VLOOKUP(B81,Table3[#All],2,0) -> Inventory | K81: =TEXT(ROW(), "0000") -> 0081
A82: 45684 | B82: Sales | C82: 2540 | D82: Cash | F82: =TEXT(A82,"MM-YYYY") -> 01-2025 | J82: =VLOOKUP(B82,Table3[#All],2,0) -> Sales | K82: =TEXT(ROW(), "0000") -> 0082
A83: 45684 | B83: Sales | C83: 1500 | D83: Card | F83: =TEXT(A83,"MM-YYYY") -> 01-2025 | J83: =VLOOKUP(B83,Table3[#All],2,0) -> Sales | K83: =TEXT(ROW(), "0000") -> 0083
A84: 45684 | B84: Dairy | C84: 1135 | D84: Bank | F84: =TEXT(A84,"MM-YYYY") -> 01-2025 | G84: Paid | H84: Sameer | J84: =VLOOKUP(B84,Table3[#All],2,0) -> Inventory | K84: =TEXT(ROW(), "0000") -> 0084
A85: 45684 | B85: Charcoal | C85: 840 | D85: Bank | F85: =TEXT(A85,"MM-YYYY") -> 01-2025 | G85: Paid | H85: Sameer | J85: =VLOOKUP(B85,Table3[#All],2,0) -> Inventory | K85: =TEXT(ROW(), "0000") -> 0085
A86: 45684 | B86: Sales | C86: 780 | D86: Zomato Pay | F86: =TEXT(A86,"MM-YYYY") -> 01-2025 | J86: =VLOOKUP(B86,Table3[#All],2,0) -> Sales | K86: =TEXT(ROW(), "0000") -> 0086
A87: 45684 | B87: Sales | C87: 686 | D87: Online Sale | F87: =TEXT(A87,"MM-YYYY") -> 01-2025 | J87: =VLOOKUP(B87,Table3[#All],2,0) -> Sales | K87: =TEXT(ROW(), "0000") -> 0087
A88: 45684 | B88: Dairy | C88: 650 | D88: Cash | E88: Soya Chaap | F88: =TEXT(A88,"MM-YYYY") -> 01-2025 | G88: Paid | H88: Sameer | J88: =VLOOKUP(B88,Table3[#All],2,0) -> Inventory | K88: =TEXT(ROW(), "0000") -> 0088
A89: 45684 | B89: Sales | C89: 614 | D89: UPI | F89: =TEXT(A89,"MM-YYYY") -> 01-2025 | J89: =VLOOKUP(B89,Table3[#All],2,0) -> Sales | K89: =TEXT(ROW(), "0000") -> 0089
A90: 45684 | B90: Vegetables | C90: 526 | D90: Bank | F90: =TEXT(A90,"MM-YYYY") -> 01-2025 | G90: Paid | H90: Sameer | J90: =VLOOKUP(B90,Table3[#All],2,0) -> Inventory | K90: =TEXT(ROW(), "0000") -> 0090
A91: 45684 | B91: Civil Work | C91: 450 | D91: Cash | E91: Cement | F91: =TEXT(A91,"MM-YYYY") -> 01-2025 | G91: Paid | H91: Sameer | J91: =VLOOKUP(B91,Table3[#All],2,0) -> Maintance | K91: =TEXT(ROW(), "0000") -> 0091
A92: 45684 | B92: Tea | C92: 125 | D92: Cash | F92: =TEXT(A92,"MM-YYYY") -> 01-2025 | G92: Paid | H92: Sameer | J92: =VLOOKUP(B92,Table3[#All],2,0) -> Staff Expenses | K92: =TEXT(ROW(), "0000") -> 0092
A93: 45684 | B93: Vegetables | C93: 35 | D93: Cash | E93: Mint | F93: =TEXT(A93,"MM-YYYY") -> 01-2025 | G93: Paid | H93: Sameer | J93: =VLOOKUP(B93,Table3[#All],2,0) -> Inventory | K93: =TEXT(ROW(), "0000") -> 0093
A94: 45684 | B94: Kinners | C94: 30 | D94: Cash | F94: =TEXT(A94,"MM-YYYY") -> 01-2025 | G94: Paid | H94: Sameer | J94: =VLOOKUP(B94,Table3[#All],2,0) -> Maintance | K94: =TEXT(ROW(), "0000") -> 0094
A95: 45685 | B95: Sales | C95: 13162 | D95: Wallet | F95: =TEXT(A95,"MM-YYYY") -> 01-2025 | J95: =VLOOKUP(B95,Table3[#All],2,0) -> Sales | K95: =TEXT(ROW(), "0000") -> 0095
A96: 45685 | B96: Grocery | C96: 4708 | D96: Bank | F96: =TEXT(A96,"MM-YYYY") -> 01-2025 | G96: Paid | H96: Sameer | J96: =VLOOKUP(B96,Table3[#All],2,0) -> Inventory | K96: =TEXT(ROW(), "0000") -> 0096
A97: 45685 | B97: Chicken | C97: 4204 | D97: Bank | F97: =TEXT(A97,"MM-YYYY") -> 01-2025 | G97: Paid | H97: Sameer | J97: =VLOOKUP(B97,Table3[#All],2,0) -> Inventory | K97: =TEXT(ROW(), "0000") -> 0097
A98: 45685 | B98: Sales | C98: 2415 | D98: Cash | F98: =TEXT(A98,"MM-YYYY") -> 01-2025 | J98: =VLOOKUP(B98,Table3[#All],2,0) -> Sales | K98: =TEXT(ROW(), "0000") -> 0098
A99: 45685 | B99: Sales | C99: 1570 | D99: Card | F99: =TEXT(A99,"MM-YYYY") -> 01-2025 | J99: =VLOOKUP(B99,Table3[#All],2,0) -> Sales | K99: =TEXT(ROW(), "0000") -> 0099
A100: 45685 | B100: Dairy | C100: 1533 | D100: Bank | F100: =TEXT(A100,"MM-YYYY") -> 01-2025 | G100: Paid | H100: Sameer | J100: =VLOOKUP(B100,Table3[#All],2,0) -> Inventory | K100: =TEXT(ROW(), "0000") -> 0100
...

Sheet Summary
D1: Cash | E1: Bank_Cash | F1: Bank
H2: =SUM(Summary[Gross ]) -> 1366741
A3: Date | B3: Total Sale | C3: Total Expense | D3: Cash Expense | E3: Bank_Cash_Expenses | F3: Bank_Expenses | G3: Gross | H3: Opening Cash | I3: Cash Sales | J3: Remaining Cash (Bank_Cash) | K3: Bank Cash To Give | L3: Cash Shortage | M3: ID
A4: 45658 | B4: =SUMIFS('Daily Transactions'!C:C,'Daily Transactions'!A:A,$A4,'Daily Transactions'!B:B,"Sales") -> 0 | C4: =SUMIFS('Daily Transactions'!C:C,'Daily Transactions'!A:A,$A4,'Daily Transactions'!B:B,"<>Sales") -> 0 | D4: =SUMIFS('Daily Transactions'!C:C,'Daily Transactions'!A:A,$A4,'Daily Transactions'!B:B,"<>Sales",'Daily Transactions'!D:D,"Cash") -> 0 | E4: =SUMIFS('Daily Transactions'!C:C,'Daily Transactions'!A:A,$A4,'Daily Transactions'!B:B,"<>Sales",'Daily Transactions'!D:D,"Bank_Cash") -> 0 | F4: =SUMIFS('Daily Transactions'!C:C,'Daily Transactions'!A:A,$A4,'Daily Transactions'!B:B,"<>Sales",'Daily Transactions'!D:D,"Bank") -> 0 | G4: =B4-C4 -> 0 | H4: 0 | I4: =SUMIFS('Daily Transactions'!C:C,'Daily Transactions'!A:A,$A4,'Daily Transactions'!B:B,"Sales",'Daily Transactions'!D:D,"Cash") -> 0 | J4: =(H4+I4)-(D4+E4) -> 0 | L4: =SUMIFS('Daily Transactions'!C:C,'Daily Transactions'!A:A,$A4,'Daily Transactions'!B:B,"Cash Shortage",'Daily Transactions'!D:D,"Cash") -> 0
A5: =A4+1 -> 45659 | B5: =SUMIFS('Daily Transactions'!C:C,'Daily Transactions'!A:A,$A5,'Daily Transactions'!B:B,"Sales") -> 0 | C5: =SUMIFS('Daily Transactions'!C:C,'Daily Transactions'!A:A,$A5,'Daily Transactions'!B:B,"<>Sales") -> 0 | D5: =SUMIFS('Daily Transactions'!C:C,'Daily Transactions'!A:A,$A5,'Daily Transactions'!B:B,"<>Sales",'Daily Transactions'!D:D,"Cash") -> 0 | E5: =SUMIFS('Daily Transactions'!C:C,'Daily Transactions'!A:A,$A5,'Daily Transactions'!B:B,"<>Sales",'Daily Transactions'!D:D,"Bank_Cash") -> 0 | F5: =SUMIFS('Daily Transactions'!C:C,'Daily Transactions'!A:A,$A5,'Daily Transactions'!B:B,"<>Sales",'Daily Transactions'!D:D,"Bank") -> 0 | G5: =B5-C5 -> 0 | H5: =J4 -> 0 | I5: =SUMIFS('Daily Transactions'!C:C,'Daily Transactions'!A:A,$A5,'Daily Transactions'!B:B,"Sales",'Daily Transactions'!D:D,"Cash") -> 0 | J5: =(H5+I5)-(D5+E5) -> 0 | L5: =SUMIFS('Daily Transactions'!C:C,'Daily Transactions'!A:A,$A5,'Daily Transactions'!B:B,"Cash Shortage",'Daily Transactions'!D:D,"Cash") -> 0
A6: =A5+1 -> 45660 | B6: =SUMIFS('Daily Transactions'!C:C,'Daily Transactions'!A:A,$A6,'Daily Transactions'!B:B,"Sales") -> 0 | C6: =SUMIFS('Daily Transactions'!C:C,'Daily Transactions'!A:A,$A6,'Daily Transactions'!B:B,"<>Sales") -> 0 | D6: =SUMIFS('Daily Transactions'!C:C,'Daily Transactions'!A:A,$A6,'Daily Transactions'!B:B,"<>Sales",'Daily Transactions'!D:D,"Cash") -> 0 | E6: =SUMIFS('Daily Transactions'!C:C,'Daily Transactions'!A:A,$A6,'Daily Transactions'!B:B,"<>Sales",'Daily Transactions'!D:D,"Bank_Cash") -> 0 | F6: =SUMIFS('Daily Transactions'!C:C,'Daily Transactions'!A:A,$A6,'Daily Transactions'!B:B,"<>Sales",'Daily Transactions'!D:D,"Bank") -> 0 | G6: =B6-C6 -> 0 | H6: =J5 -> 0 | I6: =SUMIFS('Daily Transactions'!C:C,'Daily Transactions'!A:A,$A6,'Daily Transactions'!B:B,"Sales",'Daily Transactions'!D:D,"Cash") -> 0 | J6: =(H6+I6)-(D6+E6) -> 0 | L6: =SUMIFS('Daily Transactions'!C:C,'Daily Transactions'!A:A,$A6,'Daily Transactions'!B:B,"Cash Shortage",'Daily Transactions'!D:D,"Cash") -> 0
A7: =A6+1 -> 45661 | B7: =SUMIFS('Daily Transactions'!C:C,'Daily Transactions'!A:A,$A7,'Daily Transactions'!B:B,"Sales") -> 0 | C7: =SUMIFS('Daily Transactions'!C:C,'Daily Transactions'!A:A,$A7,'Daily Transactions'!B:B,"<>Sales") -> 0 | D7: =SUMIFS('Daily Transactions'!C:C,'Daily Transactions'!A:A,$A7,'Daily Transactions'!B:B,"<>Sales",'Daily Transactions'!D:D,"Cash") -> 0 | E7: =SUMIFS('Daily Transactions'!C:C,'Daily Transactions'!A:A,$A7,'Daily Transactions'!B:B,"<>Sales",'Daily Transactions'!D:D,"Bank_Cash") -> 0 | F7: =SUMIFS('Daily Transactions'!C:C,'Daily Transactions'!A:A,$A7,'Daily Transactions'!B:B,"<>Sales",'Daily Transactions'!D:D,"Bank") -> 0 | G7: =B7-C7 -> 0 | H7: =J6 -> 0 | I7: =SUMIFS('Daily Transactions'!C:C,'Daily Transactions'!A:A,$A7,'Daily Transactions'!B:B,"Sales",'Daily Transactions'!D:D,"Cash") -> 0 | J7: =(H7+I7)-(D7+E7) -> 0 | L7: =SUMIFS('Daily Transactions'!C:C,'Daily Transactions'!A:A,$A7,'Daily Transactions'!B:B,"Cash Shortage",'Daily Transactions'!D:D,"Cash") -> 0
A8: =A7+1 -> 45662 | B8: =SUMIFS('Daily Transactions'!C:C,'Daily Transactions'!A:A,$A8,'Daily Transactions'!B:B,"Sales") -> 0 | C8: =SUMIFS('Daily Transactions'!C:C,'Daily Transactions'!A:A,$A8,'Daily Transactions'!B:B,"<>Sales") -> 0 | D8: =SUMIFS('Daily Transactions'!C:C,'Daily Transactions'!A:A,$A8,'Daily Transactions'!B:B,"<>Sales",'Daily Transactions'!D:D,"Cash") -> 0 | E8: =SUMIFS('Daily Transactions'!C:C,'Daily Transactions'!A:A,$A8,'Daily Transactions'!B:B,"<>Sales",'Daily Transactions'!D:D,"Bank_Cash") -> 0 | F8: =SUMIFS('Daily Transactions'!C:C,'Daily Transactions'!A:A,$A8,'Daily Transactions'!B:B,"<>Sales",'Daily Transactions'!D:D,"Bank") -> 0 | G8: =B8-C8 -> 0 | H8: =J7 -> 0 | I8: =SUMIFS('Daily Transactions'!C:C,'Daily Transactions'!A:A,$A8,'Daily Transactions'!B:B,"Sales",'Daily Transactions'!D:D,"Cash") -> 0 | J8: =(H8+I8)-(D8+E8) -> 0 | L8: =SUMIFS('Daily Transactions'!C:C,'Daily Transactions'!A:A,$A8,'Daily Transactions'!B:B,"Cash Shortage",'Daily Transactions'!D:D,"Cash") -> 0
A9: =A8+1 -> 45663 | B9: =SUMIFS('Daily Transactions'!C:C,'Daily Transactions'!A:A,$A9,'Daily Transactions'!B:B,"Sales") -> 0 | C9: =SUMIFS('Daily Transactions'!C:C,'Daily Transactions'!A:A,$A9,'Daily Transactions'!B:B,"<>Sales") -> 0 | D9: =SUMIFS('Daily Transactions'!C:C,'Daily Transactions'!A:A,$A9,'Daily Transactions'!B:B,"<>Sales",'Daily Transactions'!D:D,"Cash") -> 0 | E9: =SUMIFS('Daily Transactions'!C:C,'Daily Transactions'!A:A,$A9,'Daily Transactions'!B:B,"<>Sales",'Daily Transactions'!D:D,"Bank_Cash") -> 0 | F9: =SUMIFS('Daily Transactions'!C:C,'Daily Transactions'!A:A,$A9,'Daily Transactions'!B:B,"<>Sales",'Daily Transactions'!D:D,"Bank") -> 0 | G9: =B9-C9 -> 0 | H9: =J8 -> 0 | I9: =SUMIFS('Daily Transactions'!C:C,'Daily Transactions'!A:A,$A9,'Daily Transactions'!B:B,"Sales",'Daily Transactions'!D:D,"Cash") -> 0 | J9: =(H9+I9)-(D9+E9) -> 0 | L9: =SUMIFS('Daily Transactions'!C:C,'Daily Transactions'!A:A,$A9,'Daily Transactions'!B:B,"Cash Shortage",'Daily Transactions'!D:D,"Cash") -> 0
A10: =A9+1 -> 45664 | B10: =SUMIFS('Daily Transactions'!C:C,'Daily Transactions'!A:A,$A10,'Daily Transactions'!B:B,"Sales") -> 0 | C10: =SUMIFS('Daily Transactions'!C:C,'Daily Transactions'!A:A,$A10,'Daily Transactions'!B:B,"<>Sales") -> 0 | D10: =SUMIFS('Daily Transactions'!C:C,'Daily Transactions'!A:A,$A10,'Daily Transactions'!B:B,"<>Sales",'Daily Transactions'!D:D,"Cash") -> 0 | E10: =SUMIFS('Daily Transactions'!C:C,'Daily Transactions'!A:A,$A10,'Daily Transactions'!B:B,"<>Sales",'Daily Transactions'!D:D,"Bank_Cash") -> 0 | F10: =SUMIFS('Daily Transactions'!C:C,'Daily Transactions'!A:A,$A10,'Daily Transactions'!B:B,"<>Sales",'Daily Transactions'!D:D,"Bank") -> 0 | G10: =B10-C10 -> 0 | H10: =J9 -> 0 | I10: =SUMIFS('Daily Transactions'!C:C,'Daily Transactions'!A:A,$A10,'Daily Transactions'!B:B,"Sales",'Daily Transactions'!D:D,"Cash") -> 0 | J10: =(H10+I10)-(D10+E10) -> 0 | L10: =SUMIFS('Daily Transactions'!C:C,'Daily Transactions'!A:A,$A10,'Daily Transactions'!B:B,"Cash Shortage",'Daily Transactions'!D:D,"Cash") -> 0
A11: =A10+1 -> 45665 | B11: =SUMIFS('Daily Transactions'!C:C,'Daily Transactions'!A:A,$A11,'Daily Transactions'!B:B,"Sales") -> 0 | C11: =SUMIFS('Daily Transactions'!C:C,'Daily Transactions'!A:A,$A11,'Daily Transactions'!B:B,"<>Sales") -> 0 | D11: =SUMIFS('Daily Transactions'!C:C,'Daily Transactions'!A:A,$A11,'Daily Transactions'!B:B,"<>Sales",'Daily Transactions'!D:D,"Cash") -> 0 | E11: =SUMIFS('Daily Transactions'!C:C,'Daily Transactions'!A:A,$A11,'Daily Transactions'!B:B,"<>Sales",'Daily Transactions'!D:D,"Bank_Cash") -> 0 | F11: =SUMIFS('Daily Transactions'!C:C,'Daily Transactions'!A:A,$A11,'Daily Transactions'!B:B,"<>Sales",'Daily Transactions'!D:D,"Bank") -> 0 | G11: =B11-C11 -> 0 | H11: =J10 -> 0 | I11: =SUMIFS('Daily Transactions'!C:C,'Daily Transactions'!A:A,$A11,'Daily Transactions'!B:B,"Sales",'Daily Transactions'!D:D,"Cash") -> 0 | J11: =(H11+I11)-(D11+E11) -> 0 | L11: =SUMIFS('Daily Transactions'!C:C,'Daily Transactions'!A:A,$A11,'Daily Transactions'!B:B,"Cash Shortage",'Daily Transactions'!D:D,"Cash") -> 0
A12: =A11+1 -> 45666 | B12: =SUMIFS('Daily Transactions'!C:C,'Daily Transactions'!A:A,$A12,'Daily Transactions'!B:B,"Sales") -> 0 | C12: =SUMIFS('Daily Transactions'!C:C,'Daily Transactions'!A:A,$A12,'Daily Transactions'!B:B,"<>Sales") -> 0 | D12: =SUMIFS('Daily Transactions'!C:C,'Daily Transactions'!A:A,$A12,'Daily Transactions'!B:B,"<>Sales",'Daily Transactions'!D:D,"Cash") -> 0 | E12: =SUMIFS('Daily Transactions'!C:C,'Daily Transactions'!A:A,$A12,'Daily Transactions'!B:B,"<>Sales",'Daily Transactions'!D:D,"Bank_Cash") -> 0 | F12: =SUMIFS('Daily Transactions'!C:C,'Daily Transactions'!A:A,$A12,'Daily Transactions'!B:B,"<>Sales",'Daily Transactions'!D:D,"Bank") -> 0 | G12: =B12-C12 -> 0 | H12: =J11 -> 0 | I12: =SUMIFS('Daily Transactions'!C:C,'Daily Transactions'!A:A,$A12,'Daily Transactions'!B:B,"Sales",'Daily Transactions'!D:D,"Cash") -> 0 | J12: =(H12+I12)-(D12+E12) -> 0 | L12: =SUMIFS('Daily Transactions'!C:C,'Daily Transactions'!A:A,$A12,'Daily Transactions'!B:B,"Cash Shortage",'Daily Transactions'!D:D,"Cash") -> 0
A13: =A12+1 -> 45667 | B13: =SUMIFS('Daily Transactions'!C:C,'Daily Transactions'!A:A,$A13,'Daily Transactions'!B:B,"Sales") -> 0 | C13: =SUMIFS('Daily Transactions'!C:C,'Daily Transactions'!A:A,$A13,'Daily Transactions'!B:B,"<>Sales") -> 0 | D13: =SUMIFS('Daily Transactions'!C:C,'Daily Transactions'!A:A,$A13,'Daily Transactions'!B:B,"<>Sales",'Daily Transactions'!D:D,"Cash") -> 0 | E13: =SUMIFS('Daily Transactions'!C:C,'Daily Transactions'!A:A,$A13,'Daily Transactions'!B:B,"<>Sales",'Daily Transactions'!D:D,"Bank_Cash") -> 0 | F13: =SUMIFS('Daily Transactions'!C:C,'Daily Transactions'!A:A,$A13,'Daily Transactions'!B:B,"<>Sales",'Daily Transactions'!D:D,"Bank") -> 0 | G13: =B13-C13 -> 0 | H13: =J12 -> 0 | I13: =SUMIFS('Daily Transactions'!C:C,'Daily Transactions'!A:A,$A13,'Daily Transactions'!B:B,"Sales",'Daily Transactions'!D:D,"Cash") -> 0 | J13: =(H13+I13)-(D13+E13) -> 0 | L13: =SUMIFS('Daily Transactions'!C:C,'Daily Transactions'!A:A,$A13,'Daily Transactions'!B:B,"Cash Shortage",'Daily Transactions'!D:D,"Cash") -> 0
A14: =A13+1 -> 45668 | B14: =SUMIFS('Daily Transactions'!C:C,'Daily Transactions'!A:A,$A14,'Daily Transactions'!B:B,"Sales") -> 0 | C14: =SUMIFS('Daily Transactions'!C:C,'Daily Transactions'!A:A,$A14,'Daily Transactions'!B:B,"<>Sales") -> 0 | D14: =SUMIFS('Daily Transactions'!C:C,'Daily Transactions'!A:A,$A14,'Daily Transactions'!B:B,"<>Sales",'Daily Transactions'!D:D,"Cash") -> 0 | E14: =SUMIFS('Daily Transactions'!C:C,'Daily Transactions'!A:A,$A14,'Daily Transactions'!B:B,"<>Sales",'Daily Transactions'!D:D,"Bank_Cash") -> 0 | F14: =SUMIFS('Daily Transactions'!C:C,'Daily Transactions'!A:A,$A14,'Daily Transactions'!B:B,"<>Sales",'Daily Transactions'!D:D,"Bank") -> 0 | G14: =B14-C14 -> 0 | H14: =J13 -> 0 | I14: =SUMIFS('Daily Transactions'!C:C,'Daily Transactions'!A:A,$A14,'Daily Transactions'!B:B,"Sales",'Daily Transactions'!D:D,"Cash") -> 0 | J14: =(H14+I14)-(D14+E14) -> 0 | L14: =SUMIFS('Daily Transactions'!C:C,'Daily Transactions'!A:A,$A14,'Daily Transactions'!B:B,"Cash Shortage",'Daily Transactions'!D:D,"Cash") -> 0
A15: =A14+1 -> 45669 | B15: =SUMIFS('Daily Transactions'!C:C,'Daily Transactions'!A:A,$A15,'Daily Transactions'!B:B,"Sales") -> 0 | C15: =SUMIFS('Daily Transactions'!C:C,'Daily Transactions'!A:A,$A15,'Daily Transactions'!B:B,"<>Sales") -> 0 | D15: =SUMIFS('Daily Transactions'!C:C,'Daily Transactions'!A:A,$A15,'Daily Transactions'!B:B,"<>Sales",'Daily Transactions'!D:D,"Cash") -> 0 | E15: =SUMIFS('Daily Transactions'!C:C,'Daily Transactions'!A:A,$A15,'Daily Transactions'!B:B,"<>Sales",'Daily Transactions'!D:D,"Bank_Cash") -> 0 | F15: =SUMIFS('Daily Transactions'!C:C,'Daily Transactions'!A:A,$A15,'Daily Transactions'!B:B,"<>Sales",'Daily Transactions'!D:D,"Bank") -> 0 | G15: =B15-C15 -> 0 | H15: =J14 -> 0 | I15: =SUMIFS('Daily Transactions'!C:C,'Daily Transactions'!A:A,$A15,'Daily Transactions'!B:B,"Sales",'Daily Transactions'!D:D,"Cash") -> 0 | J15: =(H15+I15)-(D15+E15) -> 0 | L15: =SUMIFS('Daily Transactions'!C:C,'Daily Transactions'!A:A,$A15,'Daily Transactions'!B:B,"Cash Shortage",'Daily Transactions'!D:D,"Cash") -> 0
A16: =A15+1 -> 45670 | B16: =SUMIFS('Daily Transactions'!C:C,'Daily Transactions'!A:A,$A16,'Daily Transactions'!B:B,"Sales") -> 0 | C16: =SUMIFS('Daily Transactions'!C:C,'Daily Transactions'!A:A,$A16,'Daily Transactions'!B:B,"<>Sales") -> 0 | D16: =SUMIFS('Daily Transactions'!C:C,'Daily Transactions'!A:A,$A16,'Daily Transactions'!B:B,"<>Sales",'Daily Transactions'!D:D,"Cash") -> 0 | E16: =SUMIFS('Daily Transactions'!C:C,'Daily Transactions'!A:A,$A16,'Daily Transactions'!B:B,"<>Sales",'Daily Transactions'!D:D,"Bank_Cash") -> 0 | F16: =SUMIFS('Daily Transactions'!C:C,'Daily Transactions'!A:A,$A16,'Daily Transactions'!B:B,"<>Sales",'Daily Transactions'!D:D,"Bank") -> 0 | G16: =B16-C16 -> 0 | H16: =J15 -> 0 | I16: =SUMIFS('Daily Transactions'!C:C,'Daily Transactions'!A:A,$A16,'Daily Transactions'!B:B,"Sales",'Daily Transactions'!D:D,"Cash") -> 0 | J16: =(H16+I16)-(D16+E16) -> 0 | L16: =SUMIFS('Daily Transactions'!C:C,'Daily Transactions'!A:A,$A16,'Daily Transactions'!B:B,"Cash Shortage",'Daily Transactions'!D:D,"Cash") -> 0
... A24: =A23+1 -> 45678 | B24: =SUMIFS('Daily Transactions'!C:C,'Daily Transactions'!A:A,$A24,'Daily Transactions'!B:B,"Sales") -> 0 | C24: =SUMIFS('Daily Transactions'!C:C,'Daily Transactions'!A:A,$A24,'Daily Transactions'!B:B,"<>Sales") -> 0 | D24: =SUMIFS('Daily Transactions'!C:C,'Daily Transactions'!A:A,$A24,'Daily Transactions'!B:B,"<>Sales",'Daily Transactions'!D:D,"Cash") -> 0 | E24: =SUMIFS('Daily Transactions'!C:C,'Daily Transactions'!A:A,$A24,'Daily Transactions'!B:B,"<>Sales",'Daily Transactions'!D:D,"Bank_Cash") -> 0 | F24: =SUMIFS('Daily Transactions'!C:C,'Daily Transactions'!A:A,$A24,'Daily Transactions'!B:B,"<>Sales",'Daily Transactions'!D:D,"Bank") -> 0 | G24: =B24-C24 -> 0 | H24: =J23 -> 0 | I24: =SUMIFS('Daily Transactions'!C:C,'Daily Transactions'!A:A,$A24,'Daily Transactions'!B:B,"Sales",'Daily Transactions'!D:D,"Cash") -> 0 | J24: =(H24+I24)-(D24+E24) -> 0 | L24: =SUMIFS('Daily Transactions'!C:C,'Daily Transactions'!A:A,$A24,'Daily Transactions'!B:B,"Cash Shortage",'Daily Transactions'!D:D,"Cash") -> 0
A25: =A24+1 -> 45679 | B25: =SUMIFS('Daily Transactions'!C:C,'Daily Transactions'!A:A,$A25,'Daily Transactions'!B:B,"Sales") -> 27918 | C25: =SUMIFS('Daily Transactions'!C:C,'Daily Transactions'!A:A,$A25,'Daily Transactions'!B:B,"<>Sales") -> 31943 | D25: =SUMIFS('Daily Transactions'!C:C,'Daily Transactions'!A:A,$A25,'Daily Transactions'!B:B,"<>Sales",'Daily Transactions'!D:D,"Cash") -> 1959 | E25: =SUMIFS('Daily Transactions'!C:C,'Daily Transactions'!A:A,$A25,'Daily Transactions'!B:B,"<>Sales",'Daily Transactions'!D:D,"Bank_Cash") -> 0 | F25: =SUMIFS('Daily Transactions'!C:C,'Daily Transactions'!A:A,$A25,'Daily Transactions'!B:B,"<>Sales",'Daily Transactions'!D:D,"Bank") -> 29984 | G25: =B25-C25 -> -4025 | H25: 8250 | I25: =SUMIFS('Daily Transactions'!C:C,'Daily Transactions'!A:A,$A25,'Daily Transactions'!B:B,"Sales",'Daily Transactions'!D:D,"Cash") -> 4759 | J25: =(H25+I25)-(D25+E25) -> 11050 | L25: =SUMIFS('Daily Transactions'!C:C,'Daily Transactions'!A:A,$A25,'Daily Transactions'!B:B,"Cash Shortage",'Daily Transactions'!D:D,"Cash") -> 0
A26: =A25+1 -> 45680 | B26: =SUMIFS('Daily Transactions'!C:C,'Daily Transactions'!A:A,$A26,'Daily Transactions'!B:B,"Sales") -> 13430 | C26: =SUMIFS('Daily Transactions'!C:C,'Daily Transactions'!A:A,$A26,'Daily Transactions'!B:B,"<>Sales") -> 13393 | D26: =SUMIFS('Daily Transactions'!C:C,'Daily Transactions'!A:A,$A26,'Daily Transactions'!B:B,"<>Sales",'Daily Transactions'!D:D,"Cash") -> 2110 | E26: =SUMIFS('Daily Transactions'!C:C,'Daily Transactions'!A:A,$A26,'Daily Transactions'!B:B,"<>Sales",'Daily Transactions'!D:D,"Bank_Cash") -> 0 | F26: =SUMIFS('Daily Transactions'!C:C,'Daily Transactions'!A:A,$A26,'Daily Transactions'!B:B,"<>Sales",'Daily Transactions'!D:D,"Bank") -> 11283 | G26: =B26-C26 -> 37 | H26: =J25 -> 11050 | I26: =SUMIFS('Daily Transactions'!C:C,'Daily Transactions'!A:A,$A26,'Daily Transactions'!B:B,"Sales",'Daily Transactions'!D:D,"Cash") -> 2410 | J26: =(H26+I26)-(D26+E26) -> 11350 | L26: =SUMIFS('Daily Transactions'!C:C,'Daily Transactions'!A:A,$A26,'Daily Transactions'!B:B,"Cash Shortage",'Daily Transactions'!D:D,"Cash") -> 0
A27: =A26+1 -> 45681 | B27: =SUMIFS('Daily Transactions'!C:C,'Daily Transactions'!A:A,$A27,'Daily Transactions'!B:B,"Sales") -> 24925 | C27: =SUMIFS('Daily Transactions'!C:C,'Daily Transactions'!A:A,$A27,'Daily Transactions'!B:B,"<>Sales") -> 21670 | D27: =SUMIFS('Daily Transactions'!C:C,'Daily Transactions'!A:A,$A27,'Daily Transactions'!B:B,"<>Sales",'Daily Transactions'!D:D,"Cash") -> 490 | E27: =SUMIFS('Daily Transactions'!C:C,'Daily Transactions'!A:A,$A27,'Daily Transactions'!B:B,"<>Sales",'Daily Transactions'!D:D,"Bank_Cash") -> 10300 | F27: =SUMIFS('Daily Transactions'!C:C,'Daily Transactions'!A:A,$A27,'Daily Transactions'!B:B,"<>Sales",'Daily Transactions'!D:D,"Bank") -> 10880 | G27: =B27-C27 -> 3255 | H27: =J26 -> 11350 | I27: =SUMIFS('Daily Transactions'!C:C,'Daily Transactions'!A:A,$A27,'Daily Transactions'!B:B,"Sales",'Daily Transactions'!D:D,"Cash") -> 3140 | J27: =(H27+I27)-(D27+E27) -> 3700 | L27: =SUMIFS('Daily Transactions'!C:C,'Daily Transactions'!A:A,$A27,'Daily Transactions'!B:B,"Cash Shortage",'Daily Transactions'!D:D,"Cash") -> 0
A28: =A27+1 -> 45682 | B28: =SUMIFS('Daily Transactions'!C:C,'Daily Transactions'!A:A,$A28,'Daily Transactions'!B:B,"Sales") -> 39001 | C28: =SUMIFS('Daily Transactions'!C:C,'Daily Transactions'!A:A,$A28,'Daily Transactions'!B:B,"<>Sales") -> 23322 | D28: =SUMIFS('Daily Transactions'!C:C,'Daily Transactions'!A:A,$A28,'Daily Transactions'!B:B,"<>Sales",'Daily Transactions'!D:D,"Cash") -> 3960 | E28: =SUMIFS('Daily Transactions'!C:C,'Daily Transactions'!A:A,$A28,'Daily Transactions'!B:B,"<>Sales",'Daily Transactions'!D:D,"Bank_Cash") -> 0 | F28: =SUMIFS('Daily Transactions'!C:C,'Daily Transactions'!A:A,$A28,'Daily Transactions'!B:B,"<>Sales",'Daily Transactions'!D:D,"Bank") -> 19362 | G28: =B28-C28 -> 15679 | H28: =J27 -> 3700 | I28: =SUMIFS('Daily Transactions'!C:C,'Daily Transactions'!A:A,$A28,'Daily Transactions'!B:B,"Sales",'Daily Transactions'!D:D,"Cash") -> 5660 | J28: =(H28+I28)-(D28+E28) -> 5400 | L28: =SUMIFS('Daily Transactions'!C:C,'Daily Transactions'!A:A,$A28,'Daily Transactions'!B:B,"Cash Shortage",'Daily Transactions'!D:D,"Cash") -> 0
A29: =A28+1 -> 45683 | B29: =SUMIFS('Daily Transactions'!C:C,'Daily Transactions'!A:A,$A29,'Daily Transactions'!B:B,"Sales") -> 41795 | C29: =SUMIFS('Daily Transactions'!C:C,'Daily Transactions'!A:A,$A29,'Daily Transactions'!B:B,"<>Sales") -> 19605 | D29: =SUMIFS('Daily Transactions'!C:C,'Daily Transactions'!A:A,$A29,'Daily Transactions'!B:B,"<>Sales",'Daily Transactions'!D:D,"Cash") -> 2379 | E29: =SUMIFS('Daily Transactions'!C:C,'Daily Transactions'!A:A,$A29,'Daily Transactions'!B:B,"<>Sales",'Daily Transactions'!D:D,"Bank_Cash") -> 2700 | F29: =SUMIFS('Daily Transactions'!C:C,'Daily Transactions'!A:A,$A29,'Daily Transactions'!B:B,"<>Sales",'Daily Transactions'!D:D,"Bank") -> 14526 | G29: =B29-C29 -> 22190 | H29: =J28 -> 5400 | I29: =SUMIFS('Daily Transactions'!C:C,'Daily Transactions'!A:A,$A29,'Daily Transactions'!B:B,"Sales",'Daily Transactions'!D:D,"Cash") -> 3979 | J29: =(H29+I29)-(D29+E29) -> 4300 | L29: =SUMIFS('Daily Transactions'!C:C,'Daily Transactions'!A:A,$A29,'Daily Transactions'!B:B,"Cash Shortage",'Daily Transactions'!D:D,"Cash") -> 0
A30: =A29+1 -> 45684 | B30: =SUMIFS('Daily Transactions'!C:C,'Daily Transactions'!A:A,$A30,'Daily Transactions'!B:B,"Sales") -> 21790 | C30: =SUMIFS('Daily Transactions'!C:C,'Daily Transactions'!A:A,$A30,'Daily Transactions'!B:B,"<>Sales") -> 7788 | D30: =SUMIFS('Daily Transactions'!C:C,'Daily Transactions'!A:A,$A30,'Daily Transactions'!B:B,"<>Sales",'Daily Transactions'!D:D,"Cash") -> 1290 | E30: =SUMIFS('Daily Transactions'!C:C,'Daily Transactions'!A:A,$A30,'Daily Transactions'!B:B,"<>Sales",'Daily Transactions'!D:D,"Bank_Cash") -> 0 | F30: =SUMIFS('Daily Transactions'!C:C,'Daily Transactions'!A:A,$A30,'Daily Transactions'!B:B,"<>Sales",'Daily Transactions'!D:D,"Bank") -> 6498 | G30: =B30-C30 -> 14002 | H30: =J29 -> 4300 | I30: =SUMIFS('Daily Transactions'!C:C,'Daily Transactions'!A:A,$A30,'Daily Transactions'!B:B,"Sales",'Daily Transactions'!D:D,"Cash") -> 2540 | J30: =(H30+I30)-(D30+E30) -> 5550 | L30: =SUMIFS('Daily Transactions'!C:C,'Daily Transactions'!A:A,$A30,'Daily Transactions'!B:B,"Cash Shortage",'Daily Transactions'!D:D,"Cash") -> 0
A31: =A30+1 -> 45685 | B31: =SUMIFS('Daily Transactions'!C:C,'Daily Transactions'!A:A,$A31,'Daily Transactions'!B:B,"Sales") -> 18334 | C31: =SUMIFS('Daily Transactions'!C:C,'Daily Transactions'!A:A,$A31,'Daily Transactions'!B:B,"<>Sales") -> 12279 | D31: =SUMIFS('Daily Transactions'!C:C,'Daily Transactions'!A:A,$A31,'Daily Transactions'!B:B,"<>Sales",'Daily Transactions'!D:D,"Cash") -> 1315 | E31: =SUMIFS('Daily Transactions'!C:C,'Daily Transactions'!A:A,$A31,'Daily Transactions'!B:B,"<>Sales",'Daily Transactions'!D:D,"Bank_Cash") -> 0 | F31: =SUMIFS('Daily Transactions'!C:C,'Daily Transactions'!A:A,$A31,'Daily Transactions'!B:B,"<>Sales",'Daily Transactions'!D:D,"Bank") -> 10964 | G31: =B31-C31 -> 6055 | H31: =J30 -> 5550 | I31: =SUMIFS('Daily Transactions'!C:C,'Daily Transactions'!A:A,$A31,'Daily Transactions'!B:B,"Sales",'Daily Transactions'!D:D,"Cash") -> 2415 | J31: =(H31+I31)-(D31+E31) -> 6650 | L31: =SUMIFS('Daily Transactions'!C:C,'Daily Transactions'!A:A,$A31,'Daily Transactions'!B:B,"Cash Shortage",'Daily Transactions'!D:D,"Cash") -> 0
A32: =A31+1 -> 45686 | B32: =SUMIFS('Daily Transactions'!C:C,'Daily Transactions'!A:A,$A32,'Daily Transactions'!B:B,"Sales") -> 17427 | C32: =SUMIFS('Daily Transactions'!C:C,'Daily Transactions'!A:A,$A32,'Daily Transactions'!B:B,"<>Sales") -> 12536 | D32: =SUMIFS('Daily Transactions'!C:C,'Daily Transactions'!A:A,$A32,'Daily Transactions'!B:B,"<>Sales",'Daily Transactions'!D:D,"Cash") -> 2660 | E32: =SUMIFS('Daily Transactions'!C:C,'Daily Transactions'!A:A,$A32,'Daily Transactions'!B:B,"<>Sales",'Daily Transactions'!D:D,"Bank_Cash") -> 100 | F32: =SUMIFS('Daily Transactions'!C:C,'Daily Transactions'!A:A,$A32,'Daily Transactions'!B:B,"<>Sales",'Daily Transactions'!D:D,"Bank") -> 9776 | G32: =B32-C32 -> 4891 | H32: =J31 -> 6650 | I32: =SUMIFS('Daily Transactions'!C:C,'Daily Transactions'!A:A,$A32,'Daily Transactions'!B:B,"Sales",'Daily Transactions'!D:D,"Cash") -> 2710 | J32: =(H32+I32)-(D32+E32) -> 6600 | L32: =SUMIFS('Daily Transactions'!C:C,'Daily Transactions'!A:A,$A32,'Daily Transactions'!B:B,"Cash Shortage",'Daily Transactions'!D:D,"Cash") -> 0
A33: =A32+1 -> 45687 | B33: =SUMIFS('Daily Transactions'!C:C,'Daily Transactions'!A:A,$A33,'Daily Transactions'!B:B,"Sales") -> 18440 | C33: =SUMIFS('Daily Transactions'!C:C,'Daily Transactions'!A:A,$A33,'Daily Transactions'!B:B,"<>Sales") -> 21294 | D33: =SUMIFS('Daily Transactions'!C:C,'Daily Transactions'!A:A,$A33,'Daily Transactions'!B:B,"<>Sales",'Daily Transactions'!D:D,"Cash") -> 100 | E33: =SUMIFS('Daily Transactions'!C:C,'Daily Transactions'!A:A,$A33,'Daily Transactions'!B:B,"<>Sales",'Daily Transactions'!D:D,"Bank_Cash") -> 2000 | F33: =SUMIFS('Daily Transactions'!C:C,'Daily Transactions'!A:A,$A33,'Daily Transactions'!B:B,"<>Sales",'Daily Transactions'!D:D,"Bank") -> 19194 | G33: =B33-C33 -> -2854 | H33: =J32 -> 6600 | I33: =SUMIFS('Daily Transactions'!C:C,'Daily Transactions'!A:A,$A33,'Daily Transactions'!B:B,"Sales",'Daily Transactions'!D:D,"Cash") -> 1700 | J33: =(H33+I33)-(D33+E33) -> 6200 | L33: =SUMIFS('Daily Transactions'!C:C,'Daily Transactions'!A:A,$A33,'Daily Transactions'!B:B,"Cash Shortage",'Daily Transactions'!D:D,"Cash") -> 0
A34: =A33+1 -> 45688 | B34: =SUMIFS('Daily Transactions'!C:C,'Daily Transactions'!A:A,$A34,'Daily Transactions'!B:B,"Sales") -> 25378 | C34: =SUMIFS('Daily Transactions'!C:C,'Daily Transactions'!A:A,$A34,'Daily Transactions'!B:B,"<>Sales") -> 30526 | D34: =SUMIFS('Daily Transactions'!C:C,'Daily Transactions'!A:A,$A34,'Daily Transactions'!B:B,"<>Sales",'Daily Transactions'!D:D,"Cash") -> 740 | E34: =SUMIFS('Daily Transactions'!C:C,'Daily Transactions'!A:A,$A34,'Daily Transactions'!B:B,"<>Sales",'Daily Transactions'!D:D,"Bank_Cash") -> 1500 | F34: =SUMIFS('Daily Transactions'!C:C,'Daily Transactions'!A:A,$A34,'Daily Transactions'!B:B,"<>Sales",'Daily Transactions'!D:D,"Bank") -> 28286 | G34: =B34-C34 -> -5148 | H34: =J33 -> 6200 | I34: =SUMIFS('Daily Transactions'!C:C,'Daily Transactions'!A:A,$A34,'Daily Transactions'!B:B,"Sales",'Daily Transactions'!D:D,"Cash") -> 1840 | J34: =(H34+I34)-(D34+E34) -> 5800 | L34: =SUMIFS('Daily Transactions'!C:C,'Daily Transactions'!A:A,$A34,'Daily Transactions'!B:B,"Cash Shortage",'Daily Transactions'!D:D,"Cash") -> 0
A35: =A34+1 -> 45689 | B35: =SUMIFS('Daily Transactions'!C:C,'Daily Transactions'!A:A,$A35,'Daily Transactions'!B:B,"Sales") -> 27527 | C35: =SUMIFS('Daily Transactions'!C:C,'Daily Transactions'!A:A,$A35,'Daily Transactions'!B:B,"<>Sales") -> 16775 | D35: =SUMIFS('Daily Transactions'!C:C,'Daily Transactions'!A:A,$A35,'Daily Transactions'!B:B,"<>Sales",'Daily Transactions'!D:D,"Cash") -> 4465 | E35: =SUMIFS('Daily Transactions'!C:C,'Daily Transactions'!A:A,$A35,'Daily Transactions'!B:B,"<>Sales",'Daily Transactions'!D:D,"Bank_Cash") -> 0 | F35: =SUMIFS('Daily Transactions'!C:C,'Daily Transactions'!A:A,$A35,'Daily Transactions'!B:B,"<>Sales",'Daily Transactions'!D:D,"Bank") -> 12310 | G35: =B35-C35 -> 10752 | H35: =J34 -> 5800 | I35: =SUMIFS('Daily Transactions'!C:C,'Daily Transactions'!A:A,$A35,'Daily Transactions'!B:B,"Sales",'Daily Transactions'!D:D,"Cash") -> 5015 | J35: =(H35+I35)-(D35+E35) -> 6350 | L35: =SUMIFS('Daily Transactions'!C:C,'Daily Transactions'!A:A,$A35,'Daily Transactions'!B:B,"Cash Shortage",'Daily Transactions'!D:D,"Cash") -> 0
A36: =A35+1 -> 45690 | B36: =SUMIFS('Daily Transactions'!C:C,'Daily Transactions'!A:A,$A36,'Daily Transactions'!B:B,"Sales") -> 35936 | C36: =SUMIFS('Daily Transactions'!C:C,'Daily Transactions'!A:A,$A36,'Daily Transactions'!B:B,"<>Sales") -> 29138 | D36: =SUMIFS('Daily Transactions'!C:C,'Daily Transactions'!A:A,$A36,'Daily Transactions'!B:B,"<>Sales",'Daily Transactions'!D:D,"Cash") -> 2540 | E36: =SUMIFS('Daily Transactions'!C:C,'Daily Transactions'!A:A,$A36,'Daily Transactions'!B:B,"<>Sales",'Daily Transactions'!D:D,"Bank_Cash") -> 3500 | F36: =SUMIFS('Daily Transactions'!C:C,'Daily Transactions'!A:A,$A36,'Daily Transactions'!B:B,"<>Sales",'Daily Transactions'!D:D,"Bank") -> 23098 | G36: =B36-C36 -> 6798 | H36: =J35 -> 6350 | I36: =SUMIFS('Daily Transactions'!C:C,'Daily Transactions'!A:A,$A36,'Daily Transactions'!B:B,"Sales",'Daily Transactions'!D:D,"Cash") -> 3340 | J36: =(H36+I36)-(D36+E36) -> 3650 | L36: =SUMIFS('Daily Transactions'!C:C,'Daily Transactions'!A:A,$A36,'Daily Transactions'!B:B,"Cash Shortage",'Daily Transactions'!D:D,"Cash") -> 0
A37: =A36+1 -> 45691 | B37: =SUMIFS('Daily Transactions'!C:C,'Daily Transactions'!A:A,$A37,'Daily Transactions'!B:B,"Sales") -> 22468 | C37: =SUMIFS('Daily Transactions'!C:C,'Daily Transactions'!A:A,$A37,'Daily Transactions'!B:B,"<>Sales") -> 26948 | D37: =SUMIFS('Daily Transactions'!C:C,'Daily Transactions'!A:A,$A37,'Daily Transactions'!B:B,"<>Sales",'Daily Transactions'!D:D,"Cash") -> 2915 | E37: =SUMIFS('Daily Transactions'!C:C,'Daily Transactions'!A:A,$A37,'Daily Transactions'!B:B,"<>Sales",'Daily Transactions'!D:D,"Bank_Cash") -> 0 | F37: =SUMIFS('Daily Transactions'!C:C,'Daily Transactions'!A:A,$A37,'Daily Transactions'!B:B,"<>Sales",'Daily Transactions'!D:D,"Bank") -> 24033 | G37: =B37-C37 -> -4480 | H37: =J36 -> 3650 | I37: =SUMIFS('Daily Transactions'!C:C,'Daily Transactions'!A:A,$A37,'Daily Transactions'!B:B,"Sales",'Daily Transactions'!D:D,"Cash") -> 3065 | J37: =(H37+I37)-(D37+E37) -> 3800 | L37: =SUMIFS('Daily Transactions'!C:C,'Daily Transactions'!A:A,$A37,'Daily Transactions'!B:B,"Cash Shortage",'Daily Transactions'!D:D,"Cash") -> 0
... A48: =A47+1 -> 45702 | B48: =SUMIFS('Daily Transactions'!C:C,'Daily Transactions'!A:A,$A48,'Daily Transactions'!B:B,"Sales") -> 36988 | C48: =SUMIFS('Daily Transactions'!C:C,'Daily Transactions'!A:A,$A48,'Daily Transactions'!B:B,"<>Sales") -> 6065 | D48: =SUMIFS('Daily Transactions'!C:C,'Daily Transactions'!A:A,$A48,'Daily Transactions'!B:B,"<>Sales",'Daily Transactions'!D:D,"Cash") -> 802 | E48: =SUMIFS('Daily Transactions'!C:C,'Daily Transactions'!A:A,$A48,'Daily Transactions'!B:B,"<>Sales",'Daily Transactions'!D:D,"Bank_Cash") -> 90 | F48: =SUMIFS('Daily Transactions'!C:C,'Daily Transactions'!A:A,$A48,'Daily Transactions'!B:B,"<>Sales",'Daily Transactions'!D:D,"Bank") -> 5173 | G48: =B48-C48 -> 30923 | H48: =J47 -> 7656 | I48: =SUMIFS('Daily Transactions'!C:C,'Daily Transactions'!A:A,$A48,'Daily Transactions'!B:B,"Sales",'Daily Transactions'!D:D,"Cash") -> 1999 | J48: =(H48+I48)-(D48+E48) -> 8763 | L48: =SUMIFS('Daily Transactions'!C:C,'Daily Transactions'!A:A,$A48,'Daily Transactions'!B:B,"Cash Shortage",'Daily Transactions'!D:D,"Cash") -> 0
A49: =A48+1 -> 45703 | B49: =SUMIFS('Daily Transactions'!C:C,'Daily Transactions'!A:A,$A49,'Daily Transactions'!B:B,"Sales") -> 25390 | C49: =SUMIFS('Daily Transactions'!C:C,'Daily Transactions'!A:A,$A49,'Daily Transactions'!B:B,"<>Sales") -> 10669 | D49: =SUMIFS('Daily Transactions'!C:C,'Daily Transactions'!A:A,$A49,'Daily Transactions'!B:B,"<>Sales",'Daily Transactions'!D:D,"Cash") -> 30 | E49: =SUMIFS('Daily Transactions'!C:C,'Daily Transactions'!A:A,$A49,'Daily Transactions'!B:B,"<>Sales",'Daily Transactions'!D:D,"Bank_Cash") -> 3791 | F49: =SUMIFS('Daily Transactions'!C:C,'Daily Transactions'!A:A,$A49,'Daily Transactions'!B:B,"<>Sales",'Daily Transactions'!D:D,"Bank") -> 6848 | G49: =B49-C49 -> 14721 | H49: =J48 -> 8763 | I49: =SUMIFS('Daily Transactions'!C:C,'Daily Transactions'!A:A,$A49,'Daily Transactions'!B:B,"Sales",'Daily Transactions'!D:D,"Cash") -> 5244 | J49: =(H49+I49)-(D49+E49) -> 10186 | K49: 1800 | L49: =SUMIFS('Daily Transactions'!C:C,'Daily Transactions'!A:A,$A49,'Daily Transactions'!B:B,"Cash Shortage",'Daily Transactions'!D:D,"Cash") -> 0
A50: =A49+1 -> 45704 | B50: =SUMIFS('Daily Transactions'!C:C,'Daily Transactions'!A:A,$A50,'Daily Transactions'!B:B,"Sales") -> 22504 | C50: =SUMIFS('Daily Transactions'!C:C,'Daily Transactions'!A:A,$A50,'Daily Transactions'!B:B,"<>Sales") -> 19751 | D50: =SUMIFS('Daily Transactions'!C:C,'Daily Transactions'!A:A,$A50,'Daily Transactions'!B:B,"<>Sales",'Daily Transactions'!D:D,"Cash") -> 30 | E50: =SUMIFS('Daily Transactions'!C:C,'Daily Transactions'!A:A,$A50,'Daily Transactions'!B:B,"<>Sales",'Daily Transactions'!D:D,"Bank_Cash") -> 2815 | F50: =SUMIFS('Daily Transactions'!C:C,'Daily Transactions'!A:A,$A50,'Daily Transactions'!B:B,"<>Sales",'Daily Transactions'!D:D,"Bank") -> 16906 | G50: =B50-C50 -> 2753 | H50: =J49 -> 10186 | I50: =SUMIFS('Daily Transactions'!C:C,'Daily Transactions'!A:A,$A50,'Daily Transactions'!B:B,"Sales",'Daily Transactions'!D:D,"Cash") -> 2335 | J50: =(H50+I50)-(D50+E50) -> 9676 | L50: =SUMIFS('Daily Transactions'!C:C,'Daily Transactions'!A:A,$A50,'Daily Transactions'!B:B,"Cash Shortage",'Daily Transactions'!D:D,"Cash") -> 0
A51: =A50+1 -> 45705 | B51: =SUMIFS('Daily Transactions'!C:C,'Daily Transactions'!A:A,$A51,'Daily Transactions'!B:B,"Sales") -> 13718 | C51: =SUMIFS('Daily Transactions'!C:C,'Daily Transactions'!A:A,$A51,'Daily Transactions'!B:B,"<>Sales") -> 8120 | D51: =SUMIFS('Daily Transactions'!C:C,'Daily Transactions'!A:A,$A51,'Daily Transactions'!B:B,"<>Sales",'Daily Transactions'!D:D,"Cash") -> 0 | E51: =SUMIFS('Daily Transactions'!C:C,'Daily Transactions'!A:A,$A51,'Daily Transactions'!B:B,"<>Sales",'Daily Transactions'!D:D,"Bank_Cash") -> 4705 | F51: =SUMIFS('Daily Transactions'!C:C,'Daily Transactions'!A:A,$A51,'Daily Transactions'!B:B,"<>Sales",'Daily Transactions'!D:D,"Bank") -> 3415 | G51: =B51-C51 -> 5598 | H51: =J50 -> 9676 | I51: =SUMIFS('Daily Transactions'!C:C,'Daily Transactions'!A:A,$A51,'Daily Transactions'!B:B,"Sales",'Daily Transactions'!D:D,"Cash") -> 2465 | J51: =(H51+I51)-(D51+E51) -> 7436 | L51: =SUMIFS('Daily Transactions'!C:C,'Daily Transactions'!A:A,$A51,'Daily Transactions'!B:B,"Cash Shortage",'Daily Transactions'!D:D,"Cash") -> 0
A52: =A51+1 -> 45706 | B52: =SUMIFS('Daily Transactions'!C:C,'Daily Transactions'!A:A,$A52,'Daily Transactions'!B:B,"Sales") -> 21864 | C52: =SUMIFS('Daily Transactions'!C:C,'Daily Transactions'!A:A,$A52,'Daily Transactions'!B:B,"<>Sales") -> 4597 | D52: =SUMIFS('Daily Transactions'!C:C,'Daily Transactions'!A:A,$A52,'Daily Transactions'!B:B,"<>Sales",'Daily Transactions'!D:D,"Cash") -> 15 | E52: =SUMIFS('Daily Transactions'!C:C,'Daily Transactions'!A:A,$A52,'Daily Transactions'!B:B,"<>Sales",'Daily Transactions'!D:D,"Bank_Cash") -> 135 | F52: =SUMIFS('Daily Transactions'!C:C,'Daily Transactions'!A:A,$A52,'Daily Transactions'!B:B,"<>Sales",'Daily Transactions'!D:D,"Bank") -> 4447 | G52: =B52-C52 -> 17267 | H52: =J51 -> 7436 | I52: =SUMIFS('Daily Transactions'!C:C,'Daily Transactions'!A:A,$A52,'Daily Transactions'!B:B,"Sales",'Daily Transactions'!D:D,"Cash") -> 1215 | J52: =(H52+I52)-(D52+E52) -> 8501 | L52: =SUMIFS('Daily Transactions'!C:C,'Daily Transactions'!A:A,$A52,'Daily Transactions'!B:B,"Cash Shortage",'Daily Transactions'!D:D,"Cash") -> 0
A53: =A52+1 -> 45707 | B53: =SUMIFS('Daily Transactions'!C:C,'Daily Transactions'!A:A,$A53,'Daily Transactions'!B:B,"Sales") -> 18724 | C53: =SUMIFS('Daily Transactions'!C:C,'Daily Transactions'!A:A,$A53,'Daily Transactions'!B:B,"<>Sales") -> 13749 | D53: =SUMIFS('Daily Transactions'!C:C,'Daily Transactions'!A:A,$A53,'Daily Transactions'!B:B,"<>Sales",'Daily Transactions'!D:D,"Cash") -> 40 | E53: =SUMIFS('Daily Transactions'!C:C,'Daily Transactions'!A:A,$A53,'Daily Transactions'!B:B,"<>Sales",'Daily Transactions'!D:D,"Bank_Cash") -> 5505 | F53: =SUMIFS('Daily Transactions'!C:C,'Daily Transactions'!A:A,$A53,'Daily Transactions'!B:B,"<>Sales",'Daily Transactions'!D:D,"Bank") -> 8204 | G53: =B53-C53 -> 4975 | H53: =J52 -> 8501 | I53: =SUMIFS('Daily Transactions'!C:C,'Daily Transactions'!A:A,$A53,'Daily Transactions'!B:B,"Sales",'Daily Transactions'!D:D,"Cash") -> 2677 | J53: =(H53+I53)-(D53+E53) -> 5633 | L53: =SUMIFS('Daily Transactions'!C:C,'Daily Transactions'!A:A,$A53,'Daily Transactions'!B:B,"Cash Shortage",'Daily Transactions'!D:D,"Cash") -> 0
A54: =A53+1 -> 45708 | B54: =SUMIFS('Daily Transactions'!C:C,'Daily Transactions'!A:A,$A54,'Daily Transactions'!B:B,"Sales") -> 21748 | C54: =SUMIFS('Daily Transactions'!C:C,'Daily Transactions'!A:A,$A54,'Daily Transactions'!B:B,"<>Sales") -> 7916 | D54: =SUMIFS('Daily Transactions'!C:C,'Daily Transactions'!A:A,$A54,'Daily Transactions'!B:B,"<>Sales",'Daily Transactions'!D:D,"Cash") -> 20 | E54: =SUMIFS('Daily Transactions'!C:C,'Daily Transactions'!A:A,$A54,'Daily Transactions'!B:B,"<>Sales",'Daily Transactions'!D:D,"Bank_Cash") -> 2871 | F54: =SUMIFS('Daily Transactions'!C:C,'Daily Transactions'!A:A,$A54,'Daily Transactions'!B:B,"<>Sales",'Daily Transactions'!D:D,"Bank") -> 5025 | G54: =B54-C54 -> 13832 | H54: =J53 -> 5633 | I54: =SUMIFS('Daily Transactions'!C:C,'Daily Transactions'!A:A,$A54,'Daily Transactions'!B:B,"Sales",'Daily Transactions'!D:D,"Cash") -> 4700 | J54: =(H54+I54)-(D54+E54) -> 7442 | L54: =SUMIFS('Daily Transactions'!C:C,'Daily Transactions'!A:A,$A54,'Daily Transactions'!B:B,"Cash Shortage",'Daily Transactions'!D:D,"Cash") -> 0
A55: =A54+1 -> 45709 | B55: =SUMIFS('Daily Transactions'!C:C,'Daily Transactions'!A:A,$A55,'Daily Transactions'!B:B,"Sales") -> 27657 | C55: =SUMIFS('Daily Transactions'!C:C,'Daily Transactions'!A:A,$A55,'Daily Transactions'!B:B,"<>Sales") -> 13533 | D55: =SUMIFS('Daily Transactions'!C:C,'Daily Transactions'!A:A,$A55,'Daily Transactions'!B:B,"<>Sales",'Daily Transactions'!D:D,"Cash") -> 50 | E55: =SUMIFS('Daily Transactions'!C:C,'Daily Transactions'!A:A,$A55,'Daily Transactions'!B:B,"<>Sales",'Daily Transactions'!D:D,"Bank_Cash") -> 2530 | F55: =SUMIFS('Daily Transactions'!C:C,'Daily Transactions'!A:A,$A55,'Daily Transactions'!B:B,"<>Sales",'Daily Transactions'!D:D,"Bank") -> 10953 | G55: =B55-C55 -> 14124 | H55: =J54 -> 7442 | I55: =SUMIFS('Daily Transactions'!C:C,'Daily Transactions'!A:A,$A55,'Daily Transactions'!B:B,"Sales",'Daily Transactions'!D:D,"Cash") -> 1229 | J55: =(H55+I55)-(D55+E55) -> 6091 | L55: =SUMIFS('Daily Transactions'!C:C,'Daily Transactions'!A:A,$A55,'Daily Transactions'!B:B,"Cash Shortage",'Daily Transactions'!D:D,"Cash") -> 0
A56: =A55+1 -> 45710 | B56: =SUMIFS('Daily Transactions'!C:C,'Daily Transactions'!A:A,$A56,'Daily Transactions'!B:B,"Sales") -> 24988 | C56: =SUMIFS('Daily Transactions'!C:C,'Daily Transactions'!A:A,$A56,'Daily Transactions'!B:B,"<>Sales") -> 16851 | D56: =SUMIFS('Daily Transactions'!C:C,'Daily Transactions'!A:A,$A56,'Daily Transactions'!B:B,"<>Sales",'Daily Transactions'!D:D,"Cash") -> 2040 | E56: =SUMIFS('Daily Transactions'!C:C,'Daily Transactions'!A:A,$A56,'Daily Transactions'!B:B,"<>Sales",'Daily Transactions'!D:D,"Bank_Cash") -> 3730 | F56: =SUMIFS('Daily Transactions'!C:C,'Daily Transactions'!A:A,$A56,'Daily Transactions'!B:B,"<>Sales",'Daily Transactions'!D:D,"Bank") -> 11081 | G56: =B56-C56 -> 8137 | H56: =J55 -> 6091 | I56: =SUMIFS('Daily Transactions'!C:C,'Daily Transactions'!A:A,$A56,'Daily Transactions'!B:B,"Sales",'Daily Transactions'!D:D,"Cash") -> 3140 | J56: =(H56+I56)-(D56+E56) -> 3461 | L56: =SUMIFS('Daily Transactions'!C:C,'Daily Transactions'!A:A,$A56,'Daily Transactions'!B:B,"Cash Shortage",'Daily Transactions'!D:D,"Cash") -> 0
A57: =A56+1 -> 45711 | B57: =SUMIFS('Daily Transactions'!C:C,'Daily Transactions'!A:A,$A57,'Daily Transactions'!B:B,"Sales") -> 26423 | C57: =SUMIFS('Daily Transactions'!C:C,'Daily Transactions'!A:A,$A57,'Daily Transactions'!B:B,"<>Sales") -> 5841 | D57: =SUMIFS('Daily Transactions'!C:C,'Daily Transactions'!A:A,$A57,'Daily Transactions'!B:B,"<>Sales",'Daily Transactions'!D:D,"Cash") -> 40 | E57: =SUMIFS('Daily Transactions'!C:C,'Daily Transactions'!A:A,$A57,'Daily Transactions'!B:B,"<>Sales",'Daily Transactions'!D:D,"Bank_Cash") -> 1515 | F57: =SUMIFS('Daily Transactions'!C:C,'Daily Transactions'!A:A,$A57,'Daily Transactions'!B:B,"<>Sales",'Daily Transactions'!D:D,"Bank") -> 4286 | G57: =B57-C57 -> 20582 | H57: =J56 -> 3461 | I57: =SUMIFS('Daily Transactions'!C:C,'Daily Transactions'!A:A,$A57,'Daily Transactions'!B:B,"Sales",'Daily Transactions'!D:D,"Cash") -> 1460 | J57: =(H57+I57)-(D57+E57) -> 3366 | L57: =SUMIFS('Daily Transactions'!C:C,'Daily Transactions'!A:A,$A57,'Daily Transactions'!B:B,"Cash Shortage",'Daily Transactions'!D:D,"Cash") -> 0
A58: =A57+1 -> 45712 | B58: =SUMIFS('Daily Transactions'!C:C,'Daily Transactions'!A:A,$A58,'Daily Transactions'!B:B,"Sales") -> 21819 | C58: =SUMIFS('Daily Transactions'!C:C,'Daily Transactions'!A:A,$A58,'Daily Transactions'!B:B,"<>Sales") -> 8343 | D58: =SUMIFS('Daily Transactions'!C:C,'Daily Transactions'!A:A,$A58,'Daily Transactions'!B:B,"<>Sales",'Daily Transactions'!D:D,"Cash") -> 20 | E58: =SUMIFS('Daily Transactions'!C:C,'Daily Transactions'!A:A,$A58,'Daily Transactions'!B:B,"<>Sales",'Daily Transactions'!D:D,"Bank_Cash") -> 1785 | F58: =SUMIFS('Daily Transactions'!C:C,'Daily Transactions'!A:A,$A58,'Daily Transactions'!B:B,"<>Sales",'Daily Transactions'!D:D,"Bank") -> 6538 | G58: =B58-C58 -> 13476 | H58: =J57 -> 3366 | I58: =SUMIFS('Daily Transactions'!C:C,'Daily Transactions'!A:A,$A58,'Daily Transactions'!B:B,"Sales",'Daily Transactions'!D:D,"Cash") -> 2085 | J58: =(H58+I58)-(D58+E58) -> 3646 | L58: =SUMIFS('Daily Transactions'!C:C,'Daily Transactions'!A:A,$A58,'Daily Transactions'!B:B,"Cash Shortage",'Daily Transactions'!D:D,"Cash") -> 0 | O58: 1675 | P58: 3540
A59: =A58+1 -> 45713 | B59: =SUMIFS('Daily Transactions'!C:C,'Daily Transactions'!A:A,$A59,'Daily Transactions'!B:B,"Sales") -> 15477 | C59: =SUMIFS('Daily Transactions'!C:C,'Daily Transactions'!A:A,$A59,'Daily Transactions'!B:B,"<>Sales") -> 27130 | D59: =SUMIFS('Daily Transactions'!C:C,'Daily Transactions'!A:A,$A59,'Daily Transactions'!B:B,"<>Sales",'Daily Transactions'!D:D,"Cash") -> 40 | E59: =SUMIFS('Daily Transactions'!C:C,'Daily Transactions'!A:A,$A59,'Daily Transactions'!B:B,"<>Sales",'Daily Transactions'!D:D,"Bank_Cash") -> 335 | F59: =SUMIFS('Daily Transactions'!C:C,'Daily Transactions'!A:A,$A59,'Daily Transactions'!B:B,"<>Sales",'Daily Transactions'!D:D,"Bank") -> 26755 | G59: =B59-C59 -> -11653 | H59: =J58 -> 3646 | I59: =SUMIFS('Daily Transactions'!C:C,'Daily Transactions'!A:A,$A59,'Daily Transactions'!B:B,"Sales",'Daily Transactions'!D:D,"Cash") -> 1240 | J59: =(H59+I59)-(D59+E59) -> 4511 | L59: =SUMIFS('Daily Transactions'!C:C,'Daily Transactions'!A:A,$A59,'Daily Transactions'!B:B,"Cash Shortage",'Daily Transactions'!D:D,"Cash") -> 0 | O59: 1500
A60: =A59+1 -> 45714 | B60: =SUMIFS('Daily Transactions'!C:C,'Daily Transactions'!A:A,$A60,'Daily Transactions'!B:B,"Sales") -> 0 | C60: =SUMIFS('Daily Transactions'!C:C,'Daily Transactions'!A:A,$A60,'Daily Transactions'!B:B,"<>Sales") -> 0 | D60: =SUMIFS('Daily Transactions'!C:C,'Daily Transactions'!A:A,$A60,'Daily Transactions'!B:B,"<>Sales",'Daily Transactions'!D:D,"Cash") -> 0 | E60: =SUMIFS('Daily Transactions'!C:C,'Daily Transactions'!A:A,$A60,'Daily Transactions'!B:B,"<>Sales",'Daily Transactions'!D:D,"Bank_Cash") -> 0 | F60: =SUMIFS('Daily Transactions'!C:C,'Daily Transactions'!A:A,$A60,'Daily Transactions'!B:B,"<>Sales",'Daily Transactions'!D:D,"Bank") -> 0 | G60: =B60-C60 -> 0 | H60: =J59 -> 4511 | I60: =SUMIFS('Daily Transactions'!C:C,'Daily Transactions'!A:A,$A60,'Daily Transactions'!B:B,"Sales",'Daily Transactions'!D:D,"Cash") -> 0 | J60: =(H60+I60)-(D60+E60) -> 4511 | L60: =SUMIFS('Daily Transactions'!C:C,'Daily Transactions'!A:A,$A60,'Daily Transactions'!B:B,"Cash Shortage",'Daily Transactions'!D:D,"Cash") -> 0 | O60: 1000
A61: =A60+1 -> 45715 | B61: =SUMIFS('Daily Transactions'!C:C,'Daily Transactions'!A:A,$A61,'Daily Transactions'!B:B,"Sales") -> 29334 | C61: =SUMIFS('Daily Transactions'!C:C,'Daily Transactions'!A:A,$A61,'Daily Transactions'!B:B,"<>Sales") -> 12099 | D61: =SUMIFS('Daily Transactions'!C:C,'Daily Transactions'!A:A,$A61,'Daily Transactions'!B:B,"<>Sales",'Daily Transactions'!D:D,"Cash") -> 50 | E61: =SUMIFS('Daily Transactions'!C:C,'Daily Transactions'!A:A,$A61,'Daily Transactions'!B:B,"<>Sales",'Daily Transactions'!D:D,"Bank_Cash") -> 1885 | F61: =SUMIFS('Daily Transactions'!C:C,'Daily Transactions'!A:A,$A61,'Daily Transactions'!B:B,"<>Sales",'Daily Transactions'!D:D,"Bank") -> 10164 | G61: =B61-C61 -> 17235 | H61: =J60 -> 4511 | I61: =SUMIFS('Daily Transactions'!C:C,'Daily Transactions'!A:A,$A61,'Daily Transactions'!B:B,"Sales",'Daily Transactions'!D:D,"Cash") -> 4580 | J61: =(H61+I61)-(D61+E61) -> 7156 | L61: =SUMIFS('Daily Transactions'!C:C,'Daily Transactions'!A:A,$A61,'Daily Transactions'!B:B,"Cash Shortage",'Daily Transactions'!D:D,"Cash") -> 0
A62: =A61+1 -> 45716 | B62: =SUMIFS('Daily Transactions'!C:C,'Daily Transactions'!A:A,$A62,'Daily Transactions'!B:B,"Sales") -> 44594 | C62: =SUMIFS('Daily Transactions'!C:C,'Daily Transactions'!A:A,$A62,'Daily Transactions'!B:B,"<>Sales") -> 24290 | D62: =SUMIFS('Daily Transactions'!C:C,'Daily Transactions'!A:A,$A62,'Daily Transactions'!B:B,"<>Sales",'Daily Transactions'!D:D,"Cash") -> 3791 | E62: =SUMIFS('Daily Transactions'!C:C,'Daily Transactions'!A:A,$A62,'Daily Transactions'!B:B,"<>Sales",'Daily Transactions'!D:D,"Bank_Cash") -> 5170 | F62: =SUMIFS('Daily Transactions'!C:C,'Daily Transactions'!A:A,$A62,'Daily Transactions'!B:B,"<>Sales",'Daily Transactions'!D:D,"Bank") -> 15329 | G62: =B62-C62 -> 20304 | H62: =J61 -> 7156 | I62: =SUMIFS('Daily Transactions'!C:C,'Daily Transactions'!A:A,$A62,'Daily Transactions'!B:B,"Sales",'Daily Transactions'!D:D,"Cash") -> 5440 | J62: =(H62+I62)-(D62+E62) -> 3635 | L62: =SUMIFS('Daily Transactions'!C:C,'Daily Transactions'!A:A,$A62,'Daily Transactions'!B:B,"Cash Shortage",'Daily Transactions'!D:D,"Cash") -> 0
A63: =A62+1 -> 45717 | B63: =SUMIFS('Daily Transactions'!C:C,'Daily Transactions'!A:A,$A63,'Daily Transactions'!B:B,"Sales") -> 51249 | C63: =SUMIFS('Daily Transactions'!C:C,'Daily Transactions'!A:A,$A63,'Daily Transactions'!B:B,"<>Sales") -> 19460 | D63: =SUMIFS('Daily Transactions'!C:C,'Daily Transactions'!A:A,$A63,'Daily Transactions'!B:B,"<>Sales",'Daily Transactions'!D:D,"Cash") -> 75 | E63: =SUMIFS('Daily Transactions'!C:C,'Daily Transactions'!A:A,$A63,'Daily Transactions'!B:B,"<>Sales",'Daily Transactions'!D:D,"Bank_Cash") -> 1090 | F63: =SUMIFS('Daily Transactions'!C:C,'Daily Transactions'!A:A,$A63,'Daily Transactions'!B:B,"<>Sales",'Daily Transactions'!D:D,"Bank") -> 18295 | G63: =B63-C63 -> 31789 | H63: =J62 -> 3635 | I63: =SUMIFS('Daily Transactions'!C:C,'Daily Transactions'!A:A,$A63,'Daily Transactions'!B:B,"Sales",'Daily Transactions'!D:D,"Cash") -> 4259 | J63: =(H63+I63)-(D63+E63) -> 6729 | L63: =SUMIFS('Daily Transactions'!C:C,'Daily Transactions'!A:A,$A63,'Daily Transactions'!B:B,"Cash Shortage",'Daily Transactions'!D:D,"Cash") -> 0
A64: =A63+1 -> 45718 | B64: =SUMIFS('Daily Transactions'!C:C,'Daily Transactions'!A:A,$A64,'Daily Transactions'!B:B,"Sales") -> 30215 | C64: =SUMIFS('Daily Transactions'!C:C,'Daily Transactions'!A:A,$A64,'Daily Transactions'!B:B,"<>Sales") -> 23363 | D64: =SUMIFS('Daily Transactions'!C:C,'Daily Transactions'!A:A,$A64,'Daily Transactions'!B:B,"<>Sales",'Daily Transactions'!D:D,"Cash") -> 50 | E64: =SUMIFS('Daily Transactions'!C:C,'Daily Transactions'!A:A,$A64,'Daily Transactions'!B:B,"<>Sales",'Daily Transactions'!D:D,"Bank_Cash") -> 1005 | F64: =SUMIFS('Daily Transactions'!C:C,'Daily Transactions'!A:A,$A64,'Daily Transactions'!B:B,"<>Sales",'Daily Transactions'!D:D,"Bank") -> 22308 | G64: =B64-C64 -> 6852 | H64: =J63 -> 6729 | I64: =SUMIFS('Daily Transactions'!C:C,'Daily Transactions'!A:A,$A64,'Daily Transactions'!B:B,"Sales",'Daily Transactions'!D:D,"Cash") -> 1870 | J64: =(H64+I64)-(D64+E64) -> 7544 | L64: =SUMIFS('Daily Transactions'!C:C,'Daily Transactions'!A:A,$A64,'Daily Transactions'!B:B,"Cash Shortage",'Daily Transactions'!D:D,"Cash") -> 0
A65: =A64+1 -> 45719 | B65: =SUMIFS('Daily Transactions'!C:C,'Daily Transactions'!A:A,$A65,'Daily Transactions'!B:B,"Sales") -> 22807 | C65: =SUMIFS('Daily Transactions'!C:C,'Daily Transactions'!A:A,$A65,'Daily Transactions'!B:B,"<>Sales") -> 20159 | D65: =SUMIFS('Daily Transactions'!C:C,'Daily Transactions'!A:A,$A65,'Daily Transactions'!B:B,"<>Sales",'Daily Transactions'!D:D,"Cash") -> 1015 | E65: =SUMIFS('Daily Transactions'!C:C,'Daily Transactions'!A:A,$A65,'Daily Transactions'!B:B,"<>Sales",'Daily Transactions'!D:D,"Bank_Cash") -> 4022 | F65: =SUMIFS('Daily Transactions'!C:C,'Daily Transactions'!A:A,$A65,'Daily Transactions'!B:B,"<>Sales",'Daily Transactions'!D:D,"Bank") -> 15122 | G65: =B65-C65 -> 2648 | H65: =J64 -> 7544 | I65: =SUMIFS('Daily Transactions'!C:C,'Daily Transactions'!A:A,$A65,'Daily Transactions'!B:B,"Sales",'Daily Transactions'!D:D,"Cash") -> 2014 | J65: =(H65+I65)-(D65+E65) -> 4521 | L65: =SUMIFS('Daily Transactions'!C:C,'Daily Transactions'!A:A,$A65,'Daily Transactions'!B:B,"Cash Shortage",'Daily Transactions'!D:D,"Cash") -> 0
A66: =A65+1 -> 45720 | B66: =SUMIFS('Daily Transactions'!C:C,'Daily Transactions'!A:A,$A66,'Daily Transactions'!B:B,"Sales") -> 27896 | C66: =SUMIFS('Daily Transactions'!C:C,'Daily Transactions'!A:A,$A66,'Daily Transactions'!B:B,"<>Sales") -> 29987 | D66: =SUMIFS('Daily Transactions'!C:C,'Daily Transactions'!A:A,$A66,'Daily Transactions'!B:B,"<>Sales",'Daily Transactions'!D:D,"Cash") -> 50 | E66: =SUMIFS('Daily Transactions'!C:C,'Daily Transactions'!A:A,$A66,'Daily Transactions'!B:B,"<>Sales",'Daily Transactions'!D:D,"Bank_Cash") -> 1770 | F66: =SUMIFS('Daily Transactions'!C:C,'Daily Transactions'!A:A,$A66,'Daily Transactions'!B:B,"<>Sales",'Daily Transactions'!D:D,"Bank") -> 28167 | G66: =B66-C66 -> -2091 | H66: =J65 -> 4521 | I66: =SUMIFS('Daily Transactions'!C:C,'Daily Transactions'!A:A,$A66,'Daily Transactions'!B:B,"Sales",'Daily Transactions'!D:D,"Cash") -> 3979 | J66: =(H66+I66)-(D66+E66) -> 6680 | L66: =SUMIFS('Daily Transactions'!C:C,'Daily Transactions'!A:A,$A66,'Daily Transactions'!B:B,"Cash Shortage",'Daily Transactions'!D:D,"Cash") -> 0
A67: =A66+1 -> 45721 | B67: =SUMIFS('Daily Transactions'!C:C,'Daily Transactions'!A:A,$A67,'Daily Transactions'!B:B,"Sales") -> 27793 | C67: =SUMIFS('Daily Transactions'!C:C,'Daily Transactions'!A:A,$A67,'Daily Transactions'!B:B,"<>Sales") -> 28348 | D67: =SUMIFS('Daily Transactions'!C:C,'Daily Transactions'!A:A,$A67,'Daily Transactions'!B:B,"<>Sales",'Daily Transactions'!D:D,"Cash") -> 362 | E67: =SUMIFS('Daily Transactions'!C:C,'Daily Transactions'!A:A,$A67,'Daily Transactions'!B:B,"<>Sales",'Daily Transactions'!D:D,"Bank_Cash") -> 4520 | F67: =SUMIFS('Daily Transactions'!C:C,'Daily Transactions'!A:A,$A67,'Daily Transactions'!B:B,"<>Sales",'Daily Transactions'!D:D,"Bank") -> 23466 | G67: =B67-C67 -> -555 | H67: =J66 -> 6680 | I67: =SUMIFS('Daily Transactions'!C:C,'Daily Transactions'!A:A,$A67,'Daily Transactions'!B:B,"Sales",'Daily Transactions'!D:D,"Cash") -> 2234 | J67: =(H67+I67)-(D67+E67) -> 4032 | L67: =SUMIFS('Daily Transactions'!C:C,'Daily Transactions'!A:A,$A67,'Daily Transactions'!B:B,"Cash Shortage",'Daily Transactions'!D:D,"Cash") -> 0
A68: =A67+1 -> 45722 | B68: =SUMIFS('Daily Transactions'!C:C,'Daily Transactions'!A:A,$A68,'Daily Transactions'!B:B,"Sales") -> 24962 | C68: =SUMIFS('Daily Transactions'!C:C,'Daily Transactions'!A:A,$A68,'Daily Transactions'!B:B,"<>Sales") -> 16438 | D68: =SUMIFS('Daily Transactions'!C:C,'Daily Transactions'!A:A,$A68,'Daily Transactions'!B:B,"<>Sales",'Daily Transactions'!D:D,"Cash") -> 30 | E68: =SUMIFS('Daily Transactions'!C:C,'Daily Transactions'!A:A,$A68,'Daily Transactions'!B:B,"<>Sales",'Daily Transactions'!D:D,"Bank_Cash") -> 160 | F68: =SUMIFS('Daily Transactions'!C:C,'Daily Transactions'!A:A,$A68,'Daily Transactions'!B:B,"<>Sales",'Daily Transactions'!D:D,"Bank") -> 16248 | G68: =B68-C68 -> 8524 | H68: =J67 -> 4032 | I68: =SUMIFS('Daily Transactions'!C:C,'Daily Transactions'!A:A,$A68,'Daily Transactions'!B:B,"Sales",'Daily Transactions'!D:D,"Cash") -> 1385 | J68: =(H68+I68)-(D68+E68) -> 5227 | L68: =SUMIFS('Daily Transactions'!C:C,'Daily Transactions'!A:A,$A68,'Daily Transactions'!B:B,"Cash Shortage",'Daily Transactions'!D:D,"Cash") -> 0
A69: =A68+1 -> 45723 | B69: =SUMIFS('Daily Transactions'!C:C,'Daily Transactions'!A:A,$A69,'Daily Transactions'!B:B,"Sales") -> 41834 | C69: =SUMIFS('Daily Transactions'!C:C,'Daily Transactions'!A:A,$A69,'Daily Transactions'!B:B,"<>Sales") -> 13527 | D69: =SUMIFS('Daily Transactions'!C:C,'Daily Transactions'!A:A,$A69,'Daily Transactions'!B:B,"<>Sales",'Daily Transactions'!D:D,"Cash") -> 1390 | E69: =SUMIFS('Daily Transactions'!C:C,'Daily Transactions'!A:A,$A69,'Daily Transactions'!B:B,"<>Sales",'Daily Transactions'!D:D,"Bank_Cash") -> 3219 | F69: =SUMIFS('Daily Transactions'!C:C,'Daily Transactions'!A:A,$A69,'Daily Transactions'!B:B,"<>Sales",'Daily Transactions'!D:D,"Bank") -> 8918 | G69: =B69-C69 -> 28307 | H69: =J68 -> 5227 | I69: =SUMIFS('Daily Transactions'!C:C,'Daily Transactions'!A:A,$A69,'Daily Transactions'!B:B,"Sales",'Daily Transactions'!D:D,"Cash") -> 2745 | J69: =(H69+I69)-(D69+E69) -> 3363 | L69: =SUMIFS('Daily Transactions'!C:C,'Daily Transactions'!A:A,$A69,'Daily Transactions'!B:B,"Cash Shortage",'Daily Transactions'!D:D,"Cash") -> 0
A70: =A69+1 -> 45724 | B70: =SUMIFS('Daily Transactions'!C:C,'Daily Transactions'!A:A,$A70,'Daily Transactions'!B:B,"Sales") -> 42341 | C70: =SUMIFS('Daily Transactions'!C:C,'Daily Transactions'!A:A,$A70,'Daily Transactions'!B:B,"<>Sales") -> 25225 | D70: =SUMIFS('Daily Transactions'!C:C,'Daily Transactions'!A:A,$A70,'Daily Transactions'!B:B,"<>Sales",'Daily Transactions'!D:D,"Cash") -> 1160 | E70: =SUMIFS('Daily Transactions'!C:C,'Daily Transactions'!A:A,$A70,'Daily Transactions'!B:B,"<>Sales",'Daily Transactions'!D:D,"Bank_Cash") -> 845 | F70: =SUMIFS('Daily Transactions'!C:C,'Daily Transactions'!A:A,$A70,'Daily Transactions'!B:B,"<>Sales",'Daily Transactions'!D:D,"Bank") -> 23220 | G70: =B70-C70 -> 17116 | H70: =J69 -> 3363 | I70: =SUMIFS('Daily Transactions'!C:C,'Daily Transactions'!A:A,$A70,'Daily Transactions'!B:B,"Sales",'Daily Transactions'!D:D,"Cash") -> 4715 | J70: =(H70+I70)-(D70+E70) -> 6073 | L70: =SUMIFS('Daily Transactions'!C:C,'Daily Transactions'!A:A,$A70,'Daily Transactions'!B:B,"Cash Shortage",'Daily Transactions'!D:D,"Cash") -> 0
A71: =A70+1 -> 45725 | B71: =SUMIFS('Daily Transactions'!C:C,'Daily Transactions'!A:A,$A71,'Daily Transactions'!B:B,"Sales") -> 45333 | C71: =SUMIFS('Daily Transactions'!C:C,'Daily Transactions'!A:A,$A71,'Daily Transactions'!B:B,"<>Sales") -> 21326 | D71: =SUMIFS('Daily Transactions'!C:C,'Daily Transactions'!A:A,$A71,'Daily Transactions'!B:B,"<>Sales",'Daily Transactions'!D:D,"Cash") -> 3393 | E71: =SUMIFS('Daily Transactions'!C:C,'Daily Transactions'!A:A,$A71,'Daily Transactions'!B:B,"<>Sales",'Daily Transactions'!D:D,"Bank_Cash") -> 2500 | F71: =SUMIFS('Daily Transactions'!C:C,'Daily Transactions'!A:A,$A71,'Daily Transactions'!B:B,"<>Sales",'Daily Transactions'!D:D,"Bank") -> 15433 | G71: =B71-C71 -> 24007 | H71: =J70 -> 6073 | I71: =SUMIFS('Daily Transactions'!C:C,'Daily Transactions'!A:A,$A71,'Daily Transactions'!B:B,"Sales",'Daily Transactions'!D:D,"Cash") -> 4743 | J71: =(H71+I71)-(D71+E71) -> 4923 | L71: =SUMIFS('Daily Transactions'!C:C,'Daily Transactions'!A:A,$A71,'Daily Transactions'!B:B,"Cash Shortage",'Daily Transactions'!D:D,"Cash") -> 0
A72: =A71+1 -> 45726 | B72: =SUMIFS('Daily Transactions'!C:C,'Daily Transactions'!A:A,$A72,'Daily Transactions'!B:B,"Sales") -> 20311 | C72: =SUMIFS('Daily Transactions'!C:C,'Daily Transactions'!A:A,$A72,'Daily Transactions'!B:B,"<>Sales") -> 15550 | D72: =SUMIFS('Daily Transactions'!C:C,'Daily Transactions'!A:A,$A72,'Daily Transactions'!B:B,"<>Sales",'Daily Transactions'!D:D,"Cash") -> 1210 | E72: =SUMIFS('Daily Transactions'!C:C,'Daily Transactions'!A:A,$A72,'Daily Transactions'!B:B,"<>Sales",'Daily Transactions'!D:D,"Bank_Cash") -> 1870 | F72: =SUMIFS('Daily Transactions'!C:C,'Daily Transactions'!A:A,$A72,'Daily Transactions'!B:B,"<>Sales",'Daily Transactions'!D:D,"Bank") -> 12470 | G72: =B72-C72 -> 4761 | H72: =J71 -> 4923 | I72: =SUMIFS('Daily Transactions'!C:C,'Daily Transactions'!A:A,$A72,'Daily Transactions'!B:B,"Sales",'Daily Transactions'!D:D,"Cash") -> 1210 | J72: =(H72+I72)-(D72+E72) -> 3053 | L72: =SUMIFS('Daily Transactions'!C:C,'Daily Transactions'!A:A,$A72,'Daily Transactions'!B:B,"Cash Shortage",'Daily Transactions'!D:D,"Cash") -> 0
... A202: =A201+1 -> 45856 | B202: =SUMIFS('Daily Transactions'!C:C,'Daily Transactions'!A:A,$A202,'Daily Transactions'!B:B,"Sales") -> 21311 | C202: =SUMIFS('Daily Transactions'!C:C,'Daily Transactions'!A:A,$A202,'Daily Transactions'!B:B,"<>Sales") -> 8038 | D202: =SUMIFS('Daily Transactions'!C:C,'Daily Transactions'!A:A,$A202,'Daily Transactions'!B:B,"<>Sales",'Daily Transactions'!D:D,"Cash") -> 95 | E202: =SUMIFS('Daily Transactions'!C:C,'Daily Transactions'!A:A,$A202,'Daily Transactions'!B:B,"<>Sales",'Daily Transactions'!D:D,"Bank_Cash") -> 1590 | F202: =SUMIFS('Daily Transactions'!C:C,'Daily Transactions'!A:A,$A202,'Daily Transactions'!B:B,"<>Sales",'Daily Transactions'!D:D,"Bank") -> 6353 | G202: =B202-C202 -> 13273 | H202: =J201 -> 15200 | I202: =SUMIFS('Daily Transactions'!C:C,'Daily Transactions'!A:A,$A202,'Daily Transactions'!B:B,"Sales",'Daily Transactions'!D:D,"Cash") -> 735 | J202: =(H202+I202)-(D202+E202) -> 14250 | L202: =SUMIFS('Daily Transactions'!C:C,'Daily Transactions'!A:A,$A202,'Daily Transactions'!B:B,"Cash Shortage",'Daily Transactions'!D:D,"Cash") -> 0
A203: =A202+1 -> 45857 | B203: =SUMIFS('Daily Transactions'!C:C,'Daily Transactions'!A:A,$A203,'Daily Transactions'!B:B,"Sales") -> 19988 | C203: =SUMIFS('Daily Transactions'!C:C,'Daily Transactions'!A:A,$A203,'Daily Transactions'!B:B,"<>Sales") -> 12162 | D203: =SUMIFS('Daily Transactions'!C:C,'Daily Transactions'!A:A,$A203,'Daily Transactions'!B:B,"<>Sales",'Daily Transactions'!D:D,"Cash") -> 100 | E203: =SUMIFS('Daily Transactions'!C:C,'Daily Transactions'!A:A,$A203,'Daily Transactions'!B:B,"<>Sales",'Daily Transactions'!D:D,"Bank_Cash") -> 5630 | F203: =SUMIFS('Daily Transactions'!C:C,'Daily Transactions'!A:A,$A203,'Daily Transactions'!B:B,"<>Sales",'Daily Transactions'!D:D,"Bank") -> 6432 | G203: =B203-C203 -> 7826 | H203: =J202 -> 14250 | I203: =SUMIFS('Daily Transactions'!C:C,'Daily Transactions'!A:A,$A203,'Daily Transactions'!B:B,"Sales",'Daily Transactions'!D:D,"Cash") -> 2930 | J203: =H203+I203-D203-E203 -> 11450 | L203: =SUMIFS('Daily Transactions'!C:C,'Daily Transactions'!A:A,$A203,'Daily Transactions'!B:B,"Cash Shortage",'Daily Transactions'!D:D,"Cash") -> 0
A204: =A203+1 -> 45858 | B204: =SUMIFS('Daily Transactions'!C:C,'Daily Transactions'!A:A,$A204,'Daily Transactions'!B:B,"Sales") -> 27975 | C204: =SUMIFS('Daily Transactions'!C:C,'Daily Transactions'!A:A,$A204,'Daily Transactions'!B:B,"<>Sales") -> 20902 | D204: =SUMIFS('Daily Transactions'!C:C,'Daily Transactions'!A:A,$A204,'Daily Transactions'!B:B,"<>Sales",'Daily Transactions'!D:D,"Cash") -> 80 | E204: =SUMIFS('Daily Transactions'!C:C,'Daily Transactions'!A:A,$A204,'Daily Transactions'!B:B,"<>Sales",'Daily Transactions'!D:D,"Bank_Cash") -> 10480 | F204: =SUMIFS('Daily Transactions'!C:C,'Daily Transactions'!A:A,$A204,'Daily Transactions'!B:B,"<>Sales",'Daily Transactions'!D:D,"Bank") -> 10342 | G204: =B204-C204 -> 7073 | H204: =J203 -> 11450 | I204: =SUMIFS('Daily Transactions'!C:C,'Daily Transactions'!A:A,$A204,'Daily Transactions'!B:B,"Sales",'Daily Transactions'!D:D,"Cash") -> 2960 | J204: =H204+I204-D204-E204 -> 3850 | L204: =SUMIFS('Daily Transactions'!C:C,'Daily Transactions'!A:A,$A204,'Daily Transactions'!B:B,"Cash Shortage",'Daily Transactions'!D:D,"Cash") -> 0
A205: =A204+1 -> 45859 | B205: =SUMIFS('Daily Transactions'!C:C,'Daily Transactions'!A:A,$A205,'Daily Transactions'!B:B,"Sales") -> 6623 | C205: =SUMIFS('Daily Transactions'!C:C,'Daily Transactions'!A:A,$A205,'Daily Transactions'!B:B,"<>Sales") -> 14715 | D205: =SUMIFS('Daily Transactions'!C:C,'Daily Transactions'!A:A,$A205,'Daily Transactions'!B:B,"<>Sales",'Daily Transactions'!D:D,"Cash") -> 380 | E205: =SUMIFS('Daily Transactions'!C:C,'Daily Transactions'!A:A,$A205,'Daily Transactions'!B:B,"<>Sales",'Daily Transactions'!D:D,"Bank_Cash") -> 1250 | F205: =SUMIFS('Daily Transactions'!C:C,'Daily Transactions'!A:A,$A205,'Daily Transactions'!B:B,"<>Sales",'Daily Transactions'!D:D,"Bank") -> 13085 | G205: =B205-C205 -> -8092 | H205: =J204 -> 3850 | I205: =SUMIFS('Daily Transactions'!C:C,'Daily Transactions'!A:A,$A205,'Daily Transactions'!B:B,"Sales",'Daily Transactions'!D:D,"Cash") -> 680 | J205: =H205+I205-D205-E205 -> 2900 | L205: =SUMIFS('Daily Transactions'!C:C,'Daily Transactions'!A:A,$A205,'Daily Transactions'!B:B,"Cash Shortage",'Daily Transactions'!D:D,"Cash") -> 0
A206: =A205+1 -> 45860 | B206: =SUMIFS('Daily Transactions'!C:C,'Daily Transactions'!A:A,$A206,'Daily Transactions'!B:B,"Sales") -> 17033 | C206: =SUMIFS('Daily Transactions'!C:C,'Daily Transactions'!A:A,$A206,'Daily Transactions'!B:B,"<>Sales") -> 5606 | D206: =SUMIFS('Daily Transactions'!C:C,'Daily Transactions'!A:A,$A206,'Daily Transactions'!B:B,"<>Sales",'Daily Transactions'!D:D,"Cash") -> 55 | E206: =SUMIFS('Daily Transactions'!C:C,'Daily Transactions'!A:A,$A206,'Daily Transactions'!B:B,"<>Sales",'Daily Transactions'!D:D,"Bank_Cash") -> 700 | F206: =SUMIFS('Daily Transactions'!C:C,'Daily Transactions'!A:A,$A206,'Daily Transactions'!B:B,"<>Sales",'Daily Transactions'!D:D,"Bank") -> 4851 | G206: =B206-C206 -> 11427 | H206: =J205 -> 2900 | I206: =SUMIFS('Daily Transactions'!C:C,'Daily Transactions'!A:A,$A206,'Daily Transactions'!B:B,"Sales",'Daily Transactions'!D:D,"Cash") -> 3455 | J206: =H206+I206-D206-E206 -> 5600 | L206: =SUMIFS('Daily Transactions'!C:C,'Daily Transactions'!A:A,$A206,'Daily Transactions'!B:B,"Cash Shortage",'Daily Transactions'!D:D,"Cash") -> 0 | M206: 4500
A207: =A206+1 -> 45861 | B207: =SUMIFS('Daily Transactions'!C:C,'Daily Transactions'!A:A,$A207,'Daily Transactions'!B:B,"Sales") -> 24067 | C207: =SUMIFS('Daily Transactions'!C:C,'Daily Transactions'!A:A,$A207,'Daily Transactions'!B:B,"<>Sales") -> 8255 | D207: =SUMIFS('Daily Transactions'!C:C,'Daily Transactions'!A:A,$A207,'Daily Transactions'!B:B,"<>Sales",'Daily Transactions'!D:D,"Cash") -> 2130 | E207: =SUMIFS('Daily Transactions'!C:C,'Daily Transactions'!A:A,$A207,'Daily Transactions'!B:B,"<>Sales",'Daily Transactions'!D:D,"Bank_Cash") -> 0 | F207: =SUMIFS('Daily Transactions'!C:C,'Daily Transactions'!A:A,$A207,'Daily Transactions'!B:B,"<>Sales",'Daily Transactions'!D:D,"Bank") -> 6125 | G207: =B207-C207 -> 15812 | H207: =J206 -> 5600 | I207: =SUMIFS('Daily Transactions'!C:C,'Daily Transactions'!A:A,$A207,'Daily Transactions'!B:B,"Sales",'Daily Transactions'!D:D,"Cash") -> 1850 | J207: =H207+I207-D207-E207 -> 5320 | L207: =SUMIFS('Daily Transactions'!C:C,'Daily Transactions'!A:A,$A207,'Daily Transactions'!B:B,"Cash Shortage",'Daily Transactions'!D:D,"Cash") -> 0
A208: =A207+1 -> 45862 | B208: =SUMIFS('Daily Transactions'!C:C,'Daily Transactions'!A:A,$A208,'Daily Transactions'!B:B,"Sales") -> 14789 | C208: =SUMIFS('Daily Transactions'!C:C,'Daily Transactions'!A:A,$A208,'Daily Transactions'!B:B,"<>Sales") -> 13725 | D208: =SUMIFS('Daily Transactions'!C:C,'Daily Transactions'!A:A,$A208,'Daily Transactions'!B:B,"<>Sales",'Daily Transactions'!D:D,"Cash") -> 170 | E208: =SUMIFS('Daily Transactions'!C:C,'Daily Transactions'!A:A,$A208,'Daily Transactions'!B:B,"<>Sales",'Daily Transactions'!D:D,"Bank_Cash") -> 0 | F208: =SUMIFS('Daily Transactions'!C:C,'Daily Transactions'!A:A,$A208,'Daily Transactions'!B:B,"<>Sales",'Daily Transactions'!D:D,"Bank") -> 13555 | G208: =B208-C208 -> 1064 | H208: =J207 -> 5320 | I208: =SUMIFS('Daily Transactions'!C:C,'Daily Transactions'!A:A,$A208,'Daily Transactions'!B:B,"Sales",'Daily Transactions'!D:D,"Cash") -> 1050 | J208: =H208+I208-D208-E208 -> 6200 | L208: =SUMIFS('Daily Transactions'!C:C,'Daily Transactions'!A:A,$A208,'Daily Transactions'!B:B,"Cash Shortage",'Daily Transactions'!D:D,"Cash") -> 0
A209: =A208+1 -> 45863 | B209: =SUMIFS('Daily Transactions'!C:C,'Daily Transactions'!A:A,$A209,'Daily Transactions'!B:B,"Sales") -> 15490 | C209: =SUMIFS('Daily Transactions'!C:C,'Daily Transactions'!A:A,$A209,'Daily Transactions'!B:B,"<>Sales") -> 13227 | D209: =SUMIFS('Daily Transactions'!C:C,'Daily Transactions'!A:A,$A209,'Daily Transactions'!B:B,"<>Sales",'Daily Transactions'!D:D,"Cash") -> 55 | E209: =SUMIFS('Daily Transactions'!C:C,'Daily Transactions'!A:A,$A209,'Daily Transactions'!B:B,"<>Sales",'Daily Transactions'!D:D,"Bank_Cash") -> 3350 | F209: =SUMIFS('Daily Transactions'!C:C,'Daily Transactions'!A:A,$A209,'Daily Transactions'!B:B,"<>Sales",'Daily Transactions'!D:D,"Bank") -> 9822 | G209: =B209-C209 -> 2263 | H209: =J208 -> 6200 | I209: =SUMIFS('Daily Transactions'!C:C,'Daily Transactions'!A:A,$A209,'Daily Transactions'!B:B,"Sales",'Daily Transactions'!D:D,"Cash") -> 1855 | J209: =H209+I209-D209-E209 -> 4650 | L209: =SUMIFS('Daily Transactions'!C:C,'Daily Transactions'!A:A,$A209,'Daily Transactions'!B:B,"Cash Shortage",'Daily Transactions'!D:D,"Cash") -> 0
A210: =A209+1 -> 45864 | B210: =SUMIFS('Daily Transactions'!C:C,'Daily Transactions'!A:A,$A210,'Daily Transactions'!B:B,"Sales") -> 21682 | C210: =SUMIFS('Daily Transactions'!C:C,'Daily Transactions'!A:A,$A210,'Daily Transactions'!B:B,"<>Sales") -> 19627 | D210: =SUMIFS('Daily Transactions'!C:C,'Daily Transactions'!A:A,$A210,'Daily Transactions'!B:B,"<>Sales",'Daily Transactions'!D:D,"Cash") -> 60 | E210: =SUMIFS('Daily Transactions'!C:C,'Daily Transactions'!A:A,$A210,'Daily Transactions'!B:B,"<>Sales",'Daily Transactions'!D:D,"Bank_Cash") -> 500 | F210: =SUMIFS('Daily Transactions'!C:C,'Daily Transactions'!A:A,$A210,'Daily Transactions'!B:B,"<>Sales",'Daily Transactions'!D:D,"Bank") -> 19067 | G210: =B210-C210 -> 2055 | H210: =J209 -> 4650 | I210: =SUMIFS('Daily Transactions'!C:C,'Daily Transactions'!A:A,$A210,'Daily Transactions'!B:B,"Sales",'Daily Transactions'!D:D,"Cash") -> 2360 | J210: =H210+I210-D210-E210 -> 6450 | L210: =SUMIFS('Daily Transactions'!C:C,'Daily Transactions'!A:A,$A210,'Daily Transactions'!B:B,"Cash Shortage",'Daily Transactions'!D:D,"Cash") -> 0
A211: =A210+1 -> 45865 | B211: =SUMIFS('Daily Transactions'!C:C,'Daily Transactions'!A:A,$A211,'Daily Transactions'!B:B,"Sales") -> 15920 | C211: =SUMIFS('Daily Transactions'!C:C,'Daily Transactions'!A:A,$A211,'Daily Transactions'!B:B,"<>Sales") -> 7647 | D211: =SUMIFS('Daily Transactions'!C:C,'Daily Transactions'!A:A,$A211,'Daily Transactions'!B:B,"<>Sales",'Daily Transactions'!D:D,"Cash") -> 110 | E211: =SUMIFS('Daily Transactions'!C:C,'Daily Transactions'!A:A,$A211,'Daily Transactions'!B:B,"<>Sales",'Daily Transactions'!D:D,"Bank_Cash") -> 1505 | F211: =SUMIFS('Daily Transactions'!C:C,'Daily Transactions'!A:A,$A211,'Daily Transactions'!B:B,"<>Sales",'Daily Transactions'!D:D,"Bank") -> 6032 | G211: =B211-C211 -> 8273 | H211: =J210 -> 6450 | I211: =SUMIFS('Daily Transactions'!C:C,'Daily Transactions'!A:A,$A211,'Daily Transactions'!B:B,"Sales",'Daily Transactions'!D:D,"Cash") -> 3865 | J211: =H211+I211-D211-E211 -> 8700 | L211: =SUMIFS('Daily Transactions'!C:C,'Daily Transactions'!A:A,$A211,'Daily Transactions'!B:B,"Cash Shortage",'Daily Transactions'!D:D,"Cash") -> 0
A212: =A211+1 -> 45866 | B212: =SUMIFS('Daily Transactions'!C:C,'Daily Transactions'!A:A,$A212,'Daily Transactions'!B:B,"Sales") -> 13269 | C212: =SUMIFS('Daily Transactions'!C:C,'Daily Transactions'!A:A,$A212,'Daily Transactions'!B:B,"<>Sales") -> 7638 | D212: =SUMIFS('Daily Transactions'!C:C,'Daily Transactions'!A:A,$A212,'Daily Transactions'!B:B,"<>Sales",'Daily Transactions'!D:D,"Cash") -> 90 | E212: =SUMIFS('Daily Transactions'!C:C,'Daily Transactions'!A:A,$A212,'Daily Transactions'!B:B,"<>Sales",'Daily Transactions'!D:D,"Bank_Cash") -> 2030 | F212: =SUMIFS('Daily Transactions'!C:C,'Daily Transactions'!A:A,$A212,'Daily Transactions'!B:B,"<>Sales",'Daily Transactions'!D:D,"Bank") -> 5518 | G212: =B212-C212 -> 5631 | H212: =J211 -> 8700 | I212: =SUMIFS('Daily Transactions'!C:C,'Daily Transactions'!A:A,$A212,'Daily Transactions'!B:B,"Sales",'Daily Transactions'!D:D,"Cash") -> 1720 | J212: =H212+I212-D212-E212 -> 8300 | L212: =SUMIFS('Daily Transactions'!C:C,'Daily Transactions'!A:A,$A212,'Daily Transactions'!B:B,"Cash Shortage",'Daily Transactions'!D:D,"Cash") -> 0
A213: =A212+1 -> 45867 | B213: =SUMIFS('Daily Transactions'!C:C,'Daily Transactions'!A:A,$A213,'Daily Transactions'!B:B,"Sales") -> 8195 | C213: =SUMIFS('Daily Transactions'!C:C,'Daily Transactions'!A:A,$A213,'Daily Transactions'!B:B,"<>Sales") -> 6315 | D213: =SUMIFS('Daily Transactions'!C:C,'Daily Transactions'!A:A,$A213,'Daily Transactions'!B:B,"<>Sales",'Daily Transactions'!D:D,"Cash") -> 30 | E213: =SUMIFS('Daily Transactions'!C:C,'Daily Transactions'!A:A,$A213,'Daily Transactions'!B:B,"<>Sales",'Daily Transactions'!D:D,"Bank_Cash") -> 810 | F213: =SUMIFS('Daily Transactions'!C:C,'Daily Transactions'!A:A,$A213,'Daily Transactions'!B:B,"<>Sales",'Daily Transactions'!D:D,"Bank") -> 5475 | G213: =B213-C213 -> 1880 | H213: =J212 -> 8300 | I213: =SUMIFS('Daily Transactions'!C:C,'Daily Transactions'!A:A,$A213,'Daily Transactions'!B:B,"Sales",'Daily Transactions'!D:D,"Cash") -> 940 | J213: =H213+I213-D213-E213 -> 8400 | L213: =SUMIFS('Daily Transactions'!C:C,'Daily Transactions'!A:A,$A213,'Daily Transactions'!B:B,"Cash Shortage",'Daily Transactions'!D:D,"Cash") -> 0
A214: =A213+1 -> 45868 | B214: =SUMIFS('Daily Transactions'!C:C,'Daily Transactions'!A:A,$A214,'Daily Transactions'!B:B,"Sales") -> 14556 | C214: =SUMIFS('Daily Transactions'!C:C,'Daily Transactions'!A:A,$A214,'Daily Transactions'!B:B,"<>Sales") -> 4865 | D214: =SUMIFS('Daily Transactions'!C:C,'Daily Transactions'!A:A,$A214,'Daily Transactions'!B:B,"<>Sales",'Daily Transactions'!D:D,"Cash") -> 69 | E214: =SUMIFS('Daily Transactions'!C:C,'Daily Transactions'!A:A,$A214,'Daily Transactions'!B:B,"<>Sales",'Daily Transactions'!D:D,"Bank_Cash") -> 2920 | F214: =SUMIFS('Daily Transactions'!C:C,'Daily Transactions'!A:A,$A214,'Daily Transactions'!B:B,"<>Sales",'Daily Transactions'!D:D,"Bank") -> 1876 | G214: =B214-C214 -> 9691 | H214: =J213 -> 8400 | I214: =SUMIFS('Daily Transactions'!C:C,'Daily Transactions'!A:A,$A214,'Daily Transactions'!B:B,"Sales",'Daily Transactions'!D:D,"Cash") -> 3789 | J214: =H214+I214-D214-E214 -> 9200 | L214: =SUMIFS('Daily Transactions'!C:C,'Daily Transactions'!A:A,$A214,'Daily Transactions'!B:B,"Cash Shortage",'Daily Transactions'!D:D,"Cash") -> 0
A215: =A214+1 -> 45869 | B215: =SUMIFS('Daily Transactions'!C:C,'Daily Transactions'!A:A,$A215,'Daily Transactions'!B:B,"Sales") -> 18448 | C215: =SUMIFS('Daily Transactions'!C:C,'Daily Transactions'!A:A,$A215,'Daily Transactions'!B:B,"<>Sales") -> 6462 | D215: =SUMIFS('Daily Transactions'!C:C,'Daily Transactions'!A:A,$A215,'Daily Transactions'!B:B,"<>Sales",'Daily Transactions'!D:D,"Cash") -> 69 | E215: =SUMIFS('Daily Transactions'!C:C,'Daily Transactions'!A:A,$A215,'Daily Transactions'!B:B,"<>Sales",'Daily Transactions'!D:D,"Bank_Cash") -> 2780 | F215: =SUMIFS('Daily Transactions'!C:C,'Daily Transactions'!A:A,$A215,'Daily Transactions'!B:B,"<>Sales",'Daily Transactions'!D:D,"Bank") -> 3613 | G215: =B215-C215 -> 11986 | H215: =J214 -> 9200 | I215: =SUMIFS('Daily Transactions'!C:C,'Daily Transactions'!A:A,$A215,'Daily Transactions'!B:B,"Sales",'Daily Transactions'!D:D,"Cash") -> 1949 | J215: =H215+I215-D215-E215 -> 8300 | L215: =SUMIFS('Daily Transactions'!C:C,'Daily Transactions'!A:A,$A215,'Daily Transactions'!B:B,"Cash Shortage",'Daily Transactions'!D:D,"Cash") -> 0
A216: =A215+1 -> 45870 | B216: =SUMIFS('Daily Transactions'!C:C,'Daily Transactions'!A:A,$A216,'Daily Transactions'!B:B,"Sales") -> 19092 | C216: =SUMIFS('Daily Transactions'!C:C,'Daily Transactions'!A:A,$A216,'Daily Transactions'!B:B,"<>Sales") -> 18652 | D216: =SUMIFS('Daily Transactions'!C:C,'Daily Transactions'!A:A,$A216,'Daily Transactions'!B:B,"<>Sales",'Daily Transactions'!D:D,"Cash") -> 120 | E216: =SUMIFS('Daily Transactions'!C:C,'Daily Transactions'!A:A,$A216,'Daily Transactions'!B:B,"<>Sales",'Daily Transactions'!D:D,"Bank_Cash") -> 710 | F216: =SUMIFS('Daily Transactions'!C:C,'Daily Transactions'!A:A,$A216,'Daily Transactions'!B:B,"<>Sales",'Daily Transactions'!D:D,"Bank") -> 17822 | G216: =B216-C216 -> 440 | H216: =J215 -> 8300 | I216: =SUMIFS('Daily Transactions'!C:C,'Daily Transactions'!A:A,$A216,'Daily Transactions'!B:B,"Sales",'Daily Transactions'!D:D,"Cash") -> 1880 | J216: =H216+I216-D216-E216 -> 9350 | L216: =SUMIFS('Daily Transactions'!C:C,'Daily Transactions'!A:A,$A216,'Daily Transactions'!B:B,"Cash Shortage",'Daily Transactions'!D:D,"Cash") -> 0
A217: =A216+1 -> 45871 | B217: =SUMIFS('Daily Transactions'!C:C,'Daily Transactions'!A:A,$A217,'Daily Transactions'!B:B,"Sales") -> 20005 | C217: =SUMIFS('Daily Transactions'!C:C,'Daily Transactions'!A:A,$A217,'Daily Transactions'!B:B,"<>Sales") -> 13416 | D217: =SUMIFS('Daily Transactions'!C:C,'Daily Transactions'!A:A,$A217,'Daily Transactions'!B:B,"<>Sales",'Daily Transactions'!D:D,"Cash") -> 275 | E217: =SUMIFS('Daily Transactions'!C:C,'Daily Transactions'!A:A,$A217,'Daily Transactions'!B:B,"<>Sales",'Daily Transactions'!D:D,"Bank_Cash") -> 2000 | F217: =SUMIFS('Daily Transactions'!C:C,'Daily Transactions'!A:A,$A217,'Daily Transactions'!B:B,"<>Sales",'Daily Transactions'!D:D,"Bank") -> 11141 | G217: =B217-C217 -> 6589 | H217: =J216 -> 9350 | I217: =SUMIFS('Daily Transactions'!C:C,'Daily Transactions'!A:A,$A217,'Daily Transactions'!B:B,"Sales",'Daily Transactions'!D:D,"Cash") -> 2675 | J217: =H217+I217-D217-E217 -> 9750 | L217: =SUMIFS('Daily Transactions'!C:C,'Daily Transactions'!A:A,$A217,'Daily Transactions'!B:B,"Cash Shortage",'Daily Transactions'!D:D,"Cash") -> 0
A218: =A217+1 -> 45872 | B218: =SUMIFS('Daily Transactions'!C:C,'Daily Transactions'!A:A,$A218,'Daily Transactions'!B:B,"Sales") -> 29422 | C218: =SUMIFS('Daily Transactions'!C:C,'Daily Transactions'!A:A,$A218,'Daily Transactions'!B:B,"<>Sales") -> 16277 | D218: =SUMIFS('Daily Transactions'!C:C,'Daily Transactions'!A:A,$A218,'Daily Transactions'!B:B,"<>Sales",'Daily Transactions'!D:D,"Cash") -> 4320 | E218: =SUMIFS('Daily Transactions'!C:C,'Daily Transactions'!A:A,$A218,'Daily Transactions'!B:B,"<>Sales",'Daily Transactions'!D:D,"Bank_Cash") -> 0 | F218: =SUMIFS('Daily Transactions'!C:C,'Daily Transactions'!A:A,$A218,'Daily Transactions'!B:B,"<>Sales",'Daily Transactions'!D:D,"Bank") -> 11957 | G218: =B218-C218 -> 13145 | H218: =J217 -> 9750 | I218: =SUMIFS('Daily Transactions'!C:C,'Daily Transactions'!A:A,$A218,'Daily Transactions'!B:B,"Sales",'Daily Transactions'!D:D,"Cash") -> 3559 | J218: =H218+I218-D218-E218 -> 8989 | L218: =SUMIFS('Daily Transactions'!C:C,'Daily Transactions'!A:A,$A218,'Daily Transactions'!B:B,"Cash Shortage",'Daily Transactions'!D:D,"Cash") -> 0 | M218: Cash in Counter | N218: 1070 | O218: To Bank Cash | P218: =2950+3800 -> 6750
A219: =A218+1 -> 45873 | B219: =SUMIFS('Daily Transactions'!C:C,'Daily Transactions'!A:A,$A219,'Daily Transactions'!B:B,"Sales") -> 10791 | C219: =SUMIFS('Daily Transactions'!C:C,'Daily Transactions'!A:A,$A219,'Daily Transactions'!B:B,"<>Sales") -> 14857 | D219: =SUMIFS('Daily Transactions'!C:C,'Daily Transactions'!A:A,$A219,'Daily Transactions'!B:B,"<>Sales",'Daily Transactions'!D:D,"Cash") -> 1725 | E219: =SUMIFS('Daily Transactions'!C:C,'Daily Transactions'!A:A,$A219,'Daily Transactions'!B:B,"<>Sales",'Daily Transactions'!D:D,"Bank_Cash") -> 2600 | F219: =SUMIFS('Daily Transactions'!C:C,'Daily Transactions'!A:A,$A219,'Daily Transactions'!B:B,"<>Sales",'Daily Transactions'!D:D,"Bank") -> 10532 | G219: =B219-C219 -> -4066 | H219: =J218 -> 8989 | I219: =SUMIFS('Daily Transactions'!C:C,'Daily Transactions'!A:A,$A219,'Daily Transactions'!B:B,"Sales",'Daily Transactions'!D:D,"Cash") -> 4025 | J219: =H219+I219-D219-E219 -> 8689 | L219: =SUMIFS('Daily Transactions'!C:C,'Daily Transactions'!A:A,$A219,'Daily Transactions'!B:B,"Cash Shortage",'Daily Transactions'!D:D,"Cash") -> 0 | M219: Cash in Counter | N219: 1030 | O219: To Bank Cash | P219: 1700
A220: =A219+1 -> 45874 | B220: =SUMIFS('Daily Transactions'!C:C,'Daily Transactions'!A:A,$A220,'Daily Transactions'!B:B,"Sales") -> 15968 | C220: =SUMIFS('Daily Transactions'!C:C,'Daily Transactions'!A:A,$A220,'Daily Transactions'!B:B,"<>Sales") -> 400 | D220: =SUMIFS('Daily Transactions'!C:C,'Daily Transactions'!A:A,$A220,'Daily Transactions'!B:B,"<>Sales",'Daily Transactions'!D:D,"Cash") -> 0 | E220: =SUMIFS('Daily Transactions'!C:C,'Daily Transactions'!A:A,$A220,'Daily Transactions'!B:B,"<>Sales",'Daily Transactions'!D:D,"Bank_Cash") -> 0 | F220: =SUMIFS('Daily Transactions'!C:C,'Daily Transactions'!A:A,$A220,'Daily Transactions'!B:B,"<>Sales",'Daily Transactions'!D:D,"Bank") -> 400 | G220: =B220-C220 -> 15568 | H220: =J219 -> 8689 | I220: =SUMIFS('Daily Transactions'!C:C,'Daily Transactions'!A:A,$A220,'Daily Transactions'!B:B,"Sales",'Daily Transactions'!D:D,"Cash") -> 3035 | J220: =H220+I220-D220-E220 -> 11724 | L220: =SUMIFS('Daily Transactions'!C:C,'Daily Transactions'!A:A,$A220,'Daily Transactions'!B:B,"Cash Shortage",'Daily Transactions'!D:D,"Cash") -> 0
A221: =A220+1 -> 45875 | B221: =SUMIFS('Daily Transactions'!C:C,'Daily Transactions'!A:A,$A221,'Daily Transactions'!B:B,"Sales") -> 10684 | C221: =SUMIFS('Daily Transactions'!C:C,'Daily Transactions'!A:A,$A221,'Daily Transactions'!B:B,"<>Sales") -> 8521 | D221: =SUMIFS('Daily Transactions'!C:C,'Daily Transactions'!A:A,$A221,'Daily Transactions'!B:B,"<>Sales",'Daily Transactions'!D:D,"Cash") -> 622 | E221: =SUMIFS('Daily Transactions'!C:C,'Daily Transactions'!A:A,$A221,'Daily Transactions'!B:B,"<>Sales",'Daily Transactions'!D:D,"Bank_Cash") -> 2200 | F221: =SUMIFS('Daily Transactions'!C:C,'Daily Transactions'!A:A,$A221,'Daily Transactions'!B:B,"<>Sales",'Daily Transactions'!D:D,"Bank") -> 5699 | G221: =B221-C221 -> 2163 | H221: =J220 -> 11724 | I221: =SUMIFS('Daily Transactions'!C:C,'Daily Transactions'!A:A,$A221,'Daily Transactions'!B:B,"Sales",'Daily Transactions'!D:D,"Cash") -> 1825 | J221: =H221+I221-D221-E221 -> 10727 | L221: =SUMIFS('Daily Transactions'!C:C,'Daily Transactions'!A:A,$A221,'Daily Transactions'!B:B,"Cash Shortage",'Daily Transactions'!D:D,"Cash") -> 0
A222: =A221+1 -> 45876 | B222: =SUMIFS('Daily Transactions'!C:C,'Daily Transactions'!A:A,$A222,'Daily Transactions'!B:B,"Sales") -> 22687 | C222: =SUMIFS('Daily Transactions'!C:C,'Daily Transactions'!A:A,$A222,'Daily Transactions'!B:B,"<>Sales") -> 993 | D222: =SUMIFS('Daily Transactions'!C:C,'Daily Transactions'!A:A,$A222,'Daily Transactions'!B:B,"<>Sales",'Daily Transactions'!D:D,"Cash") -> 0 | E222: =SUMIFS('Daily Transactions'!C:C,'Daily Transactions'!A:A,$A222,'Daily Transactions'!B:B,"<>Sales",'Daily Transactions'!D:D,"Bank_Cash") -> 0 | F222: =SUMIFS('Daily Transactions'!C:C,'Daily Transactions'!A:A,$A222,'Daily Transactions'!B:B,"<>Sales",'Daily Transactions'!D:D,"Bank") -> 993 | G222: =B222-C222 -> 21694 | H222: =J221 -> 10727 | I222: =SUMIFS('Daily Transactions'!C:C,'Daily Transactions'!A:A,$A222,'Daily Transactions'!B:B,"Sales",'Daily Transactions'!D:D,"Cash") -> 4147 | J222: =H222+I222-D222-E222 -> 14874 | L222: =SUMIFS('Daily Transactions'!C:C,'Daily Transactions'!A:A,$A222,'Daily Transactions'!B:B,"Cash Shortage",'Daily Transactions'!D:D,"Cash") -> 0
A223: =A222+1 -> 45877 | B223: =SUMIFS('Daily Transactions'!C:C,'Daily Transactions'!A:A,$A223,'Daily Transactions'!B:B,"Sales") -> 19692 | C223: =SUMIFS('Daily Transactions'!C:C,'Daily Transactions'!A:A,$A223,'Daily Transactions'!B:B,"<>Sales") -> 22198 | D223: =SUMIFS('Daily Transactions'!C:C,'Daily Transactions'!A:A,$A223,'Daily Transactions'!B:B,"<>Sales",'Daily Transactions'!D:D,"Cash") -> 0 | E223: =SUMIFS('Daily Transactions'!C:C,'Daily Transactions'!A:A,$A223,'Daily Transactions'!B:B,"<>Sales",'Daily Transactions'!D:D,"Bank_Cash") -> 5075 | F223: =SUMIFS('Daily Transactions'!C:C,'Daily Transactions'!A:A,$A223,'Daily Transactions'!B:B,"<>Sales",'Daily Transactions'!D:D,"Bank") -> 17123 | G223: =B223-C223 -> -2506 | H223: =J222 -> 14874 | I223: =SUMIFS('Daily Transactions'!C:C,'Daily Transactions'!A:A,$A223,'Daily Transactions'!B:B,"Sales",'Daily Transactions'!D:D,"Cash") -> 1180 | J223: =H223+I223-D223-E223 -> 10979 | L223: =SUMIFS('Daily Transactions'!C:C,'Daily Transactions'!A:A,$A223,'Daily Transactions'!B:B,"Cash Shortage",'Daily Transactions'!D:D,"Cash") -> 0 | N223: 3900 | P223: 3265 | U223: 1600
A224: =A223+1 -> 45878 | B224: =SUMIFS('Daily Transactions'!C:C,'Daily Transactions'!A:A,$A224,'Daily Transactions'!B:B,"Sales") -> 16217 | C224: =SUMIFS('Daily Transactions'!C:C,'Daily Transactions'!A:A,$A224,'Daily Transactions'!B:B,"<>Sales") -> 32195 | D224: =SUMIFS('Daily Transactions'!C:C,'Daily Transactions'!A:A,$A224,'Daily Transactions'!B:B,"<>Sales",'Daily Transactions'!D:D,"Cash") -> 2187 | E224: =SUMIFS('Daily Transactions'!C:C,'Daily Transactions'!A:A,$A224,'Daily Transactions'!B:B,"<>Sales",'Daily Transactions'!D:D,"Bank_Cash") -> 0 | F224: =SUMIFS('Daily Transactions'!C:C,'Daily Transactions'!A:A,$A224,'Daily Transactions'!B:B,"<>Sales",'Daily Transactions'!D:D,"Bank") -> 30008 | G224: =B224-C224 -> -15978 | H224: =J223 -> 10979 | I224: =SUMIFS('Daily Transactions'!C:C,'Daily Transactions'!A:A,$A224,'Daily Transactions'!B:B,"Sales",'Daily Transactions'!D:D,"Cash") -> 2189 | J224: =H224+I224-D224-E224 -> 10981 | L224: =SUMIFS('Daily Transactions'!C:C,'Daily Transactions'!A:A,$A224,'Daily Transactions'!B:B,"Cash Shortage",'Daily Transactions'!D:D,"Cash") -> 0 | N224: =N223-2815 -> 1085 | P224: =P223-J223 -> -7714
A225: =A224+1 -> 45879 | B225: =SUMIFS('Daily Transactions'!C:C,'Daily Transactions'!A:A,$A225,'Daily Transactions'!B:B,"Sales") -> 30536 | C225: =SUMIFS('Daily Transactions'!C:C,'Daily Transactions'!A:A,$A225,'Daily Transactions'!B:B,"<>Sales") -> 7323 | D225: =SUMIFS('Daily Transactions'!C:C,'Daily Transactions'!A:A,$A225,'Daily Transactions'!B:B,"<>Sales",'Daily Transactions'!D:D,"Cash") -> 2430 | E225: =SUMIFS('Daily Transactions'!C:C,'Daily Transactions'!A:A,$A225,'Daily Transactions'!B:B,"<>Sales",'Daily Transactions'!D:D,"Bank_Cash") -> 0 | F225: =SUMIFS('Daily Transactions'!C:C,'Daily Transactions'!A:A,$A225,'Daily Transactions'!B:B,"<>Sales",'Daily Transactions'!D:D,"Bank") -> 4893 | G225: =B225-C225 -> 23213 | H225: =J224 -> 10981 | I225: =SUMIFS('Daily Transactions'!C:C,'Daily Transactions'!A:A,$A225,'Daily Transactions'!B:B,"Sales",'Daily Transactions'!D:D,"Cash") -> 2960 | J225: =H225+I225-D225-E225 -> 11511 | L225: =SUMIFS('Daily Transactions'!C:C,'Daily Transactions'!A:A,$A225,'Daily Transactions'!B:B,"Cash Shortage",'Daily Transactions'!D:D,"Cash") -> 0
A226: =A225+1 -> 45880 | B226: =SUMIFS('Daily Transactions'!C:C,'Daily Transactions'!A:A,$A226,'Daily Transactions'!B:B,"Sales") -> 12816 | C226: =SUMIFS('Daily Transactions'!C:C,'Daily Transactions'!A:A,$A226,'Daily Transactions'!B:B,"<>Sales") -> 9054 | D226: =SUMIFS('Daily Transactions'!C:C,'Daily Transactions'!A:A,$A226,'Daily Transactions'!B:B,"<>Sales",'Daily Transactions'!D:D,"Cash") -> 1020 | E226: =SUMIFS('Daily Transactions'!C:C,'Daily Transactions'!A:A,$A226,'Daily Transactions'!B:B,"<>Sales",'Daily Transactions'!D:D,"Bank_Cash") -> 0 | F226: =SUMIFS('Daily Transactions'!C:C,'Daily Transactions'!A:A,$A226,'Daily Transactions'!B:B,"<>Sales",'Daily Transactions'!D:D,"Bank") -> 8034 | G226: =B226-C226 -> 3762 | H226: =J225 -> 11511 | I226: =SUMIFS('Daily Transactions'!C:C,'Daily Transactions'!A:A,$A226,'Daily Transactions'!B:B,"Sales",'Daily Transactions'!D:D,"Cash") -> 910 | J226: =H226+I226-D226-E226 -> 11401 | L226: =SUMIFS('Daily Transactions'!C:C,'Daily Transactions'!A:A,$A226,'Daily Transactions'!B:B,"Cash Shortage",'Daily Transactions'!D:D,"Cash") -> 0
A227: =A226+1 -> 45881 | B227: =SUMIFS('Daily Transactions'!C:C,'Daily Transactions'!A:A,$A227,'Daily Transactions'!B:B,"Sales") -> 9246 | C227: =SUMIFS('Daily Transactions'!C:C,'Daily Transactions'!A:A,$A227,'Daily Transactions'!B:B,"<>Sales") -> 2863 | D227: =SUMIFS('Daily Transactions'!C:C,'Daily Transactions'!A:A,$A227,'Daily Transactions'!B:B,"<>Sales",'Daily Transactions'!D:D,"Cash") -> 100 | E227: =SUMIFS('Daily Transactions'!C:C,'Daily Transactions'!A:A,$A227,'Daily Transactions'!B:B,"<>Sales",'Daily Transactions'!D:D,"Bank_Cash") -> 0 | F227: =SUMIFS('Daily Transactions'!C:C,'Daily Transactions'!A:A,$A227,'Daily Transactions'!B:B,"<>Sales",'Daily Transactions'!D:D,"Bank") -> 2763 | G227: =B227-C227 -> 6383 | H227: =J226 -> 11401 | I227: =SUMIFS('Daily Transactions'!C:C,'Daily Transactions'!A:A,$A227,'Daily Transactions'!B:B,"Sales",'Daily Transactions'!D:D,"Cash") -> 1810 | J227: =H227+I227-D227-E227 -> 13111 | L227: =SUMIFS('Daily Transactions'!C:C,'Daily Transactions'!A:A,$A227,'Daily Transactions'!B:B,"Cash Shortage",'Daily Transactions'!D:D,"Cash") -> 0
A228: =A227+1 -> 45882 | B228: =SUMIFS('Daily Transactions'!C:C,'Daily Transactions'!A:A,$A228,'Daily Transactions'!B:B,"Sales") -> 10745 | C228: =SUMIFS('Daily Transactions'!C:C,'Daily Transactions'!A:A,$A228,'Daily Transactions'!B:B,"<>Sales") -> 15355 | D228: =SUMIFS('Daily Transactions'!C:C,'Daily Transactions'!A:A,$A228,'Daily Transactions'!B:B,"<>Sales",'Daily Transactions'!D:D,"Cash") -> 2050 | E228: =SUMIFS('Daily Transactions'!C:C,'Daily Transactions'!A:A,$A228,'Daily Transactions'!B:B,"<>Sales",'Daily Transactions'!D:D,"Bank_Cash") -> 0 | F228: =SUMIFS('Daily Transactions'!C:C,'Daily Transactions'!A:A,$A228,'Daily Transactions'!B:B,"<>Sales",'Daily Transactions'!D:D,"Bank") -> 13305 | G228: =B228-C228 -> -4610 | H228: =J227 -> 13111 | I228: =SUMIFS('Daily Transactions'!C:C,'Daily Transactions'!A:A,$A228,'Daily Transactions'!B:B,"Sales",'Daily Transactions'!D:D,"Cash") -> 1310 | J228: =H228+I228-D228-E228 -> 12371 | L228: =SUMIFS('Daily Transactions'!C:C,'Daily Transactions'!A:A,$A228,'Daily Transactions'!B:B,"Cash Shortage",'Daily Transactions'!D:D,"Cash") -> 0
A229: =A228+1 -> 45883 | B229: =SUMIFS('Daily Transactions'!C:C,'Daily Transactions'!A:A,$A229,'Daily Transactions'!B:B,"Sales") -> 19832 | C229: =SUMIFS('Daily Transactions'!C:C,'Daily Transactions'!A:A,$A229,'Daily Transactions'!B:B,"<>Sales") -> 4967 | D229: =SUMIFS('Daily Transactions'!C:C,'Daily Transactions'!A:A,$A229,'Daily Transactions'!B:B,"<>Sales",'Daily Transactions'!D:D,"Cash") -> 905 | E229: =SUMIFS('Daily Transactions'!C:C,'Daily Transactions'!A:A,$A229,'Daily Transactions'!B:B,"<>Sales",'Daily Transactions'!D:D,"Bank_Cash") -> 0 | F229: =SUMIFS('Daily Transactions'!C:C,'Daily Transactions'!A:A,$A229,'Daily Transactions'!B:B,"<>Sales",'Daily Transactions'!D:D,"Bank") -> 4062 | G229: =B229-C229 -> 14865 | H229: =J228 -> 12371 | I229: =SUMIFS('Daily Transactions'!C:C,'Daily Transactions'!A:A,$A229,'Daily Transactions'!B:B,"Sales",'Daily Transactions'!D:D,"Cash") -> 3750 | J229: =H229+I229-D229-E229 -> 15216 | L229: =SUMIFS('Daily Transactions'!C:C,'Daily Transactions'!A:A,$A229,'Daily Transactions'!B:B,"Cash Shortage",'Daily Transactions'!D:D,"Cash") -> 0
A230: =A229+1 -> 45884 | B230: =SUMIFS('Daily Transactions'!C:C,'Daily Transactions'!A:A,$A230,'Daily Transactions'!B:B,"Sales") -> 22981 | C230: =SUMIFS('Daily Transactions'!C:C,'Daily Transactions'!A:A,$A230,'Daily Transactions'!B:B,"<>Sales") -> 11822.5 | D230: =SUMIFS('Daily Transactions'!C:C,'Daily Transactions'!A:A,$A230,'Daily Transactions'!B:B,"<>Sales",'Daily Transactions'!D:D,"Cash") -> 4470 | E230: =SUMIFS('Daily Transactions'!C:C,'Daily Transactions'!A:A,$A230,'Daily Transactions'!B:B,"<>Sales",'Daily Transactions'!D:D,"Bank_Cash") -> 0 | F230: =SUMIFS('Daily Transactions'!C:C,'Daily Transactions'!A:A,$A230,'Daily Transactions'!B:B,"<>Sales",'Daily Transactions'!D:D,"Bank") -> 7352.5 | G230: =B230-C230 -> 11158.5 | H230: =J229 -> 15216 | I230: =SUMIFS('Daily Transactions'!C:C,'Daily Transactions'!A:A,$A230,'Daily Transactions'!B:B,"Sales",'Daily Transactions'!D:D,"Cash") -> 3070 | J230: =H230+I230-D230-E230 -> 13816 | L230: =SUMIFS('Daily Transactions'!C:C,'Daily Transactions'!A:A,$A230,'Daily Transactions'!B:B,"Cash Shortage",'Daily Transactions'!D:D,"Cash") -> 0
A231: =A230+1 -> 45885 | B231: =SUMIFS('Daily Transactions'!C:C,'Daily Transactions'!A:A,$A231,'Daily Transactions'!B:B,"Sales") -> 15515 | C231: =SUMIFS('Daily Transactions'!C:C,'Daily Transactions'!A:A,$A231,'Daily Transactions'!B:B,"<>Sales") -> 10953 | D231: =SUMIFS('Daily Transactions'!C:C,'Daily Transactions'!A:A,$A231,'Daily Transactions'!B:B,"<>Sales",'Daily Transactions'!D:D,"Cash") -> 3900 | E231: =SUMIFS('Daily Transactions'!C:C,'Daily Transactions'!A:A,$A231,'Daily Transactions'!B:B,"<>Sales",'Daily Transactions'!D:D,"Bank_Cash") -> 0 | F231: =SUMIFS('Daily Transactions'!C:C,'Daily Transactions'!A:A,$A231,'Daily Transactions'!B:B,"<>Sales",'Daily Transactions'!D:D,"Bank") -> 7053 | G231: =B231-C231 -> 4562 | H231: =J230 -> 13816 | I231: =SUMIFS('Daily Transactions'!C:C,'Daily Transactions'!A:A,$A231,'Daily Transactions'!B:B,"Sales",'Daily Transactions'!D:D,"Cash") -> 2530 | J231: =H231+I231-D231-E231 -> 12446 | L231: =SUMIFS('Daily Transactions'!C:C,'Daily Transactions'!A:A,$A231,'Daily Transactions'!B:B,"Cash Shortage",'Daily Transactions'!D:D,"Cash") -> 0
A232: =A231+1 -> 45886 | B232: =SUMIFS('Daily Transactions'!C:C,'Daily Transactions'!A:A,$A232,'Daily Transactions'!B:B,"Sales") -> 19547 | C232: =SUMIFS('Daily Transactions'!C:C,'Daily Transactions'!A:A,$A232,'Daily Transactions'!B:B,"<>Sales") -> 12224 | D232: =SUMIFS('Daily Transactions'!C:C,'Daily Transactions'!A:A,$A232,'Daily Transactions'!B:B,"<>Sales",'Daily Transactions'!D:D,"Cash") -> 2994 | E232: =SUMIFS('Daily Transactions'!C:C,'Daily Transactions'!A:A,$A232,'Daily Transactions'!B:B,"<>Sales",'Daily Transactions'!D:D,"Bank_Cash") -> 0 | F232: =SUMIFS('Daily Transactions'!C:C,'Daily Transactions'!A:A,$A232,'Daily Transactions'!B:B,"<>Sales",'Daily Transactions'!D:D,"Bank") -> 9230 | G232: =B232-C232 -> 7323 | H232: =J231 -> 12446 | I232: =SUMIFS('Daily Transactions'!C:C,'Daily Transactions'!A:A,$A232,'Daily Transactions'!B:B,"Sales",'Daily Transactions'!D:D,"Cash") -> 2105 | J232: =H232+I232-D232-E232 -> 11557 | L232: =SUMIFS('Daily Transactions'!C:C,'Daily Transactions'!A:A,$A232,'Daily Transactions'!B:B,"Cash Shortage",'Daily Transactions'!D:D,"Cash") -> 87
A233: =A232+1 -> 45887 | B233: =SUMIFS('Daily Transactions'!C:C,'Daily Transactions'!A:A,$A233,'Daily Transactions'!B:B,"Sales") -> 9310 | C233: =SUMIFS('Daily Transactions'!C:C,'Daily Transactions'!A:A,$A233,'Daily Transactions'!B:B,"<>Sales") -> 14865 | D233: =SUMIFS('Daily Transactions'!C:C,'Daily Transactions'!A:A,$A233,'Daily Transactions'!B:B,"<>Sales",'Daily Transactions'!D:D,"Cash") -> 830 | E233: =SUMIFS('Daily Transactions'!C:C,'Daily Transactions'!A:A,$A233,'Daily Transactions'!B:B,"<>Sales",'Daily Transactions'!D:D,"Bank_Cash") -> 0 | F233: =SUMIFS('Daily Transactions'!C:C,'Daily Transactions'!A:A,$A233,'Daily Transactions'!B:B,"<>Sales",'Daily Transactions'!D:D,"Bank") -> 14035 | G233: =B233-C233 -> -5555 | H233: =J232 -> 11557 | I233: =SUMIFS('Daily Transactions'!C:C,'Daily Transactions'!A:A,$A233,'Daily Transactions'!B:B,"Sales",'Daily Transactions'!D:D,"Cash") -> 1650 | J233: =H233+I233-D233-E233 -> 12377 | L233: =SUMIFS('Daily Transactions'!C:C,'Daily Transactions'!A:A,$A233,'Daily Transactions'!B:B,"Cash Shortage",'Daily Transactions'!D:D,"Cash") -> 0
A234: =A233+1 -> 45888 | B234: =SUMIFS('Daily Transactions'!C:C,'Daily Transactions'!A:A,$A234,'Daily Transactions'!B:B,"Sales") -> 6269 | C234: =SUMIFS('Daily Transactions'!C:C,'Daily Transactions'!A:A,$A234,'Daily Transactions'!B:B,"<>Sales") -> 5614 | D234: =SUMIFS('Daily Transactions'!C:C,'Daily Transactions'!A:A,$A234,'Daily Transactions'!B:B,"<>Sales",'Daily Transactions'!D:D,"Cash") -> 120 | E234: =SUMIFS('Daily Transactions'!C:C,'Daily Transactions'!A:A,$A234,'Daily Transactions'!B:B,"<>Sales",'Daily Transactions'!D:D,"Bank_Cash") -> 0 | F234: =SUMIFS('Daily Transactions'!C:C,'Daily Transactions'!A:A,$A234,'Daily Transactions'!B:B,"<>Sales",'Daily Transactions'!D:D,"Bank") -> 5494 | G234: =B234-C234 -> 655 | H234: =J233 -> 12377 | I234: =SUMIFS('Daily Transactions'!C:C,'Daily Transactions'!A:A,$A234,'Daily Transactions'!B:B,"Sales",'Daily Transactions'!D:D,"Cash") -> 380 | J234: =H234+I234-D234-E234 -> 12637 | L234: =SUMIFS('Daily Transactions'!C:C,'Daily Transactions'!A:A,$A234,'Daily Transactions'!B:B,"Cash Shortage",'Daily Transactions'!D:D,"Cash") -> 0
A235: =A234+1 -> 45889 | B235: =SUMIFS('Daily Transactions'!C:C,'Daily Transactions'!A:A,$A235,'Daily Transactions'!B:B,"Sales") -> 11062 | C235: =SUMIFS('Daily Transactions'!C:C,'Daily Transactions'!A:A,$A235,'Daily Transactions'!B:B,"<>Sales") -> 2725 | D235: =SUMIFS('Daily Transactions'!C:C,'Daily Transactions'!A:A,$A235,'Daily Transactions'!B:B,"<>Sales",'Daily Transactions'!D:D,"Cash") -> 685 | E235: =SUMIFS('Daily Transactions'!C:C,'Daily Transactions'!A:A,$A235,'Daily Transactions'!B:B,"<>Sales",'Daily Transactions'!D:D,"Bank_Cash") -> 300 | F235: =SUMIFS('Daily Transactions'!C:C,'Daily Transactions'!A:A,$A235,'Daily Transactions'!B:B,"<>Sales",'Daily Transactions'!D:D,"Bank") -> 1740 | G235: =B235-C235 -> 8337 | H235: =J234 -> 12637 | I235: =SUMIFS('Daily Transactions'!C:C,'Daily Transactions'!A:A,$A235,'Daily Transactions'!B:B,"Sales",'Daily Transactions'!D:D,"Cash") -> 750 | J235: =H235+I235-D235-E235 -> 12402 | L235: =SUMIFS('Daily Transactions'!C:C,'Daily Transactions'!A:A,$A235,'Daily Transactions'!B:B,"Cash Shortage",'Daily Transactions'!D:D,"Cash") -> 0
A236: =A235+1 -> 45890 | B236: =SUMIFS('Daily Transactions'!C:C,'Daily Transactions'!A:A,$A236,'Daily Transactions'!B:B,"Sales") -> 16111 | C236: =SUMIFS('Daily Transactions'!C:C,'Daily Transactions'!A:A,$A236,'Daily Transactions'!B:B,"<>Sales") -> 20495 | D236: =SUMIFS('Daily Transactions'!C:C,'Daily Transactions'!A:A,$A236,'Daily Transactions'!B:B,"<>Sales",'Daily Transactions'!D:D,"Cash") -> 1088 | E236: =SUMIFS('Daily Transactions'!C:C,'Daily Transactions'!A:A,$A236,'Daily Transactions'!B:B,"<>Sales",'Daily Transactions'!D:D,"Bank_Cash") -> 0 | F236: =SUMIFS('Daily Transactions'!C:C,'Daily Transactions'!A:A,$A236,'Daily Transactions'!B:B,"<>Sales",'Daily Transactions'!D:D,"Bank") -> 19407 | G236: =B236-C236 -> -4384 | H236: =J235 -> 12402 | I236: =SUMIFS('Daily Transactions'!C:C,'Daily Transactions'!A:A,$A236,'Daily Transactions'!B:B,"Sales",'Daily Transactions'!D:D,"Cash") -> 2355 | J236: =H236+I236-D236-E236 -> 13669 | L236: =SUMIFS('Daily Transactions'!C:C,'Daily Transactions'!A:A,$A236,'Daily Transactions'!B:B,"Cash Shortage",'Daily Transactions'!D:D,"Cash") -> 0
... A242: =A241+1 -> 45896 | B242: =SUMIFS('Daily Transactions'!C:C,'Daily Transactions'!A:A,$A242,'Daily Transactions'!B:B,"Sales") -> 13226 | C242: =SUMIFS('Daily Transactions'!C:C,'Daily Transactions'!A:A,$A242,'Daily Transactions'!B:B,"<>Sales") -> 8392 | D242: =SUMIFS('Daily Transactions'!C:C,'Daily Transactions'!A:A,$A242,'Daily Transactions'!B:B,"<>Sales",'Daily Transactions'!D:D,"Cash") -> 80 | E242: =SUMIFS('Daily Transactions'!C:C,'Daily Transactions'!A:A,$A242,'Daily Transactions'!B:B,"<>Sales",'Daily Transactions'!D:D,"Bank_Cash") -> 2955 | F242: =SUMIFS('Daily Transactions'!C:C,'Daily Transactions'!A:A,$A242,'Daily Transactions'!B:B,"<>Sales",'Daily Transactions'!D:D,"Bank") -> 5357 | G242: =B242-C242 -> 4834 | H242: =J241 -> 15486 | I242: =SUMIFS('Daily Transactions'!C:C,'Daily Transactions'!A:A,$A242,'Daily Transactions'!B:B,"Sales",'Daily Transactions'!D:D,"Cash") -> 1310 | J242: =H242+I242-D242-E242 -> 13761 | L242: =SUMIFS('Daily Transactions'!C:C,'Daily Transactions'!A:A,$A242,'Daily Transactions'!B:B,"Cash Shortage",'Daily Transactions'!D:D,"Cash") -> 0
A243: =A242+1 -> 45897 | B243: =SUMIFS('Daily Transactions'!C:C,'Daily Transactions'!A:A,$A243,'Daily Transactions'!B:B,"Sales") -> 9055 | C243: =SUMIFS('Daily Transactions'!C:C,'Daily Transactions'!A:A,$A243,'Daily Transactions'!B:B,"<>Sales") -> 16011 | D243: =SUMIFS('Daily Transactions'!C:C,'Daily Transactions'!A:A,$A243,'Daily Transactions'!B:B,"<>Sales",'Daily Transactions'!D:D,"Cash") -> 1000 | E243: =SUMIFS('Daily Transactions'!C:C,'Daily Transactions'!A:A,$A243,'Daily Transactions'!B:B,"<>Sales",'Daily Transactions'!D:D,"Bank_Cash") -> 9681 | F243: =SUMIFS('Daily Transactions'!C:C,'Daily Transactions'!A:A,$A243,'Daily Transactions'!B:B,"<>Sales",'Daily Transactions'!D:D,"Bank") -> 5330 | G243: =B243-C243 -> -6956 | H243: =J242 -> 13761 | I243: =SUMIFS('Daily Transactions'!C:C,'Daily Transactions'!A:A,$A243,'Daily Transactions'!B:B,"Sales",'Daily Transactions'!D:D,"Cash") -> 2390 | J243: =H243+I243-D243-E243 -> 5470 | L243: =SUMIFS('Daily Transactions'!C:C,'Daily Transactions'!A:A,$A243,'Daily Transactions'!B:B,"Cash Shortage",'Daily Transactions'!D:D,"Cash") -> 0 | O243: =L243+30 -> 30
A244: =A243+1 -> 45898 | B244: =SUMIFS('Daily Transactions'!C:C,'Daily Transactions'!A:A,$A244,'Daily Transactions'!B:B,"Sales") -> 18643 | C244: =SUMIFS('Daily Transactions'!C:C,'Daily Transactions'!A:A,$A244,'Daily Transactions'!B:B,"<>Sales") -> 17262 | D244: =SUMIFS('Daily Transactions'!C:C,'Daily Transactions'!A:A,$A244,'Daily Transactions'!B:B,"<>Sales",'Daily Transactions'!D:D,"Cash") -> 10 | E244: =SUMIFS('Daily Transactions'!C:C,'Daily Transactions'!A:A,$A244,'Daily Transactions'!B:B,"<>Sales",'Daily Transactions'!D:D,"Bank_Cash") -> 760 | F244: =SUMIFS('Daily Transactions'!C:C,'Daily Transactions'!A:A,$A244,'Daily Transactions'!B:B,"<>Sales",'Daily Transactions'!D:D,"Bank") -> 16492 | G244: =B244-C244 -> 1381 | H244: =J243 -> 5470 | I244: =SUMIFS('Daily Transactions'!C:C,'Daily Transactions'!A:A,$A244,'Daily Transactions'!B:B,"Sales",'Daily Transactions'!D:D,"Cash") -> 1935 | J244: =H244+I244-D244-E244 -> 6635 | L244: =SUMIFS('Daily Transactions'!C:C,'Daily Transactions'!A:A,$A244,'Daily Transactions'!B:B,"Cash Shortage",'Daily Transactions'!D:D,"Cash") -> 0
A245: =A244+1 -> 45899 | B245: =SUMIFS('Daily Transactions'!C:C,'Daily Transactions'!A:A,$A245,'Daily Transactions'!B:B,"Sales") -> 16203 | C245: =SUMIFS('Daily Transactions'!C:C,'Daily Transactions'!A:A,$A245,'Daily Transactions'!B:B,"<>Sales") -> 6187 | D245: =SUMIFS('Daily Transactions'!C:C,'Daily Transactions'!A:A,$A245,'Daily Transactions'!B:B,"<>Sales",'Daily Transactions'!D:D,"Cash") -> 40 | E245: =SUMIFS('Daily Transactions'!C:C,'Daily Transactions'!A:A,$A245,'Daily Transactions'!B:B,"<>Sales",'Daily Transactions'!D:D,"Bank_Cash") -> 3581 | F245: =SUMIFS('Daily Transactions'!C:C,'Daily Transactions'!A:A,$A245,'Daily Transactions'!B:B,"<>Sales",'Daily Transactions'!D:D,"Bank") -> 2566 | G245: =B245-C245 -> 10016 | H245: =J244 -> 6635 | I245: =SUMIFS('Daily Transactions'!C:C,'Daily Transactions'!A:A,$A245,'Daily Transactions'!B:B,"Sales",'Daily Transactions'!D:D,"Cash") -> 1470 | J245: =H245+I245-D245-E245 -> 4484 | L245: =SUMIFS('Daily Transactions'!C:C,'Daily Transactions'!A:A,$A245,'Daily Transactions'!B:B,"Cash Shortage",'Daily Transactions'!D:D,"Cash") -> 0
A246: =A245+1 -> 45900 | B246: =SUMIFS('Daily Transactions'!C:C,'Daily Transactions'!A:A,$A246,'Daily Transactions'!B:B,"Sales") -> 16153 | C246: =SUMIFS('Daily Transactions'!C:C,'Daily Transactions'!A:A,$A246,'Daily Transactions'!B:B,"<>Sales") -> 26311 | D246: =SUMIFS('Daily Transactions'!C:C,'Daily Transactions'!A:A,$A246,'Daily Transactions'!B:B,"<>Sales",'Daily Transactions'!D:D,"Cash") -> 678 | E246: =SUMIFS('Daily Transactions'!C:C,'Daily Transactions'!A:A,$A246,'Daily Transactions'!B:B,"<>Sales",'Daily Transactions'!D:D,"Bank_Cash") -> 2550 | F246: =SUMIFS('Daily Transactions'!C:C,'Daily Transactions'!A:A,$A246,'Daily Transactions'!B:B,"<>Sales",'Daily Transactions'!D:D,"Bank") -> 23083 | G246: =B246-C246 -> -10158 | H246: =J245 -> 4484 | I246: =SUMIFS('Daily Transactions'!C:C,'Daily Transactions'!A:A,$A246,'Daily Transactions'!B:B,"Sales",'Daily Transactions'!D:D,"Cash") -> 520 | J246: =H246+I246-D246-E246 -> 1776 | L246: =SUMIFS('Daily Transactions'!C:C,'Daily Transactions'!A:A,$A246,'Daily Transactions'!B:B,"Cash Shortage",'Daily Transactions'!D:D,"Cash") -> 0
A247: =A246+1 -> 45901 | B247: =SUMIFS('Daily Transactions'!C:C,'Daily Transactions'!A:A,$A247,'Daily Transactions'!B:B,"Sales") -> 15214 | C247: =SUMIFS('Daily Transactions'!C:C,'Daily Transactions'!A:A,$A247,'Daily Transactions'!B:B,"<>Sales") -> 2679 | D247: =SUMIFS('Daily Transactions'!C:C,'Daily Transactions'!A:A,$A247,'Daily Transactions'!B:B,"<>Sales",'Daily Transactions'!D:D,"Cash") -> 45 | E247: =SUMIFS('Daily Transactions'!C:C,'Daily Transactions'!A:A,$A247,'Daily Transactions'!B:B,"<>Sales",'Daily Transactions'!D:D,"Bank_Cash") -> 20 | F247: =SUMIFS('Daily Transactions'!C:C,'Daily Transactions'!A:A,$A247,'Daily Transactions'!B:B,"<>Sales",'Daily Transactions'!D:D,"Bank") -> 2614 | G247: =B247-C247 -> 12535 | H247: =J246 -> 1776 | I247: =SUMIFS('Daily Transactions'!C:C,'Daily Transactions'!A:A,$A247,'Daily Transactions'!B:B,"Sales",'Daily Transactions'!D:D,"Cash") -> 2400 | J247: =H247+I247-D247-E247 -> 4111 | L247: =SUMIFS('Daily Transactions'!C:C,'Daily Transactions'!A:A,$A247,'Daily Transactions'!B:B,"Cash Shortage",'Daily Transactions'!D:D,"Cash") -> 0
A248: =A247+1 -> 45902 | B248: =SUMIFS('Daily Transactions'!C:C,'Daily Transactions'!A:A,$A248,'Daily Transactions'!B:B,"Sales") -> 12691 | C248: =SUMIFS('Daily Transactions'!C:C,'Daily Transactions'!A:A,$A248,'Daily Transactions'!B:B,"<>Sales") -> 5925 | D248: =SUMIFS('Daily Transactions'!C:C,'Daily Transactions'!A:A,$A248,'Daily Transactions'!B:B,"<>Sales",'Daily Transactions'!D:D,"Cash") -> 1220 | E248: =SUMIFS('Daily Transactions'!C:C,'Daily Transactions'!A:A,$A248,'Daily Transactions'!B:B,"<>Sales",'Daily Transactions'!D:D,"Bank_Cash") -> 175 | F248: =SUMIFS('Daily Transactions'!C:C,'Daily Transactions'!A:A,$A248,'Daily Transactions'!B:B,"<>Sales",'Daily Transactions'!D:D,"Bank") -> 4530 | G248: =B248-C248 -> 6766 | H248: =J247 -> 4111 | I248: =SUMIFS('Daily Transactions'!C:C,'Daily Transactions'!A:A,$A248,'Daily Transactions'!B:B,"Sales",'Daily Transactions'!D:D,"Cash") -> 3403 | J248: =H248+I248-D248-E248 -> 6119 | L248: =SUMIFS('Daily Transactions'!C:C,'Daily Transactions'!A:A,$A248,'Daily Transactions'!B:B,"Cash Shortage",'Daily Transactions'!D:D,"Cash") -> 0
A249: =A248+1 -> 45903 | B249: =SUMIFS('Daily Transactions'!C:C,'Daily Transactions'!A:A,$A249,'Daily Transactions'!B:B,"Sales") -> 18518 | C249: =SUMIFS('Daily Transactions'!C:C,'Daily Transactions'!A:A,$A249,'Daily Transactions'!B:B,"<>Sales") -> 6331 | D249: =SUMIFS('Daily Transactions'!C:C,'Daily Transactions'!A:A,$A249,'Daily Transactions'!B:B,"<>Sales",'Daily Transactions'!D:D,"Cash") -> 20 | E249: =SUMIFS('Daily Transactions'!C:C,'Daily Transactions'!A:A,$A249,'Daily Transactions'!B:B,"<>Sales",'Daily Transactions'!D:D,"Bank_Cash") -> 3165 | F249: =SUMIFS('Daily Transactions'!C:C,'Daily Transactions'!A:A,$A249,'Daily Transactions'!B:B,"<>Sales",'Daily Transactions'!D:D,"Bank") -> 3146 | G249: =B249-C249 -> 12187 | H249: =J248 -> 6119 | I249: =SUMIFS('Daily Transactions'!C:C,'Daily Transactions'!A:A,$A249,'Daily Transactions'!B:B,"Sales",'Daily Transactions'!D:D,"Cash") -> 900 | J249: =H249+I249-D249-E249 -> 3834 | L249: =SUMIFS('Daily Transactions'!C:C,'Daily Transactions'!A:A,$A249,'Daily Transactions'!B:B,"Cash Shortage",'Daily Transactions'!D:D,"Cash") -> 0
A250: =A249+1 -> 45904 | B250: =SUMIFS('Daily Transactions'!C:C,'Daily Transactions'!A:A,$A250,'Daily Transactions'!B:B,"Sales") -> 18476 | C250: =SUMIFS('Daily Transactions'!C:C,'Daily Transactions'!A:A,$A250,'Daily Transactions'!B:B,"<>Sales") -> 15560 | D250: =SUMIFS('Daily Transactions'!C:C,'Daily Transactions'!A:A,$A250,'Daily Transactions'!B:B,"<>Sales",'Daily Transactions'!D:D,"Cash") -> 255 | E250: =SUMIFS('Daily Transactions'!C:C,'Daily Transactions'!A:A,$A250,'Daily Transactions'!B:B,"<>Sales",'Daily Transactions'!D:D,"Bank_Cash") -> 2110 | F250: =SUMIFS('Daily Transactions'!C:C,'Daily Transactions'!A:A,$A250,'Daily Transactions'!B:B,"<>Sales",'Daily Transactions'!D:D,"Bank") -> 13195 | G250: =B250-C250 -> 2916 | H250: =J249 -> 3834 | I250: =SUMIFS('Daily Transactions'!C:C,'Daily Transactions'!A:A,$A250,'Daily Transactions'!B:B,"Sales",'Daily Transactions'!D:D,"Cash") -> 3178 | J250: =H250+I250-D250-E250 -> 4647 | L250: =SUMIFS('Daily Transactions'!C:C,'Daily Transactions'!A:A,$A250,'Daily Transactions'!B:B,"Cash Shortage",'Daily Transactions'!D:D,"Cash") -> 0
A251: =A250+1 -> 45905 | B251: =SUMIFS('Daily Transactions'!C:C,'Daily Transactions'!A:A,$A251,'Daily Transactions'!B:B,"Sales") -> 16930 | C251: =SUMIFS('Daily Transactions'!C:C,'Daily Transactions'!A:A,$A251,'Daily Transactions'!B:B,"<>Sales") -> 11364 | D251: =SUMIFS('Daily Transactions'!C:C,'Daily Transactions'!A:A,$A251,'Daily Transactions'!B:B,"<>Sales",'Daily Transactions'!D:D,"Cash") -> 220 | E251: =SUMIFS('Daily Transactions'!C:C,'Daily Transactions'!A:A,$A251,'Daily Transactions'!B:B,"<>Sales",'Daily Transactions'!D:D,"Bank_Cash") -> 3300 | F251: =SUMIFS('Daily Transactions'!C:C,'Daily Transactions'!A:A,$A251,'Daily Transactions'!B:B,"<>Sales",'Daily Transactions'!D:D,"Bank") -> 7844 | G251: =B251-C251 -> 5566 | H251: =J250 -> 4647 | I251: =SUMIFS('Daily Transactions'!C:C,'Daily Transactions'!A:A,$A251,'Daily Transactions'!B:B,"Sales",'Daily Transactions'!D:D,"Cash") -> 1940 | J251: =H251+I251-D251-E251 -> 3067 | L251: =SUMIFS('Daily Transactions'!C:C,'Daily Transactions'!A:A,$A251,'Daily Transactions'!B:B,"Cash Shortage",'Daily Transactions'!D:D,"Cash") -> 0
...

Sheet Daily Photo
K2: Item/Description | L2: Sales
C3: Expenses
B4: SUM of Amount | D4: Mode | K4: SUM of Amount | L4: f
B5: f | C5: Item/Description | D5: Bank | E5: Bank_Cash | F5: Cash | G5: (empty) | H5: Total Result | K5: Mode | L5: 45679 | M5: 45680 | N5: 45681 | O5: 45682 | P5: 45683 | Q5: 45684 | R5: 45685 | S5: 45686 | T5: 45687 | U5: 45688 | V5: 45689 | W5: 45690 | X5: 45691 | Y5: 45692 | Z5: 45693 | AA5: 45694 | AB5: 45695 | AC5: 45696 | AD5: 45697 | AE5: 45698 | AF5: 45699 | AG5: 45700 | AH5: 45701 | AI5: 45702 | AJ5: 45703 | AK5: 45704 | AL5: 45705 | AM5: 45706 | AN5: 45707 | AO5: 45708 | AP5: 45709 | AQ5: 45710 | AR5: 45711 | AS5: 45712 | AT5: 45713 | AU5: 45715 | AV5: 45716 | AW5: 45717 | AX5: 45718 | AY5: 45719 | AZ5: 45720 | BA5: 45721 | BB5: 45722 | BC5: 45723 | BD5: 45724 | BE5: 45725 | BF5: 45726 | BG5: 45727 | BH5: 45728 | BI5: 45729 | BJ5: 45730 | BK5: 45731 | BL5: 45732 | BM5: 45733 | BN5: 45734 | BO5: 45735 | BP5: 45736 | BQ5: 45737 | BR5: 45738 | BS5: 45739 | BT5: 45740 | BU5: 45741 | BV5: 45742 | BW5: 45743 | BX5: 45744 | BY5: 45745 | BZ5: 45746 | CA5: 45747 | CB5: 45748 | CC5: 45749 | CD5: 45750 | CE5: 45751 | CF5: 45752 | CG5: 45753 | CH5: 45754 | CI5: 45755 | CJ5: 45756 | CK5: 45757 | CL5: 45758 | CM5: 45759 | CN5: 45760 | CO5: 45761 | CP5: 45762 | CQ5: 45763 | CR5: 45764 | CS5: 45765 | CT5: 45766 | CU5: 45767 | CV5: 45768 | CW5: 45769 | CX5: 45770 | CY5: 45771 | CZ5: 45772 | DA5: 45773 | DB5: 45774 | DC5: 45775 | DD5: 45776 | DE5: 45777 | DF5: 45778 | DG5: 45779 | DH5: 45780 | DI5: 45781 | DJ5: 45782 | DK5: 45783 | DL5: 45784 | DM5: 45785 | DN5: 45786 | DO5: 45787 | DP5: 45788 | DQ5: 45789 | DR5: 45790 | DS5: 45791 | DT5: 45792 | DU5: 45793 | DV5: 45794 | DW5: 45795 | DX5: 45796 | DY5: 45797 | DZ5: 45798 | EA5: 45799 | EB5: 45800 | EC5: 45801 | ED5: 45802 | EE5: 45803 | EF5: 45804 | EG5: 45805 | EH5: 45806 | EI5: 45807 | EJ5: 45808 | EK5: 45809 | EL5: 45810 | EM5: 45811 | EN5: 45812 | EO5: 45813 | EP5: 45814 | EQ5: 45815 | ER5: 45816 | ES5: 45817 | ET5: 45818 | EU5: 45819 | EV5: 45820 | EW5: 45821 | EX5: 45822 | EY5: 45823 | EZ5: 45825 | FA5: 45826 | FB5: 45827 | FC5: 45828 | FD5: 45829 | FE5: 45830 | FF5: 45831 | FG5: 45832 | FH5: 45833 | FI5: 45834 | FJ5: 45835 | FK5: 45836 | FL5: 45837 | FM5: 45838 | FN5: 45839 | FO5: 45840 | FP5: 45841 | FQ5: 45842 | FR5: 45843 | FS5: 45844 | FT5: 45845 | FU5: 45846 | FV5: 45847 | FW5: 45848 | FX5: 45849 | FY5: 45850 | FZ5: 45851 | GA5: 45852 | GB5: 45853 | GC5: 45854 | GD5: 45855 | GE5: 45856 | GF5: 45857 | GG5: 45858 | GH5: 45859 | GI5: 45860 | GJ5: 45861 | GK5: 45862 | GL5: 45863 | GM5: 45864 | GN5: 45865 | GO5: 45866 | GP5: 45867 | GQ5: 45868 | GR5: 45869 | GS5: 45870 | GT5: 45871 | GU5: 45872 | GV5: 45873 | GW5: 45874 | GX5: 45875 | GY5: 45876 | GZ5: 45877 | HA5: 45878 | HB5: 45879 | HC5: 45880 | HD5: 45881 | HE5: 45882 | HF5: 45883 | HG5: 45884 | HH5: 45885 | HI5: 45886 | HJ5: 45887 | HK5: 45888 | HL5: 45889 | HM5: 45890 | HN5: 45891 | HO5: 45892 | HP5: 45893 | HQ5: 45894 | HR5: 45895 | HS5: 45896 | HT5: 45897 | HU5: 45898 | HV5: 45899 | HW5: 45900 | HX5: 45901 | HY5: 45902 | HZ5: 45903 | IA5: 45904 | IB5: 45905 | IC5: 45906 | ID5: 45907 | IE5: 45908 | IF5: 45909 | IG5: 45910 | IH5: 45911 | II5: 45912 | IJ5: 45913 | IK5: 45914 | IL5: 45915 | IM5: 45916 | IN5: 45917 | IO5: 45918 | IP5: 45919 | IQ5: 45920 | IR5: 45921 | IS5: 45922 | IT5: 45923 | IU5: 45924 | IV5: 45925 | IW5: 45926 | IX5: 45927 | IY5: 45928 | IZ5: 45929 | JA5: 45930 | JB5: 45931 | JC5: 45932 | JD5: 45933 | JE5: 45934 | JF5: 45935 | JG5: 45936 | JH5: 45937 | JI5: 45938 | JJ5: 45939 | JK5: 45940 | JL5: 45941 | JM5: 45942 | JN5: 45943 | JO5: 45944 | JP5: 45945 | JQ5: 45946 | JR5: 45947 | JS5: 45948 | JT5: 45949 | JU5: 45950 | JV5: 45951 | JW5: 45952 | JX5: 45953 | JY5: 45954 | JZ5: 45955 | KA5: 45956 | KB5: 45957 | KC5: 45958 | KD5: 45959 | KE5: 45960 | KF5: 45961 | KG5: 45962 | KH5: 45963 | KI5: 45964 | KJ5: 45965 | KK5: 45966 | KL5: 45967 | KM5: 45968 | KN5: 45969 | KO5: 45970 | KP5: 45971 | KQ5: 45972 | KR5: 45973 | KS5: 45974 | KT5: 45975 | KU5: 45976 | KV5: 45977 | KW5: 45978 | KX5: 45979 | KY5: 45980 | KZ5: 45981 | LA5: 45982 | LB5: 45983 | LC5: 45984 | LD5: 45985 | LE5: 45986 | LF5: 45987 | LG5: 45988 | LH5: Total Result
B6: 45679 | C6: Bakery | F6: 325 | H6: 325 | K6: Bank | ET6: 13949 | FE6: 3200 | LH6: 17149
C7: Chicken | D7: 5627 | H7: 5627 | K7: Card | L7: 1314 | N7: 250 | P7: 1620 | Q7: 1500 | R7: 1570 | T7: 530 | U7: 1395 | V7: 2285 | W7: 2510 | X7: 879 | Y7: 20 | AC7: 1910 | AD7: 531 | AF7: 480 | AG7: 380 | AH7: 180 | AI7: 750 | AJ7: 1685 | AK7: 1055 | AM7: 1835 | AN7: 410 | AP7: 1755 | AR7: 1350 | AS7: 765 | AU7: 2130 | AV7: 3690 | AW7: 760 | AY7: 654 | AZ7: 705 | BB7: 180 | BC7: 2755 | BD7: 449 | BE7: 2880 | BG7: 370 | BH7: 2475 | BI7: 475 | BJ7: 1088 | BL7: 1200 | BP7: 790 | BQ7: 1615 | BR7: 3315 | BS7: 1160 | BT7: 440 | BU7: 2870 | BV7: 155 | BW7: 860 | BX7: 1075 | CA7: 2090 | CB7: 400 | CE7: 790 | CF7: 1425 | CG7: 280 | CH7: 1970 | CJ7: 1370 | CK7: 1155 | CL7: 650 | CM7: 705 | CN7: 935 | CP7: 1080 | CQ7: 1270 | CT7: 1035 | CU7: 1330 | CV7: 380 | CW7: 1079 | CX7: 935 | CY7: 210 | CZ7: 1105 | DA7: 2320 | DB7: 1590 | DD7: 155 | DF7: 210 | DG7: 685 | DH7: 1460 | DJ7: 825 | DK7: 480 | DN7: 894 | DO7: 980 | DP7: 1445 | DR7: 435 | DS7: 1120 | DU7: 3920 | DW7: 1750 | DY7: 170 | DZ7: 1360 | EA7: 1055 | EB7: 225 | ED7: 260 | EE7: 80 | EG7: 230 | EH7: 1565 | EI7: 454 | EK7: 1650 | EL7: 915 | EM7: 320 | EN7: 230 | EO7: 430 | EP7: 1565 | EQ7: 520 | ER7: 410 | ES7: 799 | EU7: 2360 | EV7: 1165 | EX7: 1060 | FA7: 3010 | FB7: 1089 | FD7: 270 | FF7: 210 | FG7: 850 | FI7: 250 | FJ7: 1840 | FK7: 3263 | FM7: 1380 | FN7: 448 | FP7: 160 | FU7: 510 | FV7: 440 | FW7: 1110 | FX7: 765 | FY7: 965 | FZ7: 360 | GA7: 715 | GC7: 430 | GD7: 1135 | GF7: 300 | GG7: 1600 | GJ7: 250 | GK7: 1569 | GL7: 155 | GM7: 80 | GO7: 1139 | GP7: 175 | GQ7: 1475 | GS7: 120 | GT7: 200 | GU7: 610 | GX7: 430 | GY7: 325 | GZ7: 1020 | HB7: 1625 | HD7: 810 | HE7: 320 | HF7: 389 | HG7: 200 | HN7: 1570 | HP7: 665 | HV7: 735 | HW7: 1014 | IB7: 340 | IC7: 680 | ID7: 985 | IN7: 1170 | IP7: 1695 | IQ7: 260 | IR7: 625 | IU7: 210 | IW7: 440 | IX7: 1610 | IY7: 400 | IZ7: 1480 | JB7: 2280 | JC7: 2395 | JD7: 250 | JE7: 3030 | JF7: 380 | JH7: 230 | JI7: 1145 | JJ7: 210 | JK7: 1555 | JL7: 1660 | JM7: 2025 | JO7: 1310 | JP7: 585 | JQ7: 190 | JR7: 1255 | JS7: 620 | JT7: 1920 | JY7: 3964 | JZ7: 549 | KB7: 665 | KD7: 1750 | KF7: 2085 | KG7: 390 | KI7: 830 | KJ7: 710 | KM7: 5860 | KN7: 3915 | KO7: 1850 | KP7: 560 | KQ7: 360 | KS7: 130 | KT7: 12010 | KU7: 2725 | KW7: 720 | KX7: 210 | LB7: 710 | LC7: 2160 | LE7: 800 | LF7: 570 | LG7: 0 | LH7: 224770
C8: Dairy | D8: 1617 | F8: 855 | H8: 2472 | K8: Cash | L8: 4759 | M8: 2410 | N8: 3140 | O8: 5660 | P8: 3979 | Q8: 2540 | R8: 2415 | S8: 2710 | T8: 1700 | U8: 1840 | V8: 5015 | W8: 3340 | X8: 3065 | Y8: 2268 | Z8: 2390 | AA8: 3600 | AB8: 2160 | AC8: 5260 | AD8: 4599 | AE8: 3645 | AF8: 3210 | AG8: 4148 | AH8: 1800 | AI8: 1999 | AJ8: 5244 | AK8: 2335 | AL8: 2465 | AM8: 1215 | AN8: 2677 | AO8: 4700 | AP8: 1229 | AQ8: 3140 | AR8: 1460 | AS8: 2085 | AT8: 1240 | AU8: 4580 | AV8: 5440 | AW8: 4259 | AX8: 1870 | AY8: 2014 | AZ8: 3979 | BA8: 2234 | BB8: 1385 | BC8: 2745 | BD8: 4715 | BE8: 4743 | BF8: 1210 | BG8: 2620 | BH8: 4984 | BI8: 1360 | BJ8: 5235 | BK8: 2905 | BL8: 3548 | BM8: 1050 | BN8: 1805 | BO8: 1510 | BP8: 2080 | BQ8: 7710 | BR8: 7456 | BS8: 9034 | BT8: 4295 | BU8: 1500 | BV8: 4760 | BW8: 2640 | BX8: 1370 | BY8: 2695 | BZ8: 3074 | CA8: 3010 | CB8: 2684 | CC8: 2145 | CD8: 2320 | CE8: 2970 | CF8: 3444 | CG8: 2725 | CH8: 6595 | CI8: 1810 | CJ8: 5600 | CK8: 4635 | CL8: 1815 | CM8: 3210 | CN8: 3355 | CO8: 3600 | CP8: 2875 | CQ8: 2760 | CR8: 2440 | CS8: 2575 | CT8: 3970 | CU8: 6045 | CV8: 3440 | CW8: 2650 | CX8: 2610 | CY8: 1415 | CZ8: 3210 | DA8: 3760 | DB8: 3455 | DC8: 5320 | DD8: 4929 | DE8: 3140 | DF8: 2744 | DG8: 3895 | DH8: 2390 | DI8: 4645 | DJ8: 2934 | DK8: 1225 | DL8: 5790 | DM8: 800 | DN8: 2500 | DO8: 6055 | DP8: 1950 | DQ8: 3370 | DR8: 4000 | DS8: 3225 | DT8: 1060 | DU8: 580 | DV8: 5435 | DW8: 5350 | DX8: 4265 | DY8: 2110 | DZ8: 6335 | EA8: 1954 | EB8: 3139 | EC8: 2400 | ED8: 3565 | EE8: 1200 | EF8: 4119 | EG8: 2770 | EH8: 3295 | EI8: 1710 | EJ8: 2580 | EK8: 2169 | EL8: 2319 | EM8: 1140 | EN8: 3900 | EO8: 3230 | EP8: 2865 | EQ8: 1610 | ER8: 2381 | ES8: 1795 | ET8: 3179 | EU8: 1992 | EV8: 4055 | EW8: 1420 | EX8: 3725 | EY8: 6130 | EZ8: 3145 | FA8: 2362 | FB8: 5944 | FC8: 4245 | FD8: 5233 | FE8: 6085 | FF8: 3307 | FG8: 2760 | FH8: 3117 | FI8: 4255 | FJ8: 3435 | FK8: 3325 | FL8: 4070 | FM8: 390 | FN8: 3120 | FO8: 1660 | FP8: 3790 | FQ8: 3555 | FR8: 6324 | FS8: 2615 | FT8: 1870 | FU8: 2989 | FV8: 1895 | FW8: 1939 | FX8: 5103 | FY8: 4694 | FZ8: 7223 | GA8: 860 | GB8: 3053 | GC8: 5329 | GD8: 3555 | GE8: 735 | GF8: 2930 | GG8: 2960 | GH8: 680 | GI8: 3455 | GJ8: 1850 | GK8: 1050 | GL8: 1855 | GM8: 2360 | GN8: 3865 | GO8: 1720 | GP8: 940 | GQ8: 3789 | GR8: 1949 | GS8: 1880 | GT8: 2675 | GU8: 3559 | GV8: 4025 | GW8: 3035 | GX8: 1825 | GY8: 4147 | GZ8: 1180 | HA8: 2189 | HB8: 2960 | HC8: 910 | HD8: 1810 | HE8: 1310 | HF8: 3750 | HG8: 3070 | HH8: 2530 | HI8: 2105 | HJ8: 1650 | HK8: 380 | HL8: 750 | HM8: 2355 | HN8: 3160 | HO8: 5603 | HP8: 2560 | HQ8: 2913 | HR8: 1125 | HS8: 1310 | HT8: 2390 | HU8: 1935 | HV8: 1470 | HW8: 520 | HX8: 2400 | HY8: 3403 | HZ8: 900 | IA8: 3178 | IB8: 1940 | IC8: 3365 | ID8: 2655 | IE8: 406 | IF8: 1295 | IG8: 2839 | IH8: 3311 | II8: 3119 | IJ8: 1475 | IK8: 1550 | IL8: 1759 | IM8: 2790 | IN8: 2000 | IO8: 4180 | IP8: 5625 | IQ8: 2414 | IR8: 1825 | IS8: 1430 | IT8: 2820 | IU8: 1230 | IV8: 1610 | IW8: 1570 | IX8: 1910 | IY8: 1335 | IZ8: 340 | JA8: 3070 | JB8: 3920 | JC8: 2930 | JD8: 1485 | JE8: 1820 | JF8: 5655 | JG8: 1270 | JH8: 3550 | JI8: 3470 | JJ8: 2854 | JK8: 4545 | JL8: 1275 | JM8: 5165 | JN8: 1744 | JO8: 3670 | JP8: 3015 | JQ8: 5155 | JR8: 1415 | JS8: 2780 | JT8: 3390 | JU8: 3190 | JV8: 4740 | JW8: 4335 | JX8: 5059 | JY8: 3110 | JZ8: 5789 | KA8: 2424 | KB8: 4625 | KC8: 3699 | KD8: 6418 | KE8: 3435 | KF8: 3450 | KG8: 591 | KH8: 5673 | KI8: 1924 | KJ8: 7490 | KK8: 4975 | KL8: 5289 | KM8: 1960 | KN8: 3380 | KO8: 10912 | KP8: 1010 | KQ8: 4715 | KR8: 2880 | KS8: 3675 | KT8: 2765 | KU8: 3214 | KV8: 4490 | KW8: 1660 | KX8: 2128 | KY8: 3679 | KZ8: 2745 | LA8: 5385 | LB8: 10140 | LC8: 4690 | LD8: 3050 | LE8: 4280 | LF8: 2960 | LG8: 4570 | LH8: 959881
C9: Electric Work | F9: 60 | H9: 60 | K9: Due | U9: 210 | AO9: 180 | AP9: 230 | AT9: 100 | AV9: 260 | BS9: 530 | DO9: 1520 | DS9: 170 | EB9: 300 | ED9: 30 | EJ9: 389 | EO9: 260 | FO9: 840 | FW9: 200 | HW9: 910 | IE9: 580 | II9: 240 | IL9: 370 | IM9: 250 | IN9: 880 | IQ9: 310 | IR9: 470 | JD9: 1280 | JE9: 1670 | JG9: 680 | JH9: 320 | JI9: 250 | JL9: 575 | JN9: 670 | JR9: 446 | JV9: 1270 | KA9: 420 | KI9: 2700 | KN9: 1130 | KX9: 530 | LB9: 300 | LH9: 21470
C10: Electricity | D10: 19470 | H10: 19470 | K10: Online Sale | L10: 2183 | M10: 467 | N10: 1038 | O10: 3477 | P10: 1658 | Q10: 686 | R10: 602 | S10: 1772 | T10: 989 | U10: 2060 | V10: 1100 | W10: 4324 | X10: 789 | Y10: 1204 | Z10: 1122 | AA10: 1244 | AB10: 2298 | AC10: 2037 | AD10: 1852 | AE10: 1862 | AF10: 2768 | AG10: 1310 | AH10: 2826 | AI10: 4916 | AJ10: 658 | AK10: 1960 | AL10: 2580 | AM10: 1911 | AN10: 2114 | AO10: 840 | AP10: 1488 | AQ10: 3937 | AR10: 6166 | AS10: 3586 | AT10: 2744 | AU10: 3769 | AV10: 6323 | AW10: 8030 | AX10: 5284 | AY10: 4221 | AZ10: 6740 | BA10: 6039 | BB10: 5104 | BC10: 6175 | BD10: 11213 | BE10: 10707 | BF10: 4676 | BG10: 6204 | BH10: 9992 | BI10: 5898 | BJ10: 4039 | BK10: 503 | BL10: 3167 | BM10: 2598 | BN10: 1363 | BO10: 3235 | BP10: 1289 | BQ10: 3633 | BR10: 3118 | BS10: 216 | BT10: 1725 | BU10: 1241 | BV10: 4601 | BW10: 785 | BX10: 1992 | BY10: 1190 | BZ10: 1409 | CA10: 1992 | CB10: 4194 | CC10: 2832 | CD10: 2869 | CE10: 2785 | CF10: 3771 | CG10: 1407 | CH10: 2728 | CI10: 2358 | CJ10: 2057 | CK10: 4223 | CL10: 2949 | CM10: 3982 | CN10: 3352 | CO10: 2630 | CP10: 2142 | CQ10: 1457 | CR10: 1100 | CS10: 1973 | CT10: 4119 | CU10: 1437 | CV10: 1047 | CW10: 4056 | CX10: 1192 | CY10: 730 | CZ10: 5009 | DA10: 989 | DB10: 5317 | DC10: 1487 | DD10: 1358 | DE10: 4336 | DF10: 3655 | DG10: 1480 | DH10: 2810 | DI10: 4239 | DJ10: 566 | DK10: 2336 | DL10: 1799 | DM10: 1305 | DN10: 5379 | DO10: 1494 | DP10: 2198 | DQ10: 913 | DR10: 3658 | DS10: 989 | DT10: 2371 | DU10: 4511 | DV10: 2583 | DW10: 3005 | DX10: 2927 | DY10: 2372 | DZ10: 2989 | EA10: 1835 | EB10: 2632 | EC10: 1745 | ED10: 3544 | EE10: 1658 | EF10: 2003 | EG10: 1619 | EH10: 2498 | EI10: 948 | EJ10: 4005 | EK10: 2732 | EL10: 2777 | EM10: 2255 | EN10: 2773 | EO10: 1570 | EP10: 6497 | EQ10: 3497 | ER10: 3775 | ES10: 554 | ET10: 1362 | EU10: 4154 | EV10: 2820 | EW10: 1256 | EX10: 2258 | EY10: 2024 | EZ10: 2255 | FA10: 2635 | FB10: 1487 | FC10: 5065 | FD10: 2885 | FE10: 4126 | FF10: 2251 | FG10: 2154 | FH10: 2760 | FI10: 2663 | FJ10: 2940 | FK10: 3676 | FL10: 1735 | FM10: 2184 | FN10: 2635 | FO10: 3146 | FP10: 4401 | FQ10: 2949 | FR10: 2337 | FS10: 2431 | FT10: 1635 | FU10: 2376 | FV10: 5041 | FW10: 1288 | FX10: 3201 | FY10: 2787 | FZ10: 2350 | GA10: 1800 | GB10: 2472 | GC10: 1280 | GD10: 854 | GE10: 2422 | GF10: 4069 | GG10: 5151 | GH10: 728 | GI10: 1358 | GJ10: 1369 | GK10: 1440 | GL10: 2972 | GM10: 1964 | GN10: 2091 | GO10: 1487 | GP10: 751 | GQ10: 894 | GR10: 1949 | GS10: 1768 | GT10: 1911 | GU10: 3897 | GV10: 616 | GW10: 1099 | GX10: 1894 | GY10: 3267 | GZ10: 1153 | HA10: 1683 | HB10: 4189 | HD10: 1606 | HE10: 1055 | HG10: 643 | HH10: 2755 | HI10: 2657 | HJ10: 1521 | HK10: 1349 | HL10: 238 | HM10: 1755 | HN10: 2431 | HO10: 1561 | HP10: 2172 | HQ10: 1492 | HR10: 3158 | HS10: 2137 | HT10: 1305 | HU10: 993 | HW10: 2937 | HX10: 421 | HY10: 976 | HZ10: 226 | IA10: 8815 | IB10: 403 | IC10: 4052 | ID10: 2391 | IE10: 2338 | IF10: 657 | IG10: 2701 | IH10: 1192 | II10: 2496 | IJ10: 6188 | IK10: 1256 | IL10: 1936 | IM10: 1455 | IN10: 496 | IO10: 2542 | IP10: 3815 | IQ10: 2839 | IR10: 2586 | IS10: 1389 | IU10: 239 | IV10: 3215 | IW10: 3172 | IX10: 5547 | IY10: 1020 | IZ10: 1303 | JA10: 583 | JB10: 909 | JC10: 1834 | JD10: 1810 | JE10: 5257 | JF10: 2180 | JG10: 2332 | JH10: 2159 | JI10: 1133 | JJ10: 693 | JK10: 4596 | JL10: 1546 | JM10: 3318 | JN10: 2710 | JO10: 2342 | JP10: 5040 | JQ10: 1285 | JR10: 2820 | JS10: 920 | JT10: 170 | JU10: 1057 | JV10: 1851 | JW10: 1196 | JX10: 760 | JY10: 1644 | JZ10: 890 | KA10: 2838 | KB10: 1326 | KC10: 5125 | KD10: 1935 | KE10: 1120 | KF10: 1780 | KG10: 1551 | KH10: 755 | KI10: 1527 | KJ10: 3551 | KK10: 2241 | KL10: 1140 | KM10: 3225 | KN10: 2966 | KO10: 4265 | KP10: 1197 | KQ10: 2375 | KR10: 2148 | KS10: 1424 | KT10: 2173 | KU10: 1455 | KV10: 2969 | KW10: 676 | KX10: 3392 | KY10: 3818 | KZ10: 828 | LA10: 1786 | LB10: 2307 | LC10: 3187 | LD10: 1756 | LE10: 1931 | LF10: 1830 | LG10: 1655 | LH10: 759934
C11: Grocery | D11: 2801 | H11: 2801 | K11: UPI | L11: 240 | N11: 550 | O11: 3400 | P11: 320 | Q11: 614 | S11: 3160 | T11: 2930 | U11: 150 | V11: 180 | W11: 989 | X11: 990 | Y11: 479 | Z11: 10 | AA11: 670 | AC11: 149 | AD11: 925 | AE11: 1570 | AF11: 50 | AG11: 470 | AH11: 480 | AJ11: 1160 | AK11: 69 | AL11: 320 | AM11: 1425 | AN11: 1610 | AO11: 185 | AP11: 589 | AQ11: 1570 | AR11: 2270 | AS11: 880 | AT11: 350 | AU11: 449 | AV11: 810 | AW11: 4640 | AX11: 820 | AY11: 320 | BA11: 120 | BB11: 320 | BC11: 1393 | BD11: 2011 | BE11: 150 | BG11: 320 | BH11: 2650 | BJ11: 775 | BK11: 739 | BL11: 430 | BQ11: 1740 | BR11: 190 | BS11: 1580 | BT11: 500 | BU11: 420 | BW11: 789 | BX11: 40 | BY11: 1220 | BZ11: 420 | CA11: 1760 | CB11: 450 | CC11: 320 | CD11: 2220 | CE11: 290 | CF11: 480 | CG11: 1214 | CH11: 3595 | CJ11: 1260 | CK11: 500 | CL11: 420 | CM11: 689 | CN11: 80 | CO11: 1379 | CP11: 870 | CQ11: 2600 | CS11: 260 | CT11: 300 | CU11: 1684 | CV11: 980 | CW11: 990 | CX11: 520 | CZ11: 2310 | DA11: 230 | DB11: 540 | DC11: 350 | DD11: 150 | DF11: 100 | DH11: 1310 | DI11: 2525 | DJ11: 850 | DK11: 1810 | DL11: 60 | DN11: 750 | DO11: 3650 | DP11: 280 | DQ11: 420 | DR11: 290 | DS11: 5050 | DU11: 200 | DV11: 400 | DW11: 25 | DX11: 230 | DY11: 1519 | DZ11: 310 | EA11: 1000 | EC11: 170 | ED11: 70 | EE11: 430 | EF11: 525 | EG11: 2520 | EH11: 1720 | EI11: 2030 | EJ11: 580 | EK11: 1710 | EL11: 150 | EM11: 245 | EN11: 1534 | EO11: 1540 | EP11: 1740 | EQ11: 770 | ER11: 750 | ES11: 320 | ET11: 260 | EU11: 460 | EV11: 420 | EW11: 1790 | EX11: 910 | EY11: 20 | EZ11: 170 | FA11: 933 | FB11: 530 | FC11: 345 | FE11: 1571 | FF11: 1007 | FG11: 160 | FH11: 1143 | FI11: 595 | FJ11: 580 | FK11: 230 | FL11: 45 | FM11: 20 | FN11: 560 | FO11: 760 | FP11: 625 | FQ11: 920 | FR11: 730 | FS11: 1989 | FT11: 500 | FU11: 740 | FV11: 1395 | FW11: 405 | FX11: 260 | FY11: 230 | FZ11: 3159 | GA11: 170 | GB11: 60 | GC11: 95 | GD11: 500 | GE11: 30 | GF11: 150 | GG11: 1220 | GH11: 1245 | GI11: 1525 | GJ11: 1750 | GK11: 1055 | GM11: 190 | GN11: 220 | GP11: 200 | GQ11: 229 | GR11: 6325 | GS11: 1070 | GT11: 1610 | GU11: 350 | GV11: 310 | GW11: 599 | GX11: 380 | GY11: 1040 | GZ11: 20 | HA11: 110 | HB11: 815 | HD11: 740 | HF11: 315 | HG11: 1450 | HH11: 310 | HI11: 230 | HJ11: 360 | HL11: 320 | HN11: 1449 | HO11: 945 | HP11: 990 | HQ11: 4030 | HR11: 330 | HS11: 2210 | HU11: 860 | HV11: 930 | HW11: 550 | HZ11: 475 | IB11: 80 | IC11: 2950 | IE11: 996 | IH11: 620 | II11: 312 | IJ11: 80 | IK11: 909 | IL11: 690 | IM11: 3370 | IN11: 1590 | IO11: 1615 | IP11: 100 | IR11: 480 | IS11: 190 | IT11: 50 | IU11: 230 | IW11: 130 | IX11: 1075 | IZ11: 20 | JA11: 999 | JB11: 110 | JC11: 200 | JD11: 2924 | JF11: 2739 | JG11: 369 | JH11: 250 | JI11: 45 | JJ11: 1725 | JK11: 570 | JL11: 210 | JM11: 1000 | JN11: 980 | JO11: 840 | JP11: 220 | JQ11: 1315 | JR11: 460 | JS11: 1034 | JT11: 940 | JU11: 300 | JV11: 1958 | JW11: 650 | JX11: 420 | JY11: 1269 | JZ11: 850 | KB11: 30 | KD11: 90 | KE11: 100 | KF11: 279 | KG11: 1495 | KH11: 7715 | KI11: 500 | KJ11: 570 | KK11: 215 | KL11: 70 | KM11: 560 | KO11: 100 | KP11: 10 | KQ11: 420 | KS11: 20 | KT11: 1675 | KU11: 1800 | KV11: 1653 | KW11: 30 | KY11: 2087 | KZ11: 865 | LA11: 1115 | LB11: 1310 | LC11: 1334 | LD11: 810 | LE11: 870 | LF11: 1080 | LG11: 410 | LH11: 241925
C12: Kinners | F12: 0 | H12: 0 | K12: Wallet | L12: 19422 | M12: 10553 | N12: 19947 | O12: 26464 | P12: 33268 | Q12: 15670 | R12: 13162 | S12: 9785 | T12: 11791 | U12: 19723 | V12: 18947 | W12: 24773 | X12: 16745 | Y12: 9739 | Z12: 16846 | AA12: 16120 | AB12: 26031 | AC12: 17459 | AD12: 23463 | AE12: 10062 | AF12: 14439 | AG12: 14105 | AH12: 8789 | AI12: 28893 | AJ12: 14543 | AK12: 17085 | AL12: 8353 | AM12: 14788 | AN12: 11913 | AO12: 14834 | AP12: 22146 | AQ12: 15666 | AR12: 14098 | AS12: 11543 | AT12: 9793 | AU12: 16316 | AV12: 26223 | AW12: 32481 | AX12: 21971 | AY12: 15218 | AZ12: 16472 | BA12: 19400 | BB12: 17653 | BC12: 28766 | BD12: 23233 | BE12: 26853 | BF12: 14425 | BG12: 13289 | BH12: 20190 | BI12: 12539 | BJ12: 34924 | BK12: 20270 | BL12: 21202 | BM12: 12564 | BN12: 14284 | BO12: 11780 | BP12: 14847 | BQ12: 25241 | BR12: 21399 | BS12: 20324 | BT12: 9978 | BU12: 18648 | BV12: 14350 | BW12: 11730 | BX12: 17578 | BY12: 11875 | BZ12: 11538 | CA12: 19284 | CB12: 6869 | CC12: 11687 | CD12: 10313 | CE12: 17036 | CF12: 18895 | CG12: 19500 | CH12: 11194 | CI12: 11739 | CJ12: 13055 | CK12: 9400 | CL12: 18114 | CM12: 10788 | CN12: 20748 | CO12: 8364 | CP12: 12030 | CQ12: 9818 | CR12: 12833 | CS12: 15888 | CT12: 15463 | CU12: 23339 | CV12: 10210 | CW12: 6657 | CX12: 10840 | CY12: 9193 | CZ12: 20503 | DA12: 17575 | DB12: 14092 | DC12: 12895 | DD12: 11364 | DE12: 15392 | DF12: 21405 | DG12: 18194 | DH12: 25259 | DI12: 20117 | DJ12: 7842 | DK12: 12675 | DL12: 15728 | DM12: 11090 | DN12: 13726 | DO12: 13508 | DP12: 18547 | DQ12: 9270 | DR12: 9214 | DS12: 10134 | DT12: 12093 | DU12: 11024 | DV12: 10959 | DW12: 18583 | DX12: 5505 | DY12: 5944 | DZ12: 9834 | EA12: 14730 | EB12: 16944 | EC12: 17867 | ED12: 17353 | EE12: 10737 | EF12: 9552 | EG12: 12614 | EH12: 13478 | EI12: 18246 | EJ12: 24856 | EK12: 26482 | EL12: 10305 | EM12: 13548 | EN12: 12782 | EO12: 22272 | EP12: 15048 | EQ12: 16528 | ER12: 19753 | ES12: 11325 | EU12: 12040 | EV12: 8805 | EW12: 14970 | EX12: 15891 | EY12: 25162 | EZ12: 8659 | FA12: 10555 | FB12: 9953 | FC12: 17160 | FD12: 15189 | FE12: 19113 | FF12: 7155 | FG12: 19643 | FH12: 9159 | FI12: 11714 | FJ12: 13984 | FK12: 25036 | FL12: 20297 | FM12: 7783 | FN12: 16880 | FO12: 10789 | FP12: 9824 | FQ12: 18743 | FR12: 16530 | FS12: 16057 | FT12: 12849 | FU12: 15385 | FV12: 19584 | FW12: 9700 | FX12: 24257 | FY12: 27442 | FZ12: 12810 | GA12: 6980 | GB12: 9143 | GC12: 14075 | GD12: 6989 | GE12: 17544 | GF12: 12539 | GG12: 16799 | GH12: 3970 | GI12: 10240 | GJ12: 18449 | GK12: 9675 | GL12: 9723 | GM12: 16338 | GN12: 9744 | GO12: 8923 | GP12: 6129 | GQ12: 7769 | GR12: 8225 | GS12: 13624 | GT12: 13609 | GU12: 21006 | GV12: 5840 | GW12: 11235 | GX12: 6155 | GY12: 13908 | GZ12: 16319 | HA12: 12235 | HB12: 20058 | HC12: 9170 | HD12: 4280 | HE12: 8060 | HF12: 13543 | HG12: 17518 | HH12: 9920 | HI12: 14555 | HJ12: 5779 | HK12: 4540 | HL12: 9754 | HM12: 12001 | HN12: 17226 | HO12: 23279 | HP12: 25600 | HQ12: 7614 | HR12: 9094 | HS12: 7569 | HT12: 5360 | HU12: 13815 | HV12: 13068 | HW12: 10222 | HX12: 12393 | HY12: 8312 | HZ12: 15327 | IA12: 6483 | IB12: 14167 | IC12: 21950 | ID12: 12250 | IE12: 8585 | IF12: 14209 | IG12: 8094 | IH12: 12830 | II12: 17925 | IJ12: 13878 | IK12: 20974 | IL12: 9184 | IM12: 11350 | IN12: 14615 | IO12: 14422 | IP12: 20353 | IQ12: 24804 | IR12: 22260 | IS12: 7809 | IT12: 10397 | IU12: 7195 | IV12: 6692 | IW12: 10663 | IX12: 11083 | IY12: 12765 | IZ12: 6510 | JA12: 4865 | JB12: 15734 | JC12: 21014 | JD12: 17494 | JE12: 18734 | JF12: 30381 | JG12: 13224 | JH12: 17038 | JI12: 22368 | JJ12: 12820 | JK12: 17584 | JL12: 35087 | JM12: 30878 | JN12: 17028 | JO12: 17213 | JP12: 21072 | JQ12: 18709 | JR12: 13908 | JS12: 12800 | JT12: 18275 | JU12: 12600 | JV12: 25888 | JW12: 9149 | JX12: 10616 | JY12: 9144 | JZ12: 13660 | KA12: 10520 | KB12: 14257 | KC12: 16970 | KD12: 14811 | KE12: 13585 | KF12: 36525 | KG12: 24374 | KH12: 20846 | KI12: 12990 | KJ12: 18324 | KK12: 17139 | KL12: 21592 | KM12: 34948 | KN12: 18895 | KO12: 35353 | KP12: 12236 | KQ12: 14157 | KR12: 19844 | KS12: 15621 | KT12: 14868 | KU12: 25966 | KV12: 22459 | KW12: 14528 | KX12: 15003 | KY12: 21141 | KZ12: 17842 | LA12: 22764 | LB12: 31562 | LC12: 29572 | LD12: 16890 | LE12: 18892 | LF12: 23010 | LG12: 19394 | LH12: 4742636
C13: Petrol | F13: 400 | H13: 400 | K13: Zomato Pay | P13: 950 | Q13: 780 | R13: 585 | T13: 500 | Z13: 190 | AC13: 1280 | AD13: 715 | AF13: 629 | AG13: 2440 | AH13: 580 | AI13: 430 | AJ13: 2100 | AM13: 690 | AO13: 1009 | AP13: 220 | AQ13: 675 | AR13: 1079 | AS13: 2960 | AT13: 1250 | AU13: 2090 | AV13: 1848 | AW13: 1079 | AX13: 270 | AY13: 380 | BB13: 320 | BD13: 720 | BI13: 285 | BJ13: 130 | BM13: 150 | BS13: 844 | BW13: 150 | CC13: 430 | CE13: 360 | CH13: 690 | CI13: 550 | CJ13: 860 | CK13: 1048 | CN13: 800 | CR13: 990 | CS13: 310 | CU13: 830 | DD13: 1255 | DE13: 810 | DJ13: 400 | DK13: 535 | DL13: 450 | DM13: 460 | DQ13: 1165 | DV13: 500 | EE13: 529 | EI13: 950 | EL13: 820 | EQ13: 1660 | ET13: 830 | EU13: 1230 | EX13: 1945 | EY13: 1035 | EZ13: 555 | FB13: 570 | FC13: 1680 | FD13: 1200 | FE13: 1050 | FF13: 780 | FG13: 690 | FH13: 888 | FI13: 1099 | FM13: 390 | FO13: 818 | FR13: 1460 | FX13: 2680 | FZ13: 559 | GE13: 580 | GG13: 245 | GI13: 455 | GJ13: 399 | GL13: 785 | GM13: 750 | GQ13: 400 | GS13: 630 | HB13: 889 | HC13: 2736 | HF13: 1835 | HG13: 100 | HP13: 970 | HR13: 700 | HU13: 1040 | HZ13: 1590 | ID13: 540 | IF13: 2498 | II13: 2270 | IJ13: 399 | IL13: 450 | IM13: 1240 | IN13: 710 | IQ13: 570 | JD13: 640 | JG13: 710 | JK13: 210 | JL13: 570 | JO13: 645 | JP13: 850 | JT13: 530 | JX13: 1555 | JY13: 500 | KD13: 705 | KE13: 690 | KG13: 700 | KK13: 730 | KO13: 1595 | KS13: 882 | KU13: 442 | KV13: 504 | KY13: 1010 | LA13: 391 | LE13: 0 | LF13: 762 | LH13: 100591
C14: Stationary | F14: 100 | H14: 100 | K14: Total Result | L14: 27918 | M14: 13430 | N14: 24925 | O14: 39001 | P14: 41795 | Q14: 21790 | R14: 18334 | S14: 17427 | T14: 18440 | U14: 25378 | V14: 27527 | W14: 35936 | X14: 22468 | Y14: 13710 | Z14: 20558 | AA14: 21634 | AB14: 30489 | AC14: 28095 | AD14: 32085 | AE14: 17139 | AF14: 21576 | AG14: 22853 | AH14: 14655 | AI14: 36988 | AJ14: 25390 | AK14: 22504 | AL14: 13718 | AM14: 21864 | AN14: 18724 | AO14: 21748 | AP14: 27657 | AQ14: 24988 | AR14: 26423 | AS14: 21819 | AT14: 15477 | AU14: 29334 | AV14: 44594 | AW14: 51249 | AX14: 30215 | AY14: 22807 | AZ14: 27896 | BA14: 27793 | BB14: 24962 | BC14: 41834 | BD14: 42341 | BE14: 45333 | BF14: 20311 | BG14: 22803 | BH14: 40291 | BI14: 20557 | BJ14: 46191 | BK14: 24417 | BL14: 29547 | BM14: 16362 | BN14: 17452 | BO14: 16525 | BP14: 19006 | BQ14: 39939 | BR14: 35478 | BS14: 33688 | BT14: 16938 | BU14: 24679 | BV14: 23866 | BW14: 16954 | BX14: 22055 | BY14: 16980 | BZ14: 16441 | CA14: 28136 | CB14: 14597 | CC14: 17414 | CD14: 17722 | CE14: 24231 | CF14: 28015 | CG14: 25126 | CH14: 26772 | CI14: 16457 | CJ14: 24202 | CK14: 20961 | CL14: 23948 | CM14: 19374 | CN14: 29270 | CO14: 15973 | CP14: 18997 | CQ14: 17905 | CR14: 17363 | CS14: 21006 | CT14: 24887 | CU14: 34665 | CV14: 16057 | CW14: 15432 | CX14: 16097 | CY14: 11548 | CZ14: 32137 | DA14: 24874 | DB14: 24994 | DC14: 20052 | DD14: 19211 | DE14: 23678 | DF14: 28114 | DG14: 24254 | DH14: 33229 | DI14: 31526 | DJ14: 13417 | DK14: 19061 | DL14: 23827 | DM14: 13655 | DN14: 23249 | DO14: 27207 | DP14: 24420 | DQ14: 15138 | DR14: 17597 | DS14: 20688 | DT14: 15524 | DU14: 20235 | DV14: 19877 | DW14: 28713 | DX14: 12927 | DY14: 12115 | DZ14: 20828 | EA14: 20574 | EB14: 23240 | EC14: 22182 | ED14: 24822 | EE14: 14634 | EF14: 16199 | EG14: 19753 | EH14: 22556 | EI14: 24338 | EJ14: 32410 | EK14: 34743 | EL14: 17286 | EM14: 17508 | EN14: 21219 | EO14: 29302 | EP14: 27715 | EQ14: 24585 | ER14: 27069 | ES14: 14793 | ET14: 19580 | EU14: 22236 | EV14: 17265 | EW14: 19436 | EX14: 25789 | EY14: 34371 | EZ14: 14784 | FA14: 19495 | FB14: 19573 | FC14: 28495 | FD14: 24777 | FE14: 35145 | FF14: 14710 | FG14: 26257 | FH14: 17067 | FI14: 20576 | FJ14: 22779 | FK14: 35530 | FL14: 26147 | FM14: 12147 | FN14: 23643 | FO14: 18013 | FP14: 18800 | FQ14: 26167 | FR14: 27381 | FS14: 23092 | FT14: 16854 | FU14: 22000 | FV14: 28355 | FW14: 14642 | FX14: 36266 | FY14: 36118 | FZ14: 26461 | GA14: 10525 | GB14: 14728 | GC14: 21209 | GD14: 13033 | GE14: 21311 | GF14: 19988 | GG14: 27975 | GH14: 6623 | GI14: 17033 | GJ14: 24067 | GK14: 14789 | GL14: 15490 | GM14: 21682 | GN14: 15920 | GO14: 13269 | GP14: 8195 | GQ14: 14556 | GR14: 18448 | GS14: 19092 | GT14: 20005 | GU14: 29422 | GV14: 10791 | GW14: 15968 | GX14: 10684 | GY14: 22687 | GZ14: 19692 | HA14: 16217 | HB14: 30536 | HC14: 12816 | HD14: 9246 | HE14: 10745 | HF14: 19832 | HG14: 22981 | HH14: 15515 | HI14: 19547 | HJ14: 9310 | HK14: 6269 | HL14: 11062 | HM14: 16111 | HN14: 25836 | HO14: 31388 | HP14: 32957 | HQ14: 16049 | HR14: 14407 | HS14: 13226 | HT14: 9055 | HU14: 18643 | HV14: 16203 | HW14: 16153 | HX14: 15214 | HY14: 12691 | HZ14: 18518 | IA14: 18476 | IB14: 16930 | IC14: 32997 | ID14: 18821 | IE14: 12905 | IF14: 18659 | IG14: 13634 | IH14: 17953 | II14: 26362 | IJ14: 22020 | IK14: 24689 | IL14: 14389 | IM14: 20455 | IN14: 21461 | IO14: 22759 | IP14: 31588 | IQ14: 31197 | IR14: 28246 | IS14: 10818 | IT14: 13267 | IU14: 9104 | IV14: 11517 | IW14: 15975 | IX14: 21225 | IY14: 15520 | IZ14: 9653 | JA14: 9517 | JB14: 22953 | JC14: 28373 | JD14: 25883 | JE14: 30511 | JF14: 41335 | JG14: 18585 | JH14: 23547 | JI14: 28411 | JJ14: 18302 | JK14: 29060 | JL14: 40923 | JM14: 42386 | JN14: 23132 | JO14: 26020 | JP14: 30782 | JQ14: 26654 | JR14: 20304 | JS14: 18154 | JT14: 25225 | JU14: 17147 | JV14: 35707 | JW14: 15330 | JX14: 18410 | JY14: 19631 | JZ14: 21738 | KA14: 16202 | KB14: 20903 | KC14: 25794 | KD14: 25709 | KE14: 18930 | KF14: 44119 | KG14: 29101 | KH14: 34989 | KI14: 20471 | KJ14: 30645 | KK14: 25300 | KL14: 28091 | KM14: 46553 | KN14: 30286 | KO14: 54075 | KP14: 15013 | KQ14: 22027 | KR14: 24872 | KS14: 21752 | KT14: 33491 | KU14: 35602 | KV14: 32075 | KW14: 17614 | KX14: 21263 | KY14: 31735 | KZ14: 22280 | LA14: 31441 | LB14: 46329 | LC14: 40943 | LD14: 22506 | LE14: 26773 | LF14: 30212 | LG14: 26029 | LH14: 7068356
C15: Tea | F15: 129 | H15: 129
C16: Vegetables | D16: 469 | F16: 90 | H16: 559
B17: 22/01/2025 Result | D17: 29984 | F17: 1959 | H17: 31943
B18: 45680 | C18: Bakery | F18: 160 | H18: 160
C19: Chicken | D19: 6577 | H19: 6577
C20: Dairy | D20: 1486 | H20: 1486
C21: Grocery | D21: 2540 | H21: 2540
C22: Maintenance | F22: 350 | H22: 350
C23: Mutton | F23: 1480 | H23: 1480
C24: Tea | F24: 120 | H24: 120
C25: Vegetables | D25: 680 | H25: 680
B26: 23/01/2025 Result | D26: 11283 | F26: 2110 | H26: 13393
B27: 45681 | C27: Advance | E27: 10300 | H27: 10300
C28: Charcoal | D28: 840 | H28: 840
C29: Chicken | D29: 4243 | H29: 4243
C30: Dairy | D30: 1250 | H30: 1250
C31: Grocery | D31: 3967 | H31: 3967
C32: Kinners | F32: 40 | H32: 40
C33: Maintenance | F33: 350 | H33: 350
C34: Tea | F34: 100 | H34: 100
C35: Vegetables | D35: 580 | H35: 580
B36: 24/01/2025 Result | D36: 10880 | E36: 10300 | F36: 490 | H36: 21670
B37: 45682 | C37: Beverages | F37: 2964 | H37: 2964
C38: Chicken | D38: 1928 | H38: 1928
C39: Dairy | D39: 1296 | F39: 40 | H39: 1336
C40: Disposable | D40: 3095 | H40: 3095
C41: Electric Work | F41: 635 | H41: 635
C42: Gas | D42: 9100 | H42: 9100
C43: Grocery | D43: 3373 | H43: 3373
C44: Restaurant New Inventory | F44: 200 | H44: 200
C45: Tea | F45: 121 | H45: 121
C46: Vegetables | D46: 570 | H46: 570
B47: 25/01/2025 Result | D47: 19362 | F47: 3960 | H47: 23322
B48: 45683 | C48: Advance | E48: 2700 | H48: 2700
C49: Bakery | F49: 485 | H49: 485
C50: Beverages | F50: 40 | H50: 40
C51: Chicken | D51: 8385 | H51: 8385
C52: Dairy | D52: 2486 | F52: 1153 | H52: 3639
C53: Electric Work | F53: 185 | H53: 185
C54: Grocery | D54: 3000 | H54: 3000
C55: Momos | F55: 420 | H55: 420
C56: Tea | F56: 96 | H56: 96
C57: Vegetables | D57: 655 | H57: 655
B58: 26/01/2025 Result | D58: 14526 | E58: 2700 | F58: 2379 | H58: 19605
B59: 45684 | C59: Charcoal | D59: 840 | H59: 840
C60: Chicken | D60: 3997 | H60: 3997
C61: Civil Work | F61: 450 | H61: 450
C62: Dairy | D62: 1135 | F62: 650 | H62: 1785
C63: Kinners | F63: 30 | H63: 30
C64: Tea | F64: 125 | H64: 125
C65: Vegetables | D65: 526 | F65: 35 | H65: 561
B66: 27/01/2025 Result | D66: 6498 | F66: 1290 | H66: 7788
B67: 45685 | C67: Beverages | F67: 40 | H67: 40
C68: Chicken | D68: 4204 | H68: 4204
C69: Dairy | D69: 1533 | F69: 802 | H69: 2335
C70: Grocery | D70: 4708 | H70: 4708
C71: Kinners | F71: 23 | H71: 23
C72: Restaurant New Inventory | F72: 350 | H72: 350
C73: Tea | F73: 100 | H73: 100
C74: Vegetables | D74: 519 | H74: 519
B75: 28/01/2025 Result | D75: 10964 | F75: 1315 | H75: 12279
B76: 45686 | C76: Beverages | F76: 2400 | H76: 2400
C77: Charcoal | D77: 1680 | H77: 1680
C78: Dairy | D78: 201 | H78: 201
C79: Kinners | F79: 20 | H79: 20
C80: Petrol | E80: 100 | H80: 100
C81: Restaurant New Inventory | D81: 7428 | H81: 7428
C82: Tea | F82: 210 | H82: 210
C83: Vegetables | D83: 467 | F83: 30 | H83: 497
B84: 29/01/2025 Result | D84: 9776 | E84: 100 | F84: 2660 | H84: 12536
B85: 45687 | C85: Advance | E85: 2000 | H85: 2000
C86: Chicken | D86: 6170 | H86: 6170
C87: Dairy | D87: 848 | H87: 848
C88: Grocery | D88: 3181 | H88: 3181
C89: Police | D89: 8500 | H89: 8500
C90: Tea | F90: 100 | H90: 100
C91: Vegetables | D91: 495 | H91: 495
B92: 30/01/2025 Result | D92: 19194 | E92: 2000 | F92: 100 | H92: 21294
B93: 45688 | C93: Bakery | F93: 455 | H93: 455
C94: Chicken | D94: 5930 | H94: 5930
C95: Dairy | D95: 1741 | F95: 60 | H95: 1801
C96: Garbage Vehicle | E96: 1500 | H96: 1500
C97: Grocery | D97: 3216 | H97: 3216
C98: Kinners | F98: 35 | H98: 35
C99: Restaurant New Inventory | D99: 16800 | H99: 16800
C100: Tea | F100: 100 | H100: 100
C101: Vegetables | D101: 599 | F101: 90 | H101: 689
...

Sheet Payment
P2: Mode | Q2: Category
P3: Bank | Q3: <> Sales then its expenses
A4: Remarks/Vendors | B4: - all - | Q4: Expenses if any ( Remaning cash )
Q5: Can be sales and expenses
A6: SUM of Amount | B6: Month | Q6: Sales
A7: Item/Description | B7: 45962 | C7: 01-2025 | D7: 02-2025 | E7: 03-2025 | F7: 04-2025 | G7: 05-2025 | H7: 06-2025 | I7: 07-2025 | J7: 08-2025 | K7: 09-2025 | L7: 10-2025 | M7: 11-2025 | N7: 12-1899 | O7: (empty) | P7: Total Result | Q7: Sales | T7: Paid | U7: Unpaid
A8: Bakery | C8: 1425 | D8: 3337 | E8: 6765 | F8: 5915 | G8: 3465 | H8: 5530 | I8: 4505 | J8: 4220 | K8: 2550 | L8: 4375 | M8: 5900 | P8: 47987 | Q8: Sales | S8: ✅ Total Paid | T8: =SUMIFS('Daily Transactions'!C2:C8647, 'Daily Transactions'!G2:G8647,$T$7) -> 3723308.5
A9: Bank | D9: 6000 | J9: 3300 | P9: 9300 | Q9: Sales | S9: ❌ Total Unpaid | U9: =SUMIFS('Daily Transactions'!C2:C8648, 'Daily Transactions'!G2:G8648,$U$7) -> 923698
A10: Beverages | C10: 5444 | D10: 9270 | E10: 23908 | F10: 15083 | G10: 11580 | H10: 11295 | I10: 14103 | J10: 8730 | K10: 9305 | L10: 10502 | M10: 13742 | P10: 132962 | Q10: Sales | S10: 💰 Total Sales | T10: =SUMIFS('Daily Transactions'!C2:C100, 'Daily Transactions'!B2:B100, "Sales") -> 186006
A11: Cash Return to Cx | L11: 30 | M11: 670 | P11: 700 | Q11: Sales
A12: Cash Shortage | D12: 2395 | J12: 9413 | L12: 475 | P12: 12283
A13: Chamber Clean | E13: 1500 | H13: 1000 | I13: 1000 | J13: 1500 | K13: 1000 | P13: 6000
A14: Chapati | E14: 18980 | G14: 6000 | P14: 24980
A15: Charcoal | C15: 3360 | D15: 14280 | E15: 17640 | F15: 15120 | G15: 20160 | H15: 18480 | I15: 17880 | J15: 15450 | K15: 17100 | L15: 18000 | M15: 11580 | P15: 169050
A16: Chicken | C16: 47061 | D16: 92451 | E16: 154327 | F16: 100199 | G16: 104431 | H16: 115196 | I16: 94394 | J16: 70448 | K16: 62860 | L16: 124006 | M16: 141319 | P16: 1106692 | T16: Paid | U16: Unpaid | V16: Total
A17: Civil Work | C17: 450 | E17: 670 | H17: 5890 | J17: 310 | P17: 7320 | S17: Dairy | T17: =SUMIFS('Daily Transactions'!$C$2:$C$8647,'Daily Transactions'!$B$2:$B$8647,$S17 , 'Daily Transactions'!$G$2:$G$8647, $T$7) -> 212595 | U17: =SUMIFS('Daily Transactions'!$C$2:$C$8647,'Daily Transactions'!$B$2:$B$8647,$S17 , 'Daily Transactions'!$G$2:$G$8647, $U$7) -> 120155 | V17: =SUM(T17:U17) -> 332750
A18: Counter Cash | D18: 70 | E18: 530 | F18: 100 | J18: 260 | K18: 475 | P18: 1435 | S18: Chicken | T18: =SUMIFS('Daily Transactions'!$C$2:$C$8647,'Daily Transactions'!$B$2:$B$8647,$S18 , 'Daily Transactions'!$G$2:$G$8647, $T$7) -> 986818 | U18: =SUMIFS('Daily Transactions'!$C$2:$C$8647,'Daily Transactions'!$B$2:$B$8647,$S18 , 'Daily Transactions'!$G$2:$G$8647, $U$7) -> 119874 | V18: =SUM(T18:U18) -> 1106692
A19: Dairy | C19: 17153 | D19: 31454 | E19: 45870 | F19: 33052 | G19: 31744 | H19: 31140 | I19: 29351 | J19: 24800 | K19: 23654 | L19: 34057 | M19: 32560 | P19: 334835 | S19: Grocery | T19: =SUMIFS('Daily Transactions'!$C$2:$C$8647,'Daily Transactions'!$B$2:$B$8647,$S19 , 'Daily Transactions'!$G$2:$G$8647, $T$7) -> 550302.5 | U19: =SUMIFS('Daily Transactions'!$C$2:$C$8647,'Daily Transactions'!$B$2:$B$8647,$S19 , 'Daily Transactions'!$G$2:$G$8647, $U$7) -> 283013 | V19: =SUM(T19:U19) -> 833315.5
A20: Disposable | C20: 3095 | D20: 12865 | E20: 22350 | F20: 12655 | G20: 17830 | H20: 14775 | I20: 15905 | J20: 26715 | K20: 14625 | L20: 13075 | M20: 14398 | P20: 168288 | S20: Dairy | T20: =SUMIFS('Daily Transactions'!$C$2:$C$8647,'Daily Transactions'!$B$2:$B$8647,$S20 , 'Daily Transactions'!$G$2:$G$8647, $T$7) -> 212595 | U20: =SUMIFS('Daily Transactions'!$C$2:$C$8647,'Daily Transactions'!$B$2:$B$8647,$S20 , 'Daily Transactions'!$G$2:$G$8647, $U$7) -> 120155 | V20: =SUM(T20:U20) -> 332750
A21: Donation | E21: 4000 | F21: 1000 | J21: 3600 | L21: 70 | P21: 8670 | S21: Vegetables | T21: =SUMIFS('Daily Transactions'!$C$2:$C$8647,'Daily Transactions'!$B$2:$B$8647,$S21 , 'Daily Transactions'!$G$2:$G$8647, $T$7) -> 176749 | U21: =SUMIFS('Daily Transactions'!$C$2:$C$8647,'Daily Transactions'!$B$2:$B$8647,$S21 , 'Daily Transactions'!$G$2:$G$8647, $U$7) -> 56193 | V21: =SUM(T21:U21) -> 232942
A22: Egg | D22: 5196 | E22: 8509 | F22: 5160 | G22: 6895 | H22: 6463 | I22: 5179 | J22: 3719 | K22: 2612 | L22: 3511 | M22: 4570 | P22: 51814 | S22: Bakery | T22: =SUMIFS('Daily Transactions'!$C$2:$C$8647,'Daily Transactions'!$B$2:$B$8647,$S22 , 'Daily Transactions'!$G$2:$G$8647, $T$7) -> 47987 | U22: =SUMIFS('Daily Transactions'!$C$2:$C$8647,'Daily Transactions'!$B$2:$B$8647,$S22 , 'Daily Transactions'!$G$2:$G$8647, $U$7) -> 0 | V22: =SUM(T22:U22) -> 47987
A23: Electric Work | C23: 880 | D23: 30 | E23: 650 | F23: 60 | H23: 3850 | J23: 220 | K23: 870 | L23: 3040 | P23: 9600 | S23: Mutton | T23: =SUMIFS('Daily Transactions'!$C$2:$C$8647,'Daily Transactions'!$B$2:$B$8647,$S23 , 'Daily Transactions'!$G$2:$G$8647, $T$7) -> 195057 | U23: =SUMIFS('Daily Transactions'!$C$2:$C$8647,'Daily Transactions'!$B$2:$B$8647,$S23 , 'Daily Transactions'!$G$2:$G$8647, $U$7) -> 0 | V23: =SUM(T23:U23) -> 195057
A24: Electricity | C24: 19470 | D24: 21050 | E24: 21320 | F24: 19710 | G24: 23960 | H24: 20760 | I24: 19900 | J24: 19290 | K24: 20795 | L24: 25495 | M24: 115 | P24: 211865
A25: Garbage Vehicle | C25: 1500 | D25: 700 | E25: 2200 | F25: 2200 | G25: 2200 | H25: 2100 | I25: 2200 | J25: 2200 | K25: 2200 | L25: 2200 | M25: 700 | P25: 20400
A26: Gas | C26: 9100 | D26: 10920 | E26: 23660 | F26: 30180 | G26: 29920 | H26: 29580 | I26: 30204 | J26: 26320 | K26: 27081 | L26: 20917 | P26: 237882
A27: Grocery | C27: 26786 | D27: 76120 | E27: 109247 | F27: 73806 | G27: 74716 | H27: 69955 | I27: 72973 | J27: 93720.5 | K27: 73433 | L27: 88807 | M27: 94902 | P27: 854465.5
A28: Hotel Commision | E28: 330 | G28: 2014 | H28: 2750 | I28: 5422 | J28: 1500 | K28: 4023 | L28: 8024 | M28: 1900 | P28: 25963
A29: Internet | D29: 600 | E29: 600 | F29: 600 | G29: 600 | H29: 600 | I29: 600 | K29: 1200 | L29: 600 | P29: 5400
A30: Kinners | C30: 148 | D30: 534 | E30: 702 | F30: 422 | G30: 355 | H30: 156 | I30: 170 | J30: 410 | K30: 380 | L30: 785 | M30: 503 | P30: 4565
A31: Maintenance | C31: 700 | D31: 4195 | E31: 2390 | F31: 3685 | G31: 13710 | H31: 10590 | I31: 5290 | J31: 19600 | K31: 12420 | L31: 33745 | M31: 43502 | P31: 149827
A32: Medical | D32: 20 | E32: 700 | H32: 115 | I32: 90 | J32: 560 | K32: 50 | L32: 1440 | M32: 1530 | P32: 4505
A33: Momos | C33: 420 | D33: 630 | E33: 630 | F33: 420 | G33: 630 | H33: 910 | I33: 420 | J33: 420 | K33: 245 | L33: 1400 | M33: 840 | P33: 6965
A34: Mutton | B34: 1850 | C34: 1480 | D34: 11560 | E34: 82847 | F34: 8950 | G34: 15800 | H34: 10420 | I34: 11280 | J34: 13450 | K34: 11280 | L34: 15040 | M34: 11100 | P34: 195057
A35: Petrol | C35: 500 | D35: 3725 | E35: 3765 | F35: 3265 | G35: 4805 | H35: 6720 | I35: 2020 | J35: 2230 | K35: 3190 | L35: 2460 | M35: 4670 | P35: 37350
A36: Plumbing Work | E36: 215 | F36: 1550 | J36: 355 | K36: 1075 | L36: 90 | M36: 20 | P36: 3305
A37: Police | C37: 8500 | D37: 2000 | E37: 19000 | F37: 2000 | G37: 19000 | H37: 2000 | P37: 52500
A38: Restaurant New Inventory | C38: 24778 | D38: 600 | E38: 3060 | F38: 1930 | G38: 1550 | H38: 10614 | I38: 13250 | J38: 1400 | K38: 33820 | L38: 9559 | M38: 4100 | P38: 104661
A39: Staff | L39: 2600 | P39: 2600
A40: Staff | L40: 2950 | P40: 2950
A41: Staff Edi | E41: 7500 | P41: 7500
A42: Stationary | C42: 100 | D42: 20 | E42: 100 | F42: 200 | G42: 130 | H42: 200 | I42: 2370 | J42: 170 | K42: 100 | L42: 6455 | M42: 545 | P42: 10390
A43: Tea | C43: 1201 | D43: 3168 | E43: 3968 | F43: 4212 | G43: 4320 | H43: 4576 | I43: 2523 | J43: 460 | K43: 3205 | L43: 3588 | M43: 1550 | P43: 32771
A44: Vegetables | C44: 5805 | D44: 25567 | E44: 24549 | F44: 16819 | G44: 16331 | H44: 18619 | I44: 12268 | J44: 13679 | K44: 12865 | L44: 45279 | M44: 42701 | P44: 234482
A45: Water 20 Ltrs | E45: 2040 | F45: 2610 | G45: 2220 | H45: 2100 | I45: 1950 | J45: 140 | L45: 1740 | P45: 12800
A46: Water Tanker | E46: 1200 | J46: 2200 | K46: 2000 | L46: 800 | P46: 6200
A47: (empty)
A48: Total Result | B48: 1850 | C48: 179356 | D48: 338757 | E48: 615722 | F48: 360903 | G48: 414366 | H48: 406384 | I48: 365247 | J48: 370789.5 | K48: 344413 | L48: 485115 | M48: 433417 | P48: 4316319.5
A53: Item/Description | B53: Advance
A55: SUM of Amount | B55: Month
A56: Remarks/Vendors | B56: 01-2025 | C56: 02-2025 | D56: 03-2025 | E56: 04-2025 | F56: 05-2025 | G56: 06-2025 | H56: 07-2025 | I56: 08-2025 | J56: 09-2025 | K56: 10-2025 | L56: 11-2025 | M56: Total Result
A57: Abid | I57: 1200 | M57: 1200
A58: Abid cleiner | L58: 1250 | M58: 1250
A59: Abid Salary | G59: 1200 | H59: 1200 | K59: 1250 | M59: 3650
A60: Abrar Advance | K60: 500 | M60: 500
A61: Aditya | I61: 1000 | M61: 1000 | P61: Column 1
A62: Advance | L62: 2000 | M62: 2000
A63: Advance sandeeop | K63: 500 | M63: 500
A64: Akheel | I64: 3000 | M64: 3000
A65: Akhil | K65: 1500 | M65: 1500
A66: Akhil Salary | D66: 150 | M66: 150
A67: Alam Bhai | D67: 4000 | M67: 4000
A68: Ayaz | K68: 1000 | M68: 1000
A69: ayub | C69: 500 | M69: 500
A70: Ayub Bhai | D70: 1500 | M70: 1500
A71: ayub tava person | D71: 500 | M71: 500
A72: Danish | C72: 3500 | H72: 3000 | M72: 6500
A73: Danish advance | L73: 1000 | M73: 1000
A74: Dinesh Advance | L74: 100 | M74: 100
A75: Disposable payment Umesh sir | B75: 2700 | M75: 2700
A76: Ibrar | H76: 1000 | I76: 3000 | J76: 500 | K76: 500 | M76: 5000
A77: Ibrar Advance | I77: 1000 | J77: 500 | M77: 1500
A78: Imraan | I78: 1000 | J78: 500 | M78: 1500
A79: Imran | H79: 2000 | J79: 7000 | M79: 9000
A80: Irfan | C80: 1000 | M80: 1000
A81: Irman | I81: 349 | M81: 349
A82: Juber | E82: 2000 | F82: 6000 | M82: 8000
A83: Juber | D83: 5000 | M83: 5000
A84: Junaid | E84: 516 | M84: 516
A85: kanaya | C85: 2300 | M85: 2300
A86: Khenya | D86: 4700 | E86: 1000 | G86: 7200 | M86: 12900
A87: Laxmi Bai | D87: 1000 | I87: 6000 | M87: 7000
A88: Laxmi Bai Salary | C88: 3000 | E88: 5000 | F88: 6000 | G88: 6000 | H88: 6000 | M88: 26000
A89: Laxmi Salary | K89: 6000 | M89: 6000
A90: Luxmi By | L90: 6000 | M90: 6000
A91: Mahesh | C91: 200 | D91: 1000 | M91: 1200
A92: Manohar advance | K92: 1000 | L92: 3000 | M92: 4000
A93: Mausi | D93: 6000 | M93: 6000
A94: Mujeeb | C94: 1000 | M94: 1000
A95: mujib indian helper | D95: 500 | M95: 500
A96: Mukesh | H96: 3000 | M96: 3000
A97: Mukesh Kumar | F97: 200 | G97: 5100 | H97: 200 | M97: 5500
A98: Musatafa | K98: 2240 | M98: 2240
A99: nafees | C99: 200 | M99: 200
A100: Naseem Bhai Salary | B100: 2000 | M100: 2000
A101: Nasim | L101: 600 | M101: 600
A102: Nasim advance | J102: 605 | L102: 120 | M102: 725
A103: Nasim Bhai | D103: 600 | F103: 600 | H103: 1300 | K103: 5600 | M103: 8100
A104: Porter For Golden Chicken | G104: 170 | M104: 170
A105: Prakash | H105: 1500 | I105: 500 | M105: 2000
A106: Prakash Salary | H106: 1000 | M106: 1000
...

Sheet Categories
D1: Item/Description | E1: Grouping | F1: Type | G1: ID
D2: Advance | E2: Salary | F2: Expense
D3: Bakery | E3: Grocery | F3: Expense | Q3: Mode
D4: Beverages | E4: Grocery | F4: Expense | L4: Counter Cash | Q4: Bank
D5: Charcoal | E5: Inventory | F5: Expense | L5: Cash Shortage | Q5: Wallet
D6: Chicken | E6: Inventory | F6: Expense | L6: Bank | Q6: Cash
D7: Civil Work | E7: Maintance | F7: Expense | L7: Water Tanker | Q7: Online Sale
D8: Dairy | E8: Inventory | F8: Expense | L8: Chamber Clean | Q8: Card | T8: Bank
D9: Disposable | E9: Inventory | F9: Expense | L9: Chapati | Q9: UPI | T9: Wallet
D10: Donation | E10: Maintance | F10: Expense | L10: Staff Edi | Q10: Bank_Cash | T10: Cash
D11: Egg | E11: Grocery | F11: Expense | Q11: Zomato Pay | T11: Online Sale
D12: Electric Work | E12: Maintance | F12: Expense | Q12: Due | T12: Card
D13: Electricity | E13: Fixed Maintance | F13: Expense | T13: UPI
D14: Garbage Vehicle | E14: Fixed Maintance | F14: Expense | T14: Bank_Cash
D15: Gas | E15: Fixed Maintance | F15: Expense | T15: Zomato Pay
D16: Grocery | E16: Inventory | F16: Expense | T16: Due
D17: Internet | E17: Fixed Maintance | F17: Expense
D18: Kinners | E18: Maintance | F18: Expense
D19: Maintance | E19: Maintance | F19: Expense
D20: Medical | E20: Staff Expenses | F20: Expense
D21: Momos | E21: Inventory | F21: Expense
D22: Mutton | E22: Inventory | F22: Expense
D23: Petrol | E23: Bike Maintance | F23: Expense
D24: Plumbing Work | E24: Maintance | F24: Expense
D25: Police | E25: Fixed Maintance | F25: Expense
D26: Restaurant New Inventory | E26: New Inventory | F26: Expense
D27: Sales | E27: Sales | F27: Income
D28: Stationary | E28: Inventory | F28: Expense
... D42: Inventory | E42: Inventory | F42: Expense
